Workbook
Name Receita: #REF!

Sheet JAN
A1: 4 | B1: Lançamento de Compras e Gastos Casa
I3: Previsto | K3: Real | N3: Diferença
H4: Renda 1 | I4: =2398+K66 -> 7488 | J4: 1940 | K4: =1940+J66 -> 2230 | N4: =I4-K4 -> 5258
H5: Renda 2 | I5: =2500+Q67 -> 2500 | J5: 2500 | K5: 2500 | N5: =I5-J5 -> 0
B6: Despesas Mensais | H6: Renda Total | I6: =+I4+I5 -> 9988 | K6: =+K4+K5 -> 4730 | N6: =+I6-K6 -> 5258
H7: Despesas | I7: =+SUM(I22,O24,I29,O34,I38,O42,I51,O52,I57,O59,I66,O67,) -> 19252.3 | K7: =+SUM(J22,J29,J38,J51,J57,J66,P67,P59,P52,P42,P34,P24,) -> 3651 | N7: =+I7-K7 -> 15601.3
B8: Data | C8: Despesa | D8: Valor | E8: Área | H8: Saldo | I8: =+I6-I7 -> -9264.3 | K8: =+K6-K7 -> 1079 | N8: =I8-K8 -> -10343.3
D9: =SUM(D10:D114) -> 0
B10: 45658
B11: 45659 | H11: MORADIA | I11: Previsto | J11: Real | K11: Diferença | N11: TRANSPORTE | O11: Previsto | P11: Real | Q11: Diferença
B12: 45660 | G12: 1 | H12: Caixa de Emergência | I12: 150 | J12: =SUMIF(E$10:E$146,"1",D$10:D$146) -> 0 | K12: =+I12-J12 -> 150 | M12: 40 | N12: Uber 99 | O12: 58 | P12: 45 | Q12: =+O12-P12 -> 13
B13: 45661 | G13: 2 | H13: Inevitavelmento fixo | I13: =J66 -> 290 | J13: =SUMIF(E$10:E$146,"2",D$10:D$146) -> 0 | K13: =+I13-J13 -> 290 | M13: 41 | N13: Uber | O13: 68 | P13: =SUMIF(E$10:E$146,"41",D$10:D$146) -> 0 | Q13: =+O13-P13 -> 68
B14: 45662 | G14: 3 | H14: Das Jhenis | I14: 250 | J14: =SUMIF(E$10:E$146,"3",D$10:D$146) -> 0 | K14: =+I14-J14 -> 250 | M14: 42 | N14: Transporte Público | O14: 440 | P14: 0 | Q14: =+O14-P14 -> 440
B15: 45663 | G15: 4 | H15: Cartao Jhenismara | I15: 1200 | J15: 1400 | K15: =+I15-J15 -> -200 | M15: 43 | N15: Transporte Trabalho J | O15: 240 | P15: 143 | Q15: =+O15-P15 -> 97
B16: 45664 | G16: 5 | H16: Emergência Casa | I16: 120 | J16: =SUMIF(E$10:E$146,"5",D$10:D$146) -> 0 | K16: =+I16-J16 -> 120 | M16: 44 | N16: Transporte Trabalho M | O16: 110 | P16: 240 | Q16: =+O16-P16 -> -130
B17: 45665 | G17: 6 | H17: Energia | I17: 150 | J17: 150 | K17: =+I17-J17 -> 0 | M17: 45 | N17: Caixa Carro J | O17: 0 | P17: =SUMIF(E$10:E$146,"45",D$10:D$146) -> 0 | Q17: =+O17-P17 -> 0
B18: 45666 | G18: 7 | H18: Água | I18: 77 | J18: 77 | K18: =+I18-J18 -> 0 | M18: 46 | N18: Caixa Carro M | O18: 0 | P18: =SUMIF(E$10:E$146,"46",D$10:D$146) -> 0 | Q18: =+O18-P18 -> 0
B19: 45667 | G19: 8 | H19: Gás | I19: 55 | J19: 55 | K19: =+I19-J19 -> 0 | M19: 47 | N19: Contas Extras | O19: 0 | P19: =SUMIF(E$10:E$146,"47",D$10:D$146) -> 0 | Q19: =+O19-P19 -> 0
B20: 45668 | G20: 9 | H20: Cartao (Matheus) | I20: 175 | J20: 175 | K20: =+I20-J20 -> 0 | M20: 48 | O20: 0 | P20: =SUMIF(E$10:E$146,"48",D$10:D$146) -> 0 | Q20: =+O20-P20 -> 0
B21: 45669 | G21: 10 | H21: Outrs Dispesas | I21: 0 | J21: =SUMIF(E$10:E$146,"10",D$10:D$146) -> 0 | K21: =+I21-J21 -> 0 | M21: 49 | O21: 0 | P21: 0 | Q21: =+O21-P21 -> 0
B22: 45670 | H22: TOTAL | I22: =SUM(I12:I21) -> 2467 | J22: =SUM(J12:J21) -> 1857 | K22: =+I22-J22 -> 610 | M22: 50 | O22: 0 | P22: 0 | Q22: =+O22-P22 -> 0
B23: 45671 | M23: 51 | O23: 0 | P23: =SUMIF(E$10:E$146,"51",D$10:D$146) -> 0 | Q23: =+O23-P23 -> 0
B24: 45672 | H24: ALIMENTAÇÃO | I24: Previsto | J24: Real | K24: Diferença | N24: TOTAL | O24: =SUM(O12:O23) -> 916 | P24: =SUM(P12:P23) -> 428 | Q24: =+O24-P24 -> 488
B25: 45673 | G25: 11 | H25: Supermercado | I25: 450 | J25: 450 | K25: =+I25-J25 -> 0
B26: 45674 | G26: 12 | H26: Restaurante | I26: 140 | J26: 140 | K26: =+I26-J26 -> 0 | N26: EDUCAÇÃO | O26: Previsto | P26: Real | Q26: Diferença
B27: 45675 | G27: 13 | H27: Café \ Almoço | I27: 100 | J27: 250 | K27: =+I27-J27 -> -150 | M27: 52 | N27: Mensalidades | O27: 0 | P27: =SUMIF(E$10:E$146,"52",D$10:D$146) -> 0 | Q27: =+O27-P27 -> 0
B28: 45676 | G28: 14 | H28: Pedidos IFood | I28: 140 | J28: =SUMIF(E$10:E$146,"14",D$10:D$146) -> 0 | K28: =+I28-J28 -> 140 | M28: 53 | N28: Idiomas | O28: 0 | P28: =SUMIF(E$10:E$146,"53",D$10:D$146) -> 0 | Q28: =+O28-P28 -> 0
B29: 45677 | H29: TOTAL | I29: =SUM(I25:I28) -> 830 | J29: =SUM(J25:J28) -> 840 | K29: =+I29-J29 -> -10 | M29: 54 | N29: CNH [Matheus] | O29: 0 | P29: =SUMIF(E$10:E$146,"54",D$10:D$146) -> 0 | Q29: =+O29-P29 -> 0
B30: 45678 | M30: 55 | N30: Cursos | O30: 140 | P30: =SUMIF(E$10:E$146,"55",D$10:D$146) -> 0 | Q30: =+O30-P30 -> 140
B31: 45679 | H31: COMUNICAÇÃO | I31: Previsto | J31: Real | K31: Diferença | M31: 56 | N31: Livros | O31: 0 | P31: =SUMIF(E$10:E$146,"56",D$10:D$146) -> 0 | Q31: =+O31-P31 -> 0
B32: 45680 | G32: 15 | H32: Celular | I32: 45 | J32: 45 | K32: =+I32-J32 -> 0 | M32: 57 | N32: Faculdade [Jhenis] | O32: 0 | P32: =SUMIF(E$10:E$146,"57",D$10:D$146) -> 0 | Q32: =+O32-P32 -> 0
B33: 45681 | G33: 16 | H33: Internet | I33: 89 | J33: 89 | K33: =+I33-J33 -> 0 | M33: 58 | N33: Outros Educação | O33: 0 | P33: =SUMIF(E$10:E$146,"58",D$10:D$146) -> 0 | Q33: =+O33-P33 -> 0
B34: 45682 | G34: 17 | H34: Streaming | I34: 24 | J34: 24 | K34: =+I34-J34 -> 0 | N34: TOTAL | O34: =SUM(O27:O33) -> 140 | P34: =SUM(P27:P33) -> 0 | Q34: =+O34-P34 -> 140
B35: 45683 | G35: 18 | H35: Netflix | I35: 21.9 | J35: 22 | K35: =+I35-J35 -> -0.1
B36: 45684 | G36: 19 | H36: Amazon | I36: 10.9 | J36: 11 | K36: =+I36-J36 -> -0.1 | N36: LAZER | O36: Previsto | P36: Real | Q36: Diferença
B37: 45685 | G37: 20 | H37: Max Plus | I37: 34.5 | J37: 45 | K37: =+I37-J37 -> -10.5 | M37: 60 | N37: Cinema | O37: 450 | P37: =SUMIF(E$10:E$146,"60",D$10:D$146) -> 0 | Q37: =+O37-P37 -> 450
B38: 45686 | H38: TOTAL | I38: =SUM(I32:I37) -> 225.3 | J38: =SUM(J32:J37) -> 236 | K38: =+I38-J38 -> -10.7 | M38: 61 | N38: Esportes | O38: 0 | P38: =SUMIF(E$10:E$146,"61",D$10:D$146) -> 0 | Q38: =+O38-P38 -> 0
B39: 45687 | M39: 62 | N39: Shows [Consertos] | O39: 120 | P39: =SUMIF(E$10:E$146,"62",D$10:D$146) -> 0 | Q39: =+O39-P39 -> 120
B40: 45688 | H40: SAÚDE E CUIDADOS | I40: Previsto | J40: Real | K40: Diferença | M40: 63 | N40: Viagens [Férias] | O40: 148 | P40: =SUMIF(E$10:E$146,"63",D$10:D$146) -> 0 | Q40: =+O40-P40 -> 148
G41: 21 | H41: Academia | I41: 120 | J41: =SUMIF(E$10:E$146,"21",D$10:D$146) -> 0 | K41: =+I41-J41 -> 120 | M41: 64 | N41: Outros Lazer | O41: 60 | P41: =SUMIF(E$10:E$146,"64",D$10:D$146) -> 0 | Q41: =+O41-P41 -> 60
G42: 22 | H42: Emergencia Médica | I42: 120 | J42: =SUMIF(E$10:E$146,"22",D$10:D$146) -> 0 | K42: =+I42-J42 -> 120 | N42: TOTAL | O42: =SUM(O37:O41) -> 778 | P42: =SUM(P37:P41) -> 0 | Q42: =+O42-P42 -> 778
G43: 23 | H43: Emergência Dentista | I43: 100 | J43: =SUMIF(E$10:E$146,"23",D$10:D$146) -> 0 | K43: =+I43-J43 -> 100
G44: 24 | H44: Cosméticos | I44: 100 | J44: =SUMIF(E$10:E$146,"24",D$10:D$146) -> 0 | K44: =+I44-J44 -> 100 | N44: Necessidades Da Casa | O44: Previsto | P44: Real | Q44: Diferença
G45: 25 | H45: Dentista | I45: 150 | J45: =SUMIF(E$10:E$146,"25",D$10:D$146) -> 0 | K45: =+I45-J45 -> 150 | M45: 70 | N45: Cama | O45: 0 | P45: =SUMIF(E$10:E$146,"70",D$10:D$146) -> 0 | Q45: =+O45-P45 -> 0
G46: 26 | H46: Exames médicos | I46: 0 | J46: =SUMIF(E$10:E$146,"26",D$10:D$146) -> 0 | K46: =+I46-J46 -> 0 | M46: 71 | N46: Consertos [ Futuros | O46: 0 | P46: =SUMIF(E$10:E$146,"71",D$10:D$146) -> 0 | Q46: =+O46-P46 -> 0
G47: 27 | H47: Farmácia | I47: 89 | J47: =SUMIF(E$10:E$146,"27",D$10:D$146) -> 0 | K47: =+I47-J47 -> 89 | M47: 72 | N47: Geladeira | O47: 0 | P47: =SUMIF(E$10:E$146,"72",D$10:D$146) -> 0 | Q47: =+O47-P47 -> 0
G48: 28 | H48: Médicos particular | I48: 0 | J48: =SUMIF(E$10:E$146,"28",D$10:D$146) -> 0 | K48: =+I48-J48 -> 0 | M48: 73 | N48: Lava e seca | O48: 0 | P48: =SUMIF(E$10:E$146,"73",D$10:D$146) -> 0 | Q48: =+O48-P48 -> 0
G49: 29 | H49: Suplementos | I49: 0 | J49: =SUMIF(E$10:E$146,"29",D$10:D$146) -> 0 | K49: =+I49-J49 -> 0 | M49: 74 | N49: Lavanderia louça | O49: 0 | P49: =SUMIF(E$10:E$146,"74",D$10:D$146) -> 0 | Q49: =+O49-P49 -> 0
G50: 30 | H50: Outros Saúde | I50: 0 | J50: =SUMIF(E$10:E$146,"30",D$10:D$146) -> 0 | K50: =+I50-J50 -> 0 | M50: 75 | N50: Utensílios e decoração | O50: 0 | P50: =SUMIF(E$10:E$146,"75",D$10:D$146) -> 0 | Q50: =+O50-P50 -> 0
H51: TOTAL | I51: =SUM(I41:I50) -> 679 | J51: =SUM(J41:J50) -> 0 | K51: =+I51-J51 -> 679 | M51: 76 | N51: Outros Artigos | O51: 0 | P51: =SUMIF(E$10:E$146,"76",D$10:D$146) -> 0 | Q51: =+O51-P51 -> 0
N52: TOTAL | O52: =SUM(O45:O51) -> 0 | P52: =SUM(P45:P51) -> 0 | Q52: =+O52-P52 -> 0
H53: VESTUÁRIO | I53: Previsto | J53: Real | K53: Diferença
G54: 31 | H54: Roupas | I54: 39 | J54: =SUMIF(E$10:E$146,"31",D$10:D$146) -> 0 | K54: =+I54-J54 -> 39 | N54: Div Matheus | O54: Previsto | P54: Real | Q54: Diferença
G55: 32 | H55: Sapatos | I55: 0 | J55: =SUMIF(E$10:E$146,"32",D$10:D$146) -> 0 | K55: =+I55-J55 -> 0 | M55: 80 | N55: Casas Bahia | O55: 5200 | P55: =SUMIF(E$10:E$146,"80",D$10:D$146) -> 0 | Q55: =+O55-P55 -> 5200
G56: 33 | H56: Outros Vestuário | I56: 0 | J56: =SUMIF(E$10:E$146,"33",D$10:D$146) -> 0 | K56: =+I56-J56 -> 0 | M56: 81 | N56: Faculdade | O56: 1740 | P56: =SUMIF(E$10:E$146,"81",D$10:D$146) -> 0 | Q56: =+O56-P56 -> 1740
H57: TOTAL | I57: =SUM(I54:I56) -> 39 | J57: =SUM(J54:J56) -> 0 | K57: =+I57-J57 -> 39 | M57: 82 | N57: Magalu | O57: 380 | P57: =SUMIF(E$10:E$146,"82",D$10:D$146) -> 0 | Q57: =+O57-P57 -> 380
M58: 83 | N58: Vivo | O58: 478 | P58: =SUMIF(E$10:E$146,"83",D$10:D$146) -> 0 | Q58: =+O58-P58 -> 478
H59: Inv\ Longo Prazo | I59: Previsto | J59: Rendimento | K59: Dividendos | N59: TOTAL | O59: =SUM(O55:O58) -> 7798 | P59: =SUM(P55:P58) -> 0 | Q59: =+O59-P59 -> 7798
G60: 34 | H60: Comissoes | I60: 1200 | J60: 150 | K60: =+I60-O621 -> 1200
G61: 35 | H61: Renda Variavel | I61: 1200 | J61: =SUMIF(E$10:E$146,"34",D$10:D$146) -> 0 | K61: =+I61-O622 -> 1200
G62: 36 | H62: Fundos imobiliário | I62: 1200 | J62: =SUMIF(E$10:E$146,"35",D$10:D$146) -> 0 | K62: =+I62-J62 -> 1200 | N62: Inv\ Curto Prazo | O62: Previsto | P62: Real | Q62: Diferença
G63: 37 | H63: Ações Baixo Risco | I63: 1200 | J63: =SUMIF(E$10:E$146,"36",D$10:D$146) -> 0 | K63: =+I63-J63 -> 1200 | M63: 90 | N63: Investimentos Mensais | O63: 0 | P63: =SUMIF(E$10:E$146,"90",D$10:D$146) -> 0 | Q63: =+O63-P63 -> 0
G64: 38 | H64: Projetos | I64: 580 | J64: 140 | N64: Alununas a Mais
G65: 39 | H65: Ações Altos Risco | I65: 1200 | J65: =SUMIF(E$10:E$146,"37",D$10:D$146) -> 0 | K65: =+I65-J65 -> 1200 | M65: 91 | N65: Cartas de Crédito | O65: 0 | P65: =SUMIF(E$10:E$146,"91",D$10:D$146) -> 0 | Q65: =+O65-P65 -> 0
H66: TOTAL | I66: =SUM(I61:I65) -> 5380 | J66: =SUM(J60:J65) -> 290 | K66: =+I66-J66 -> 5090 | M66: 92 | N66: Outros Financeiro | O66: 0 | P66: =SUMIF(E$10:E$146,"92",D$10:D$146) -> 0 | Q66: =+O66-P66 -> 0
N67: TOTAL | O67: =SUM(O63:O66) -> 0 | P67: =SUM(P63:P66) -> 0 | Q67: =+O67-P67 -> 0

Sheet FEV
B1: Lançamento de Compras e Gastos Casa
I3: Previsto | K3: Real | N3: Diferença
H4: Renda 1 | I4: =2398+K66 -> 2398 | J4: 1940 | K4: =1940+J66 -> 1940 | N4: =I4-K4 -> 458
H5: Renda 2 | I5: =2500+Q67 -> 2500 | J5: 2500 | K5: 2500 | N5: =I5-J5 -> 0
B6: Despesas Mensais | H6: Renda Total | I6: =+I4+I5 -> 4898 | K6: =+K4+K5 -> 4440 | N6: =+I6-K6 -> 458
H7: Despesas | I7: =+SUM(I22,O24,I29,O34,I38,O42,I51,O52,I57,O59,I66,O67,) -> 7213.3 | K7: =+SUM(J22,J29,J38,J51,J57,J66,P67,P59,P52,P42,P34,P24,) -> 3361 | N7: =+I7-K7 -> 3852.3
B8: Data | C8: Despesa | D8: Valor | E8: Área | H8: Saldo | I8: =+I6-I7 -> -2315.3 | K8: =+K6-K7 -> 1079 | N8: =I8-K8 -> -3394.3
D9: =SUM(D10:D112) -> 0
B10: 45689
B11: 45690 | H11: MORADIA | I11: Previsto | J11: Real | K11: Diferença | N11: TRANSPORTE | O11: Previsto | P11: Real | Q11: Diferença
B12: 45691 | G12: 1 | H12: Caixa de Emergência | I12: 150 | J12: =SUMIF(E$10:E$144,"1",D$10:D$144) -> 0 | K12: =+I12-J12 -> 150 | M12: 40 | N12: Uber 99 | O12: 58 | P12: 45 | Q12: =+O12-P12 -> 13
B13: 45692 | G13: 2 | H13: Inevitavelmento fixo | I13: 1200 | J13: =SUMIF(E$10:E$144,"2",D$10:D$144) -> 0 | K13: =+I13-J13 -> 1200 | M13: 41 | N13: Uber | O13: 68 | P13: =SUMIF(E$10:E$144,"41",D$10:D$144) -> 0 | Q13: =+O13-P13 -> 68
B14: 45693 | G14: 3 | H14: Das Jhenis | I14: 250 | J14: =SUMIF(E$10:E$144,"3",D$10:D$144) -> 0 | K14: =+I14-J14 -> 250 | M14: 42 | N14: Transporte Público | O14: 440 | P14: 0 | Q14: =+O14-P14 -> 440
B15: 45694 | G15: 4 | H15: Cartao Jhenismara | I15: 1200 | J15: 1400 | K15: =+I15-J15 -> -200 | M15: 43 | N15: Transporte Trabalho J | O15: 240 | P15: 143 | Q15: =+O15-P15 -> 97
B16: 45695 | G16: 5 | H16: Emergência Casa | I16: 120 | J16: =SUMIF(E$10:E$144,"5",D$10:D$144) -> 0 | K16: =+I16-J16 -> 120 | M16: 44 | N16: Transporte Trabalho M | O16: 110 | P16: 240 | Q16: =+O16-P16 -> -130
B17: 45696 | G17: 6 | H17: Energia | I17: 150 | J17: 150 | K17: =+I17-J17 -> 0 | M17: 45 | N17: Caixa Carro J | O17: 0 | P17: =SUMIF(E$10:E$144,"45",D$10:D$144) -> 0 | Q17: =+O17-P17 -> 0
B18: 45697 | G18: 7 | H18: Água | I18: 77 | J18: 77 | K18: =+I18-J18 -> 0 | M18: 46 | N18: Caixa Carro M | O18: 0 | P18: =SUMIF(E$10:E$144,"46",D$10:D$144) -> 0 | Q18: =+O18-P18 -> 0
B19: 45698 | G19: 8 | H19: Gás | I19: 55 | J19: 55 | K19: =+I19-J19 -> 0 | M19: 47 | O19: 0 | P19: =SUMIF(E$10:E$144,"47",D$10:D$144) -> 0 | Q19: =+O19-P19 -> 0
B20: 45699 | G20: 9 | H20: Cartao (Matheus) | I20: 175 | J20: 175 | K20: =+I20-J20 -> 0 | M20: 48 | O20: 0 | P20: =SUMIF(E$10:E$144,"48",D$10:D$144) -> 0 | Q20: =+O20-P20 -> 0
B21: 45700 | G21: 10 | H21: Outrs Dispesas | J21: =SUMIF(E$10:E$144,"10",D$10:D$144) -> 0 | K21: =+I21-J21 -> 0 | M21: 49 | O21: 0 | P21: 0 | Q21: =+O21-P21 -> 0
B22: 45701 | H22: TOTAL | I22: =SUM(I12:I21) -> 3377 | J22: =SUM(J12:J21) -> 1857 | K22: =+I22-J22 -> 1520 | M22: 50 | O22: 0 | P22: 0 | Q22: =+O22-P22 -> 0
B23: 45702 | M23: 51 | N23: Outros Transporte | O23: 0 | P23: =SUMIF(E$10:E$144,"51",D$10:D$144) -> 0 | Q23: =+O23-P23 -> 0
B24: 45703 | H24: ALIMENTAÇÃO | I24: Previsto | J24: Real | K24: Diferença | N24: TOTAL | O24: =SUM(O12:O23) -> 916 | P24: =SUM(P12:P23) -> 428 | Q24: =+O24-P24 -> 488
B25: 45704 | G25: 11 | H25: Supermercado | I25: 450 | J25: 450 | K25: =+I25-J25 -> 0
B26: 45705 | G26: 12 | H26: Restaurante | I26: 140 | J26: 140 | K26: =+I26-J26 -> 0 | N26: EDUCAÇÃO | O26: Previsto | P26: Real | Q26: Diferença
B27: 45706 | G27: 13 | H27: Café \ Almoço | I27: 100 | J27: 250 | K27: =+I27-J27 -> -150 | M27: 52 | N27: Mensalidades | O27: 0 | P27: =SUMIF(E$10:E$144,"52",D$10:D$144) -> 0 | Q27: =+O27-P27 -> 0
B28: 45707 | G28: 14 | H28: Pedidos IFood | I28: 140 | J28: =SUMIF(E$10:E$144,"14",D$10:D$144) -> 0 | K28: =+I28-J28 -> 140 | M28: 53 | N28: Idiomas | O28: 0 | P28: =SUMIF(E$10:E$144,"53",D$10:D$144) -> 0 | Q28: =+O28-P28 -> 0
B29: 45708 | H29: TOTAL | I29: =SUM(I25:I28) -> 830 | J29: =SUM(J25:J28) -> 840 | K29: =+I29-J29 -> -10 | M29: 54 | N29: CNH [Matheus] | O29: 0 | P29: =SUMIF(E$10:E$144,"54",D$10:D$144) -> 0 | Q29: =+O29-P29 -> 0
B30: 45709 | M30: 55 | N30: Cursos | O30: 140 | P30: =SUMIF(E$10:E$144,"55",D$10:D$144) -> 0 | Q30: =+O30-P30 -> 140
B31: 45710 | H31: COMUNICAÇÃO | I31: Previsto | J31: Real | K31: Diferença | M31: 56 | N31: Livros | O31: 0 | P31: =SUMIF(E$10:E$144,"56",D$10:D$144) -> 0 | Q31: =+O31-P31 -> 0
B32: 45711 | G32: 15 | H32: Celular | I32: 45 | J32: 45 | K32: =+I32-J32 -> 0 | M32: 57 | N32: Faculdade [Jhenis] | O32: 0 | P32: =SUMIF(E$10:E$144,"57",D$10:D$144) -> 0 | Q32: =+O32-P32 -> 0
B33: 45712 | G33: 16 | H33: Internet | I33: 89 | J33: 89 | K33: =+I33-J33 -> 0 | M33: 58 | N33: Outros Educação | O33: 0 | P33: =SUMIF(E$10:E$144,"58",D$10:D$144) -> 0 | Q33: =+O33-P33 -> 0
B34: 45713 | G34: 17 | H34: Streaming | I34: 24 | J34: 24 | K34: =+I34-J34 -> 0 | N34: TOTAL | O34: =SUM(O27:O33) -> 140 | P34: =SUM(P27:P33) -> 0 | Q34: =+O34-P34 -> 140
B35: 45714 | G35: 18 | H35: Netflix | I35: 21.9 | J35: 22 | K35: =+I35-J35 -> -0.1
B36: 45715 | G36: 19 | H36: Amazon | I36: 10.9 | J36: 11 | K36: =+I36-J36 -> -0.1 | N36: LAZER | O36: Previsto | P36: Real | Q36: Diferença
B37: 45716 | G37: 20 | H37: Max Plus | I37: 34.5 | J37: 45 | K37: =+I37-J37 -> -10.5 | M37: 60 | N37: Cinema | O37: 450 | P37: =SUMIF(E$10:E$144,"60",D$10:D$144) -> 0 | Q37: =+O37-P37 -> 450
H38: TOTAL | I38: =SUM(I32:I37) -> 225.3 | J38: =SUM(J32:J37) -> 236 | K38: =+I38-J38 -> -10.7 | M38: 61 | N38: Esportes | O38: 0 | P38: =SUMIF(E$10:E$144,"61",D$10:D$144) -> 0 | Q38: =+O38-P38 -> 0
M39: 62 | N39: Shows [Consertos] | O39: 120 | P39: =SUMIF(E$10:E$144,"62",D$10:D$144) -> 0 | Q39: =+O39-P39 -> 120
H40: SAÚDE E CUIDADOS | I40: Previsto | J40: Real | K40: Diferença | M40: 63 | N40: Viagens [Férias] | O40: 148 | P40: =SUMIF(E$10:E$144,"63",D$10:D$144) -> 0 | Q40: =+O40-P40 -> 148
G41: 21 | H41: Academia | I41: 120 | J41: =SUMIF(E$10:E$144,"21",D$10:D$144) -> 0 | K41: =+I41-J41 -> 120 | M41: 64 | N41: Outros Lazer | O41: 60 | P41: =SUMIF(E$10:E$144,"64",D$10:D$144) -> 0 | Q41: =+O41-P41 -> 60
G42: 22 | H42: Emergencia Médica | I42: 120 | J42: =SUMIF(E$10:E$144,"22",D$10:D$144) -> 0 | K42: =+I42-J42 -> 120 | N42: TOTAL | O42: =SUM(O37:O41) -> 778 | P42: =SUM(P37:P41) -> 0 | Q42: =+O42-P42 -> 778
G43: 23 | H43: Emergência Dentista | I43: 100 | J43: =SUMIF(E$10:E$144,"23",D$10:D$144) -> 0 | K43: =+I43-J43 -> 100
G44: 24 | H44: Cosméticos | I44: 100 | J44: =SUMIF(E$10:E$144,"24",D$10:D$144) -> 0 | K44: =+I44-J44 -> 100 | N44: Necessidades Da Casa | O44: Previsto | P44: Real | Q44: Diferença
G45: 25 | H45: Dentista | I45: 150 | J45: =SUMIF(E$10:E$144,"25",D$10:D$144) -> 0 | K45: =+I45-J45 -> 150 | M45: 70 | N45: Cama | O45: 0 | P45: =SUMIF(E$10:E$144,"70",D$10:D$144) -> 0 | Q45: =+O45-P45 -> 0
G46: 26 | H46: Exames médicos | I46: 0 | J46: =SUMIF(E$10:E$144,"26",D$10:D$144) -> 0 | K46: =+I46-J46 -> 0 | M46: 71 | N46: Consertos [ Futuros | O46: 0 | P46: =SUMIF(E$10:E$144,"71",D$10:D$144) -> 0 | Q46: =+O46-P46 -> 0
G47: 27 | H47: Farmácia | I47: 89 | J47: =SUMIF(E$10:E$144,"27",D$10:D$144) -> 0 | K47: =+I47-J47 -> 89 | M47: 72 | N47: Geladeira | O47: 0 | P47: =SUMIF(E$10:E$144,"72",D$10:D$144) -> 0 | Q47: =+O47-P47 -> 0
G48: 28 | H48: Médicos particular | I48: 0 | J48: =SUMIF(E$10:E$144,"28",D$10:D$144) -> 0 | K48: =+I48-J48 -> 0 | M48: 73 | N48: Lava e seca | O48: 0 | P48: =SUMIF(E$10:E$144,"73",D$10:D$144) -> 0 | Q48: =+O48-P48 -> 0
G49: 29 | H49: Suplementos | I49: 0 | J49: =SUMIF(E$10:E$144,"29",D$10:D$144) -> 0 | K49: =+I49-J49 -> 0 | M49: 74 | N49: Lavanderia louça | O49: 0 | P49: =SUMIF(E$10:E$144,"74",D$10:D$144) -> 0 | Q49: =+O49-P49 -> 0
G50: 30 | H50: Outros Saúde | I50: 0 | J50: =SUMIF(E$10:E$144,"30",D$10:D$144) -> 0 | K50: =+I50-J50 -> 0 | M50: 75 | N50: Utensílios e decoração | O50: 0 | P50: =SUMIF(E$10:E$144,"75",D$10:D$144) -> 0 | Q50: =+O50-P50 -> 0
H51: TOTAL | I51: =SUM(I41:I50) -> 679 | J51: =SUM(J41:J50) -> 0 | K51: =+I51-J51 -> 679 | M51: 76 | N51: Outros Artigos | O51: 0 | P51: =SUMIF(E$10:E$144,"76",D$10:D$144) -> 0 | Q51: =+O51-P51 -> 0
N52: TOTAL | O52: =SUM(O45:O51) -> 0 | P52: =SUM(P45:P51) -> 0 | Q52: =+O52-P52 -> 0
H53: VESTUÁRIO | I53: Previsto | J53: Real | K53: Diferença
G54: 31 | H54: Roupas | I54: 39 | J54: =SUMIF(E$10:E$144,"31",D$10:D$144) -> 0 | K54: =+I54-J54 -> 39 | N54: OUTROS | O54: Previsto | P54: Real | Q54: Diferença
G55: 32 | H55: Sapatos | I55: 0 | J55: =SUMIF(E$10:E$144,"32",D$10:D$144) -> 0 | K55: =+I55-J55 -> 0 | M55: 80 | N55: Presentes | O55: 89 | P55: =SUMIF(E$10:E$144,"80",D$10:D$144) -> 0 | Q55: =+O55-P55 -> 89
G56: 33 | H56: Outros Vestuário | I56: 0 | J56: =SUMIF(E$10:E$144,"33",D$10:D$144) -> 0 | K56: =+I56-J56 -> 0 | M56: 81 | N56: Doações | O56: 0 | P56: =SUMIF(E$10:E$144,"81",D$10:D$144) -> 0 | Q56: =+O56-P56 -> 0
H57: TOTAL | I57: =SUM(I54:I56) -> 39 | J57: =SUM(J54:J56) -> 0 | K57: =+I57-J57 -> 39 | M57: 82 | N57: Ensaio | O57: 140 | P57: =SUMIF(E$10:E$144,"82",D$10:D$144) -> 0 | Q57: =+O57-P57 -> 140
M58: 83 | N58: Outros | O58: 0 | P58: =SUMIF(E$10:E$144,"83",D$10:D$144) -> 0 | Q58: =+O58-P58 -> 0
H59: Investimentos | I59: Previsto | J59: Rendimento | K59: Dividendos | N59: TOTAL | O59: =SUM(O55:O58) -> 229 | P59: =SUM(P55:P58) -> 0 | Q59: =+O59-P59 -> 229
G60: 34 | H60: Renda Variavel | I60: 1200 | J60: =SUMIF(E$10:E$144,"34",D$10:D$144) -> 0 | K60: =+I60-O620 -> 1200
G61: 35 | H61: Fundos imobiliário | I61: 1200 | J61: =SUMIF(E$10:E$144,"35",D$10:D$144) -> 0 | K61: =+I61-J61 -> 1200 | N61: FINANCEIRO | O61: Previsto | P61: Real | Q61: Diferença
G62: 36 | H62: Ações Baixo Risco | I62: 1200 | J62: =SUMIF(E$10:E$144,"36",D$10:D$144) -> 0 | K62: =+I62-J62 -> 1200 | M62: 90 | N62: Investimentos Mensais | O62: 0 | P62: =SUMIF(E$10:E$144,"90",D$10:D$144) -> 0 | Q62: =+O62-P62 -> 0
G63: 37 | H63: Ações Altos Risco | I63: 1200 | J63: =SUMIF(E$10:E$144,"37",D$10:D$144) -> 0 | K63: =+I63-J63 -> 1200 | M63: 91 | N63: Cartas de Crédito | O63: 0 | P63: =SUMIF(E$10:E$144,"91",D$10:D$144) -> 0 | Q63: =+O63-P63 -> 0
H64: TOTAL | I64: =SUM(I60:I63) -> 4800 | J64: =SUM(J60:J63) -> 0 | K64: =+I64-J64 -> 4800 | M64: 92 | N64: Outros Financeiro | O64: 0 | P64: =SUMIF(E$10:E$144,"92",D$10:D$144) -> 0 | Q64: =+O64-P64 -> 0
N65: TOTAL | O65: =SUM(O62:O64) -> 0 | P65: =SUM(P62:P64) -> 0 | Q65: =+O65-P65 -> 0

Sheet MAR
B1: Lançamento de Compras e Gastos Casa Organizada
I3: Previsto | K3: Real | N3: Diferença
H4: Renda 1 | I4: 2398 | J4: 1940 | K4: 1940 | N4: =I4-K4 -> 458
H5: Renda 2 | I5: 2500 | J5: 2500 | K5: 2500 | N5: =I5-J5 -> 0
B6: Despesas Mensais | H6: Renda Total | I6: =+I4+I5 -> 4898 | K6: =+K4+K5 -> 4440 | N6: =+I6-K6 -> 458
H7: Despesas | I7: =+SUM(I22,O24,I29,O34,I38,O42,I51,O52,I57,O59,I64,O65,) -> 12013.3 | K7: =+SUM(J22,J29,J38,J51,J57,J64,P65,P59,P52,P42,P34,P24,) -> 3361 | N7: =+I7-K7 -> 8652.3
B8: Data | C8: Despesa | D8: Valor | E8: Área | H8: Saldo | I8: =+I6-I7 -> -7115.3 | K8: =+K6-K7 -> 1079 | N8: =I8-K8 -> -8194.3
D9: =SUM(D10:D112) -> 0
B10: 45717
B11: 45718 | H11: MORADIA | I11: Previsto | J11: Real | K11: Diferença | N11: TRANSPORTE | O11: Previsto | P11: Real | Q11: Diferença
B12: 45719 | G12: 1 | H12: Caixa de Emergência | I12: 150 | J12: =SUMIF(E$10:E$144,"1",D$10:D$144) -> 0 | K12: =+I12-J12 -> 150 | M12: 40 | N12: Uber 99 | O12: 58 | P12: 45 | Q12: =+O12-P12 -> 13
B13: 45720 | G13: 2 | H13: Inevitavelmento fixo | I13: 1200 | J13: =SUMIF(E$10:E$144,"2",D$10:D$144) -> 0 | K13: =+I13-J13 -> 1200 | M13: 41 | N13: Uber | O13: 68 | P13: =SUMIF(E$10:E$144,"41",D$10:D$144) -> 0 | Q13: =+O13-P13 -> 68
B14: 45721 | G14: 3 | H14: Das Jhenis | I14: 250 | J14: =SUMIF(E$10:E$144,"3",D$10:D$144) -> 0 | K14: =+I14-J14 -> 250 | M14: 42 | N14: Transporte Público | O14: 440 | P14: 0 | Q14: =+O14-P14 -> 440
B15: 45722 | G15: 4 | H15: Cartao Jhenismara | I15: 1200 | J15: 1400 | K15: =+I15-J15 -> -200 | M15: 43 | N15: Transporte Trabalho J | O15: 240 | P15: 143 | Q15: =+O15-P15 -> 97
B16: 45723 | G16: 5 | H16: Emergência Casa | I16: 120 | J16: =SUMIF(E$10:E$144,"5",D$10:D$144) -> 0 | K16: =+I16-J16 -> 120 | M16: 44 | N16: Transporte Trabalho M | O16: 110 | P16: 240 | Q16: =+O16-P16 -> -130
B17: 45724 | G17: 6 | H17: Energia | I17: 150 | J17: 150 | K17: =+I17-J17 -> 0 | M17: 45 | N17: Caixa Carro J | O17: 0 | P17: =SUMIF(E$10:E$144,"45",D$10:D$144) -> 0 | Q17: =+O17-P17 -> 0
B18: 45725 | G18: 7 | H18: Água | I18: 77 | J18: 77 | K18: =+I18-J18 -> 0 | M18: 46 | N18: Caixa Carro M | O18: 0 | P18: =SUMIF(E$10:E$144,"46",D$10:D$144) -> 0 | Q18: =+O18-P18 -> 0
B19: 45726 | G19: 8 | H19: Gás | I19: 55 | J19: 55 | K19: =+I19-J19 -> 0 | M19: 47 | O19: 0 | P19: =SUMIF(E$10:E$144,"47",D$10:D$144) -> 0 | Q19: =+O19-P19 -> 0
B20: 45727 | G20: 9 | H20: Cartao (Matheus) | I20: 175 | J20: 175 | K20: =+I20-J20 -> 0 | M20: 48 | O20: 0 | P20: =SUMIF(E$10:E$144,"48",D$10:D$144) -> 0 | Q20: =+O20-P20 -> 0
B21: 45728 | G21: 10 | H21: Outrs Dispesas | J21: =SUMIF(E$10:E$144,"10",D$10:D$144) -> 0 | K21: =+I21-J21 -> 0 | M21: 49 | O21: 0 | P21: 0 | Q21: =+O21-P21 -> 0
B22: 45729 | H22: TOTAL | I22: =SUM(I12:I21) -> 3377 | J22: =SUM(J12:J21) -> 1857 | K22: =+I22-J22 -> 1520 | M22: 50 | O22: 0 | P22: 0 | Q22: =+O22-P22 -> 0
B23: 45730 | M23: 51 | N23: Outros Transporte | O23: 0 | P23: =SUMIF(E$10:E$144,"51",D$10:D$144) -> 0 | Q23: =+O23-P23 -> 0
B24: 45731 | H24: ALIMENTAÇÃO | I24: Previsto | J24: Real | K24: Diferença | N24: TOTAL | O24: =SUM(O12:O23) -> 916 | P24: =SUM(P12:P23) -> 428 | Q24: =+O24-P24 -> 488
B25: 45732 | G25: 11 | H25: Supermercado | I25: 450 | J25: 450 | K25: =+I25-J25 -> 0
B26: 45733 | G26: 12 | H26: Restaurante | I26: 140 | J26: 140 | K26: =+I26-J26 -> 0 | N26: EDUCAÇÃO | O26: Previsto | P26: Real | Q26: Diferença
B27: 45734 | G27: 13 | H27: Café \ Almoço | I27: 100 | J27: 250 | K27: =+I27-J27 -> -150 | M27: 52 | N27: Mensalidades | O27: 0 | P27: =SUMIF(E$10:E$144,"52",D$10:D$144) -> 0 | Q27: =+O27-P27 -> 0
B28: 45735 | G28: 14 | H28: Pedidos IFood | I28: 140 | J28: =SUMIF(E$10:E$144,"14",D$10:D$144) -> 0 | K28: =+I28-J28 -> 140 | M28: 53 | N28: Idiomas | O28: 0 | P28: =SUMIF(E$10:E$144,"53",D$10:D$144) -> 0 | Q28: =+O28-P28 -> 0
B29: 45736 | H29: TOTAL | I29: =SUM(I25:I28) -> 830 | J29: =SUM(J25:J28) -> 840 | K29: =+I29-J29 -> -10 | M29: 54 | N29: CNH [Matheus] | O29: 0 | P29: =SUMIF(E$10:E$144,"54",D$10:D$144) -> 0 | Q29: =+O29-P29 -> 0
B30: 45737 | M30: 55 | N30: Cursos | O30: 140 | P30: =SUMIF(E$10:E$144,"55",D$10:D$144) -> 0 | Q30: =+O30-P30 -> 140
B31: 45738 | H31: COMUNICAÇÃO | I31: Previsto | J31: Real | K31: Diferença | M31: 56 | N31: Livros | O31: 0 | P31: =SUMIF(E$10:E$144,"56",D$10:D$144) -> 0 | Q31: =+O31-P31 -> 0
B32: 45739 | G32: 15 | H32: Celular | I32: 45 | J32: 45 | K32: =+I32-J32 -> 0 | M32: 57 | N32: Faculdade [Jhenis] | O32: 0 | P32: =SUMIF(E$10:E$144,"57",D$10:D$144) -> 0 | Q32: =+O32-P32 -> 0
B33: 45740 | G33: 16 | H33: Internet | I33: 89 | J33: 89 | K33: =+I33-J33 -> 0 | M33: 58 | N33: Outros Educação | O33: 0 | P33: =SUMIF(E$10:E$144,"58",D$10:D$144) -> 0 | Q33: =+O33-P33 -> 0
B34: 45741 | G34: 17 | H34: Streaming | I34: 24 | J34: 24 | K34: =+I34-J34 -> 0 | N34: TOTAL | O34: =SUM(O27:O33) -> 140 | P34: =SUM(P27:P33) -> 0 | Q34: =+O34-P34 -> 140
B35: 45742 | G35: 18 | H35: Netflix | I35: 21.9 | J35: 22 | K35: =+I35-J35 -> -0.1
B36: 45743 | G36: 19 | H36: Amazon | I36: 10.9 | J36: 11 | K36: =+I36-J36 -> -0.1 | N36: LAZER | O36: Previsto | P36: Real | Q36: Diferença
B37: 45744 | G37: 20 | H37: Max Plus | I37: 34.5 | J37: 45 | K37: =+I37-J37 -> -10.5 | M37: 60 | N37: Cinema | O37: 450 | P37: =SUMIF(E$10:E$144,"60",D$10:D$144) -> 0 | Q37: =+O37-P37 -> 450
B38: 45745 | H38: TOTAL | I38: =SUM(I32:I37) -> 225.3 | J38: =SUM(J32:J37) -> 236 | K38: =+I38-J38 -> -10.7 | M38: 61 | N38: Esportes | O38: 0 | P38: =SUMIF(E$10:E$144,"61",D$10:D$144) -> 0 | Q38: =+O38-P38 -> 0
B39: 45746 | M39: 62 | N39: Shows [Consertos] | O39: 120 | P39: =SUMIF(E$10:E$144,"62",D$10:D$144) -> 0 | Q39: =+O39-P39 -> 120
B40: 45747 | H40: SAÚDE E CUIDADOS | I40: Previsto | J40: Real | K40: Diferença | M40: 63 | N40: Viagens [Férias] | O40: 148 | P40: =SUMIF(E$10:E$144,"63",D$10:D$144) -> 0 | Q40: =+O40-P40 -> 148
G41: 21 | H41: Academia | I41: 120 | J41: =SUMIF(E$10:E$144,"21",D$10:D$144) -> 0 | K41: =+I41-J41 -> 120 | M41: 64 | N41: Outros Lazer | O41: 60 | P41: =SUMIF(E$10:E$144,"64",D$10:D$144) -> 0 | Q41: =+O41-P41 -> 60
G42: 22 | H42: Emergencia Médica | I42: 120 | J42: =SUMIF(E$10:E$144,"22",D$10:D$144) -> 0 | K42: =+I42-J42 -> 120 | N42: TOTAL | O42: =SUM(O37:O41) -> 778 | P42: =SUM(P37:P41) -> 0 | Q42: =+O42-P42 -> 778
G43: 23 | H43: Emergência Dentista | I43: 100 | J43: =SUMIF(E$10:E$144,"23",D$10:D$144) -> 0 | K43: =+I43-J43 -> 100
G44: 24 | H44: Cosméticos | I44: 100 | J44: =SUMIF(E$10:E$144,"24",D$10:D$144) -> 0 | K44: =+I44-J44 -> 100 | N44: Necessidades Da Casa | O44: Previsto | P44: Real | Q44: Diferença
G45: 25 | H45: Dentista | I45: 150 | J45: =SUMIF(E$10:E$144,"25",D$10:D$144) -> 0 | K45: =+I45-J45 -> 150 | M45: 70 | N45: Cama | O45: 0 | P45: =SUMIF(E$10:E$144,"70",D$10:D$144) -> 0 | Q45: =+O45-P45 -> 0
G46: 26 | H46: Exames médicos | I46: 0 | J46: =SUMIF(E$10:E$144,"26",D$10:D$144) -> 0 | K46: =+I46-J46 -> 0 | M46: 71 | N46: Consertos [ Futuros | O46: 0 | P46: =SUMIF(E$10:E$144,"71",D$10:D$144) -> 0 | Q46: =+O46-P46 -> 0
G47: 27 | H47: Farmácia | I47: 89 | J47: =SUMIF(E$10:E$144,"27",D$10:D$144) -> 0 | K47: =+I47-J47 -> 89 | M47: 72 | N47: Geladeira | O47: 0 | P47: =SUMIF(E$10:E$144,"72",D$10:D$144) -> 0 | Q47: =+O47-P47 -> 0
G48: 28 | H48: Médicos particular | I48: 0 | J48: =SUMIF(E$10:E$144,"28",D$10:D$144) -> 0 | K48: =+I48-J48 -> 0 | M48: 73 | N48: Lava e seca | O48: 0 | P48: =SUMIF(E$10:E$144,"73",D$10:D$144) -> 0 | Q48: =+O48-P48 -> 0
G49: 29 | H49: Suplementos | I49: 0 | J49: =SUMIF(E$10:E$144,"29",D$10:D$144) -> 0 | K49: =+I49-J49 -> 0 | M49: 74 | N49: Lavanderia louça | O49: 0 | P49: =SUMIF(E$10:E$144,"74",D$10:D$144) -> 0 | Q49: =+O49-P49 -> 0
G50: 30 | H50: Outros Saúde | I50: 0 | J50: =SUMIF(E$10:E$144,"30",D$10:D$144) -> 0 | K50: =+I50-J50 -> 0 | M50: 75 | N50: Utensílios e decoração | O50: 0 | P50: =SUMIF(E$10:E$144,"75",D$10:D$144) -> 0 | Q50: =+O50-P50 -> 0
H51: TOTAL | I51: =SUM(I41:I50) -> 679 | J51: =SUM(J41:J50) -> 0 | K51: =+I51-J51 -> 679 | M51: 76 | N51: Outros Artigos | O51: 0 | P51: =SUMIF(E$10:E$144,"76",D$10:D$144) -> 0 | Q51: =+O51-P51 -> 0
N52: TOTAL | O52: =SUM(O45:O51) -> 0 | P52: =SUM(P45:P51) -> 0 | Q52: =+O52-P52 -> 0
H53: VESTUÁRIO | I53: Previsto | J53: Real | K53: Diferença
G54: 31 | H54: Roupas | I54: 39 | J54: =SUMIF(E$10:E$144,"31",D$10:D$144) -> 0 | K54: =+I54-J54 -> 39 | N54: OUTROS | O54: Previsto | P54: Real | Q54: Diferença
G55: 32 | H55: Sapatos | I55: 0 | J55: =SUMIF(E$10:E$144,"32",D$10:D$144) -> 0 | K55: =+I55-J55 -> 0 | M55: 80 | N55: Presentes | O55: 89 | P55: =SUMIF(E$10:E$144,"80",D$10:D$144) -> 0 | Q55: =+O55-P55 -> 89
G56: 33 | H56: Outros Vestuário | I56: 0 | J56: =SUMIF(E$10:E$144,"33",D$10:D$144) -> 0 | K56: =+I56-J56 -> 0 | M56: 81 | N56: Doações | O56: 0 | P56: =SUMIF(E$10:E$144,"81",D$10:D$144) -> 0 | Q56: =+O56-P56 -> 0
H57: TOTAL | I57: =SUM(I54:I56) -> 39 | J57: =SUM(J54:J56) -> 0 | K57: =+I57-J57 -> 39 | M57: 82 | N57: Ensaio | O57: 140 | P57: =SUMIF(E$10:E$144,"82",D$10:D$144) -> 0 | Q57: =+O57-P57 -> 140
M58: 83 | N58: Outros | O58: 0 | P58: =SUMIF(E$10:E$144,"83",D$10:D$144) -> 0 | Q58: =+O58-P58 -> 0
H59: Investimentos | I59: Previsto | J59: Rendimento | K59: Dividendos | N59: TOTAL | O59: =SUM(O55:O58) -> 229 | P59: =SUM(P55:P58) -> 0 | Q59: =+O59-P59 -> 229
G60: 34 | H60: Renda Variavel | I60: 1200 | J60: =SUMIF(E$10:E$144,"34",D$10:D$144) -> 0 | K60: =+I60-O620 -> 1200
G61: 35 | H61: Fundos imobiliário | I61: 1200 | J61: =SUMIF(E$10:E$144,"35",D$10:D$144) -> 0 | K61: =+I61-J61 -> 1200 | N61: FINANCEIRO | O61: Previsto | P61: Real | Q61: Diferença
G62: 36 | H62: Ações Baixo Risco | I62: 1200 | J62: =SUMIF(E$10:E$144,"36",D$10:D$144) -> 0 | K62: =+I62-J62 -> 1200 | M62: 90 | N62: Investimentos Mensais | O62: 0 | P62: =SUMIF(E$10:E$144,"90",D$10:D$144) -> 0 | Q62: =+O62-P62 -> 0
G63: 37 | H63: Ações Altos Risco | I63: 1200 | J63: =SUMIF(E$10:E$144,"37",D$10:D$144) -> 0 | K63: =+I63-J63 -> 1200 | M63: 91 | N63: Cartas de Crédito | O63: 0 | P63: =SUMIF(E$10:E$144,"91",D$10:D$144) -> 0 | Q63: =+O63-P63 -> 0
H64: TOTAL | I64: =SUM(I60:I63) -> 4800 | J64: =SUM(J60:J63) -> 0 | K64: =+I64-J64 -> 4800 | M64: 92 | N64: Outros Financeiro | O64: 0 | P64: =SUMIF(E$10:E$144,"92",D$10:D$144) -> 0 | Q64: =+O64-P64 -> 0
N65: TOTAL | O65: =SUM(O62:O64) -> 0 | P65: =SUM(P62:P64) -> 0 | Q65: =+O65-P65 -> 0

Sheet ABR
B1: Lançamento de Compras e Gastos Casa Organizada
I3: Previsto | K3: Real | N3: Diferença
H4: Renda 1 | I4: 2398 | J4: 1940 | K4: 1940 | N4: =I4-K4 -> 458
H5: Renda 2 | I5: 2500 | J5: 2500 | K5: 2500 | N5: =I5-J5 -> 0
B6: Despesas Mensais | H6: Renda Total | I6: =+I4+I5 -> 4898 | K6: =+K4+K5 -> 4440 | N6: =+I6-K6 -> 458
H7: Despesas | I7: =+SUM(I22,O24,I29,O34,I38,O42,I51,O52,I57,O59,I64,O65,) -> 12013.3 | K7: =+SUM(J22,J29,J38,J51,J57,J64,P65,P59,P52,P42,P34,P24,) -> 3361 | N7: =+I7-K7 -> 8652.3
B8: Data | C8: Despesa | D8: Valor | E8: Área | H8: Saldo | I8: =+I6-I7 -> -7115.3 | K8: =+K6-K7 -> 1079 | N8: =I8-K8 -> -8194.3
D9: =SUM(D10:D112) -> 0
B10: 45748
B11: 45749 | H11: MORADIA | I11: Previsto | J11: Real | K11: Diferença | N11: TRANSPORTE | O11: Previsto | P11: Real | Q11: Diferença
B12: 45750 | G12: 1 | H12: Caixa de Emergência | I12: 150 | J12: =SUMIF(E$10:E$144,"1",D$10:D$144) -> 0 | K12: =+I12-J12 -> 150 | M12: 40 | N12: Uber 99 | O12: 58 | P12: 45 | Q12: =+O12-P12 -> 13
B13: 45751 | G13: 2 | H13: Inevitavelmento fixo | I13: 1200 | J13: =SUMIF(E$10:E$144,"2",D$10:D$144) -> 0 | K13: =+I13-J13 -> 1200 | M13: 41 | N13: Uber | O13: 68 | P13: =SUMIF(E$10:E$144,"41",D$10:D$144) -> 0 | Q13: =+O13-P13 -> 68
B14: 45752 | G14: 3 | H14: Das Jhenis | I14: 250 | J14: =SUMIF(E$10:E$144,"3",D$10:D$144) -> 0 | K14: =+I14-J14 -> 250 | M14: 42 | N14: Transporte Público | O14: 440 | P14: 0 | Q14: =+O14-P14 -> 440
B15: 45753 | G15: 4 | H15: Cartao Jhenismara | I15: 1200 | J15: 1400 | K15: =+I15-J15 -> -200 | M15: 43 | N15: Transporte Trabalho J | O15: 240 | P15: 143 | Q15: =+O15-P15 -> 97
B16: 45754 | G16: 5 | H16: Emergência Casa | I16: 120 | J16: =SUMIF(E$10:E$144,"5",D$10:D$144) -> 0 | K16: =+I16-J16 -> 120 | M16: 44 | N16: Transporte Trabalho M | O16: 110 | P16: 240 | Q16: =+O16-P16 -> -130
B17: 45755 | G17: 6 | H17: Energia | I17: 150 | J17: 150 | K17: =+I17-J17 -> 0 | M17: 45 | N17: Caixa Carro J | O17: 0 | P17: =SUMIF(E$10:E$144,"45",D$10:D$144) -> 0 | Q17: =+O17-P17 -> 0
B18: 45756 | G18: 7 | H18: Água | I18: 77 | J18: 77 | K18: =+I18-J18 -> 0 | M18: 46 | N18: Caixa Carro M | O18: 0 | P18: =SUMIF(E$10:E$144,"46",D$10:D$144) -> 0 | Q18: =+O18-P18 -> 0
B19: 45757 | G19: 8 | H19: Gás | I19: 55 | J19: 55 | K19: =+I19-J19 -> 0 | M19: 47 | O19: 0 | P19: =SUMIF(E$10:E$144,"47",D$10:D$144) -> 0 | Q19: =+O19-P19 -> 0
B20: 45758 | G20: 9 | H20: Cartao (Matheus) | I20: 175 | J20: 175 | K20: =+I20-J20 -> 0 | M20: 48 | O20: 0 | P20: =SUMIF(E$10:E$144,"48",D$10:D$144) -> 0 | Q20: =+O20-P20 -> 0
B21: 45759 | G21: 10 | H21: Outrs Dispesas | J21: =SUMIF(E$10:E$144,"10",D$10:D$144) -> 0 | K21: =+I21-J21 -> 0 | M21: 49 | O21: 0 | P21: 0 | Q21: =+O21-P21 -> 0
B22: 45760 | H22: TOTAL | I22: =SUM(I12:I21) -> 3377 | J22: =SUM(J12:J21) -> 1857 | K22: =+I22-J22 -> 1520 | M22: 50 | O22: 0 | P22: 0 | Q22: =+O22-P22 -> 0
B23: 45761 | M23: 51 | N23: Outros Transporte | O23: 0 | P23: =SUMIF(E$10:E$144,"51",D$10:D$144) -> 0 | Q23: =+O23-P23 -> 0
B24: 45762 | H24: ALIMENTAÇÃO | I24: Previsto | J24: Real | K24: Diferença | N24: TOTAL | O24: =SUM(O12:O23) -> 916 | P24: =SUM(P12:P23) -> 428 | Q24: =+O24-P24 -> 488
B25: 45763 | G25: 11 | H25: Supermercado | I25: 450 | J25: 450 | K25: =+I25-J25 -> 0
B26: 45764 | G26: 12 | H26: Restaurante | I26: 140 | J26: 140 | K26: =+I26-J26 -> 0 | N26: EDUCAÇÃO | O26: Previsto | P26: Real | Q26: Diferença
B27: 45765 | G27: 13 | H27: Café \ Almoço | I27: 100 | J27: 250 | K27: =+I27-J27 -> -150 | M27: 52 | N27: Mensalidades | O27: 0 | P27: =SUMIF(E$10:E$144,"52",D$10:D$144) -> 0 | Q27: =+O27-P27 -> 0
B28: 45766 | G28: 14 | H28: Pedidos IFood | I28: 140 | J28: =SUMIF(E$10:E$144,"14",D$10:D$144) -> 0 | K28: =+I28-J28 -> 140 | M28: 53 | N28: Idiomas | O28: 0 | P28: =SUMIF(E$10:E$144,"53",D$10:D$144) -> 0 | Q28: =+O28-P28 -> 0
B29: 45767 | H29: TOTAL | I29: =SUM(I25:I28) -> 830 | J29: =SUM(J25:J28) -> 840 | K29: =+I29-J29 -> -10 | M29: 54 | N29: CNH [Matheus] | O29: 0 | P29: =SUMIF(E$10:E$144,"54",D$10:D$144) -> 0 | Q29: =+O29-P29 -> 0
B30: 45768 | M30: 55 | N30: Cursos | O30: 140 | P30: =SUMIF(E$10:E$144,"55",D$10:D$144) -> 0 | Q30: =+O30-P30 -> 140
B31: 45769 | H31: COMUNICAÇÃO | I31: Previsto | J31: Real | K31: Diferença | M31: 56 | N31: Livros | O31: 0 | P31: =SUMIF(E$10:E$144,"56",D$10:D$144) -> 0 | Q31: =+O31-P31 -> 0
B32: 45770 | G32: 15 | H32: Celular | I32: 45 | J32: 45 | K32: =+I32-J32 -> 0 | M32: 57 | N32: Faculdade [Jhenis] | O32: 0 | P32: =SUMIF(E$10:E$144,"57",D$10:D$144) -> 0 | Q32: =+O32-P32 -> 0
B33: 45771 | G33: 16 | H33: Internet | I33: 89 | J33: 89 | K33: =+I33-J33 -> 0 | M33: 58 | N33: Outros Educação | O33: 0 | P33: =SUMIF(E$10:E$144,"58",D$10:D$144) -> 0 | Q33: =+O33-P33 -> 0
B34: 45772 | G34: 17 | H34: Streaming | I34: 24 | J34: 24 | K34: =+I34-J34 -> 0 | N34: TOTAL | O34: =SUM(O27:O33) -> 140 | P34: =SUM(P27:P33) -> 0 | Q34: =+O34-P34 -> 140
B35: 45773 | G35: 18 | H35: Netflix | I35: 21.9 | J35: 22 | K35: =+I35-J35 -> -0.1
B36: 45774 | G36: 19 | H36: Amazon | I36: 10.9 | J36: 11 | K36: =+I36-J36 -> -0.1 | N36: LAZER | O36: Previsto | P36: Real | Q36: Diferença
B37: 45775 | G37: 20 | H37: Max Plus | I37: 34.5 | J37: 45 | K37: =+I37-J37 -> -10.5 | M37: 60 | N37: Cinema | O37: 450 | P37: =SUMIF(E$10:E$144,"60",D$10:D$144) -> 0 | Q37: =+O37-P37 -> 450
B38: 45776 | H38: TOTAL | I38: =SUM(I32:I37) -> 225.3 | J38: =SUM(J32:J37) -> 236 | K38: =+I38-J38 -> -10.7 | M38: 61 | N38: Esportes | O38: 0 | P38: =SUMIF(E$10:E$144,"61",D$10:D$144) -> 0 | Q38: =+O38-P38 -> 0
B39: 45777 | M39: 62 | N39: Shows [Consertos] | O39: 120 | P39: =SUMIF(E$10:E$144,"62",D$10:D$144) -> 0 | Q39: =+O39-P39 -> 120
H40: SAÚDE E CUIDADOS | I40: Previsto | J40: Real | K40: Diferença | M40: 63 | N40: Viagens [Férias] | O40: 148 | P40: =SUMIF(E$10:E$144,"63",D$10:D$144) -> 0 | Q40: =+O40-P40 -> 148
G41: 21 | H41: Academia | I41: 120 | J41: =SUMIF(E$10:E$144,"21",D$10:D$144) -> 0 | K41: =+I41-J41 -> 120 | M41: 64 | N41: Outros Lazer | O41: 60 | P41: =SUMIF(E$10:E$144,"64",D$10:D$144) -> 0 | Q41: =+O41-P41 -> 60
G42: 22 | H42: Emergencia Médica | I42: 120 | J42: =SUMIF(E$10:E$144,"22",D$10:D$144) -> 0 | K42: =+I42-J42 -> 120 | N42: TOTAL | O42: =SUM(O37:O41) -> 778 | P42: =SUM(P37:P41) -> 0 | Q42: =+O42-P42 -> 778
G43: 23 | H43: Emergência Dentista | I43: 100 | J43: =SUMIF(E$10:E$144,"23",D$10:D$144) -> 0 | K43: =+I43-J43 -> 100
G44: 24 | H44: Cosméticos | I44: 100 | J44: =SUMIF(E$10:E$144,"24",D$10:D$144) -> 0 | K44: =+I44-J44 -> 100 | N44: Necessidades Da Casa | O44: Previsto | P44: Real | Q44: Diferença
G45: 25 | H45: Dentista | I45: 150 | J45: =SUMIF(E$10:E$144,"25",D$10:D$144) -> 0 | K45: =+I45-J45 -> 150 | M45: 70 | N45: Cama | O45: 0 | P45: =SUMIF(E$10:E$144,"70",D$10:D$144) -> 0 | Q45: =+O45-P45 -> 0
G46: 26 | H46: Exames médicos | I46: 0 | J46: =SUMIF(E$10:E$144,"26",D$10:D$144) -> 0 | K46: =+I46-J46 -> 0 | M46: 71 | N46: Consertos [ Futuros | O46: 0 | P46: =SUMIF(E$10:E$144,"71",D$10:D$144) -> 0 | Q46: =+O46-P46 -> 0
G47: 27 | H47: Farmácia | I47: 89 | J47: =SUMIF(E$10:E$144,"27",D$10:D$144) -> 0 | K47: =+I47-J47 -> 89 | M47: 72 | N47: Geladeira | O47: 0 | P47: =SUMIF(E$10:E$144,"72",D$10:D$144) -> 0 | Q47: =+O47-P47 -> 0
G48: 28 | H48: Médicos particular | I48: 0 | J48: =SUMIF(E$10:E$144,"28",D$10:D$144) -> 0 | K48: =+I48-J48 -> 0 | M48: 73 | N48: Lava e seca | O48: 0 | P48: =SUMIF(E$10:E$144,"73",D$10:D$144) -> 0 | Q48: =+O48-P48 -> 0
G49: 29 | H49: Suplementos | I49: 0 | J49: =SUMIF(E$10:E$144,"29",D$10:D$144) -> 0 | K49: =+I49-J49 -> 0 | M49: 74 | N49: Lavanderia louça | O49: 0 | P49: =SUMIF(E$10:E$144,"74",D$10:D$144) -> 0 | Q49: =+O49-P49 -> 0
G50: 30 | H50: Outros Saúde | I50: 0 | J50: =SUMIF(E$10:E$144,"30",D$10:D$144) -> 0 | K50: =+I50-J50 -> 0 | M50: 75 | N50: Utensílios e decoração | O50: 0 | P50: =SUMIF(E$10:E$144,"75",D$10:D$144) -> 0 | Q50: =+O50-P50 -> 0
H51: TOTAL | I51: =SUM(I41:I50) -> 679 | J51: =SUM(J41:J50) -> 0 | K51: =+I51-J51 -> 679 | M51: 76 | N51: Outros Artigos | O51: 0 | P51: =SUMIF(E$10:E$144,"76",D$10:D$144) -> 0 | Q51: =+O51-P51 -> 0
N52: TOTAL | O52: =SUM(O45:O51) -> 0 | P52: =SUM(P45:P51) -> 0 | Q52: =+O52-P52 -> 0
H53: VESTUÁRIO | I53: Previsto | J53: Real | K53: Diferença
G54: 31 | H54: Roupas | I54: 39 | J54: =SUMIF(E$10:E$144,"31",D$10:D$144) -> 0 | K54: =+I54-J54 -> 39 | N54: OUTROS | O54: Previsto | P54: Real | Q54: Diferença
G55: 32 | H55: Sapatos | I55: 0 | J55: =SUMIF(E$10:E$144,"32",D$10:D$144) -> 0 | K55: =+I55-J55 -> 0 | M55: 80 | N55: Presentes | O55: 89 | P55: =SUMIF(E$10:E$144,"80",D$10:D$144) -> 0 | Q55: =+O55-P55 -> 89
G56: 33 | H56: Outros Vestuário | I56: 0 | J56: =SUMIF(E$10:E$144,"33",D$10:D$144) -> 0 | K56: =+I56-J56 -> 0 | M56: 81 | N56: Doações | O56: 0 | P56: =SUMIF(E$10:E$144,"81",D$10:D$144) -> 0 | Q56: =+O56-P56 -> 0
H57: TOTAL | I57: =SUM(I54:I56) -> 39 | J57: =SUM(J54:J56) -> 0 | K57: =+I57-J57 -> 39 | M57: 82 | N57: Ensaio | O57: 140 | P57: =SUMIF(E$10:E$144,"82",D$10:D$144) -> 0 | Q57: =+O57-P57 -> 140
M58: 83 | N58: Outros | O58: 0 | P58: =SUMIF(E$10:E$144,"83",D$10:D$144) -> 0 | Q58: =+O58-P58 -> 0
H59: Investimentos | I59: Previsto | J59: Rendimento | K59: Dividendos | N59: TOTAL | O59: =SUM(O55:O58) -> 229 | P59: =SUM(P55:P58) -> 0 | Q59: =+O59-P59 -> 229
G60: 34 | H60: Renda Variavel | I60: 1200 | J60: =SUMIF(E$10:E$144,"34",D$10:D$144) -> 0 | K60: =+I60-O620 -> 1200
G61: 35 | H61: Fundos imobiliário | I61: 1200 | J61: =SUMIF(E$10:E$144,"35",D$10:D$144) -> 0 | K61: =+I61-J61 -> 1200 | N61: FINANCEIRO | O61: Previsto | P61: Real | Q61: Diferença
G62: 36 | H62: Ações Baixo Risco | I62: 1200 | J62: =SUMIF(E$10:E$144,"36",D$10:D$144) -> 0 | K62: =+I62-J62 -> 1200 | M62: 90 | N62: Investimentos Mensais | O62: 0 | P62: =SUMIF(E$10:E$144,"90",D$10:D$144) -> 0 | Q62: =+O62-P62 -> 0
B63: 45717 | G63: 37 | H63: Ações Altos Risco | I63: 1200 | J63: =SUMIF(E$10:E$144,"37",D$10:D$144) -> 0 | K63: =+I63-J63 -> 1200 | M63: 91 | N63: Cartas de Crédito | O63: 0 | P63: =SUMIF(E$10:E$144,"91",D$10:D$144) -> 0 | Q63: =+O63-P63 -> 0
B64: 45718 | H64: TOTAL | I64: =SUM(I60:I63) -> 4800 | J64: =SUM(J60:J63) -> 0 | K64: =+I64-J64 -> 4800 | M64: 92 | N64: Outros Financeiro | O64: 0 | P64: =SUMIF(E$10:E$144,"92",D$10:D$144) -> 0 | Q64: =+O64-P64 -> 0
B65: 45719 | N65: TOTAL | O65: =SUM(O62:O64) -> 0 | P65: =SUM(P62:P64) -> 0 | Q65: =+O65-P65 -> 0
B66: 45720
B67: 45721
B68: 45722
B69: 45723
B70: 45724
B71: 45725
B72: 45726
B73: 45727
B74: 45728
B75: 45729
B76: 45730
B77: 45731
... B94: 45748

Sheet MAI
A1: Lançamento de Compras e Gastos Casa Organizada
I3: Previsto | K3: Real | N3: Diferença
H4: Renda 1 | I4: 2398 | J4: 1940 | K4: 1940 | N4: =I4-K4 -> 458
H5: Renda 2 | I5: 2500 | J5: 2500 | K5: 2500 | N5: =I5-J5 -> 0
B6: Despesas Mensais | H6: Renda Total | I6: =+I4+I5 -> 4898 | K6: =+K4+K5 -> 4440 | N6: =+I6-K6 -> 458
H7: Despesas | I7: =+SUM(I22,O24,I29,O34,I38,O42,I51,O52,I57,O59,I64,O65,) -> 12013.3 | K7: =+SUM(J22,J29,J38,J51,J57,J64,P65,P59,P52,P42,P34,P24,) -> 3361 | N7: =+I7-K7 -> 8652.3
B8: Data | C8: Despesa | D8: Valor | E8: Área | H8: Saldo | I8: =+I6-I7 -> -7115.3 | K8: =+K6-K7 -> 1079 | N8: =I8-K8 -> -8194.3
D9: =SUM(D10:D112) -> 0
B10: 45778
B11: 45779 | H11: MORADIA | I11: Previsto | J11: Real | K11: Diferença | N11: TRANSPORTE | O11: Previsto | P11: Real | Q11: Diferença
B12: 45780 | G12: 1 | H12: Caixa de Emergência | I12: 150 | J12: =SUMIF(E$10:E$144,"1",D$10:D$144) -> 0 | K12: =+I12-J12 -> 150 | M12: 40 | N12: Uber 99 | O12: 58 | P12: 45 | Q12: =+O12-P12 -> 13
B13: 45781 | G13: 2 | H13: Inevitavelmento fixo | I13: 1200 | J13: =SUMIF(E$10:E$144,"2",D$10:D$144) -> 0 | K13: =+I13-J13 -> 1200 | M13: 41 | N13: Uber | O13: 68 | P13: =SUMIF(E$10:E$144,"41",D$10:D$144) -> 0 | Q13: =+O13-P13 -> 68
B14: 45782 | G14: 3 | H14: Das Jhenis | I14: 250 | J14: =SUMIF(E$10:E$144,"3",D$10:D$144) -> 0 | K14: =+I14-J14 -> 250 | M14: 42 | N14: Transporte Público | O14: 440 | P14: 0 | Q14: =+O14-P14 -> 440
B15: 45783 | G15: 4 | H15: Cartao Jhenismara | I15: 1200 | J15: 1400 | K15: =+I15-J15 -> -200 | M15: 43 | N15: Transporte Trabalho J | O15: 240 | P15: 143 | Q15: =+O15-P15 -> 97
B16: 45784 | G16: 5 | H16: Emergência Casa | I16: 120 | J16: =SUMIF(E$10:E$144,"5",D$10:D$144) -> 0 | K16: =+I16-J16 -> 120 | M16: 44 | N16: Transporte Trabalho M | O16: 110 | P16: 240 | Q16: =+O16-P16 -> -130
B17: 45785 | G17: 6 | H17: Energia | I17: 150 | J17: 150 | K17: =+I17-J17 -> 0 | M17: 45 | N17: Caixa Carro J | O17: 0 | P17: =SUMIF(E$10:E$144,"45",D$10:D$144) -> 0 | Q17: =+O17-P17 -> 0
B18: 45786 | G18: 7 | H18: Água | I18: 77 | J18: 77 | K18: =+I18-J18 -> 0 | M18: 46 | N18: Caixa Carro M | O18: 0 | P18: =SUMIF(E$10:E$144,"46",D$10:D$144) -> 0 | Q18: =+O18-P18 -> 0
B19: 45787 | G19: 8 | H19: Gás | I19: 55 | J19: 55 | K19: =+I19-J19 -> 0 | M19: 47 | O19: 0 | P19: =SUMIF(E$10:E$144,"47",D$10:D$144) -> 0 | Q19: =+O19-P19 -> 0
B20: 45788 | G20: 9 | H20: Cartao (Matheus) | I20: 175 | J20: 175 | K20: =+I20-J20 -> 0 | M20: 48 | O20: 0 | P20: =SUMIF(E$10:E$144,"48",D$10:D$144) -> 0 | Q20: =+O20-P20 -> 0
B21: 45789 | G21: 10 | H21: Outrs Dispesas | J21: =SUMIF(E$10:E$144,"10",D$10:D$144) -> 0 | K21: =+I21-J21 -> 0 | M21: 49 | O21: 0 | P21: 0 | Q21: =+O21-P21 -> 0
B22: 45790 | H22: TOTAL | I22: =SUM(I12:I21) -> 3377 | J22: =SUM(J12:J21) -> 1857 | K22: =+I22-J22 -> 1520 | M22: 50 | O22: 0 | P22: 0 | Q22: =+O22-P22 -> 0
B23: 45791 | M23: 51 | N23: Outros Transporte | O23: 0 | P23: =SUMIF(E$10:E$144,"51",D$10:D$144) -> 0 | Q23: =+O23-P23 -> 0
B24: 45792 | H24: ALIMENTAÇÃO | I24: Previsto | J24: Real | K24: Diferença | N24: TOTAL | O24: =SUM(O12:O23) -> 916 | P24: =SUM(P12:P23) -> 428 | Q24: =+O24-P24 -> 488
B25: 45793 | G25: 11 | H25: Supermercado | I25: 450 | J25: 450 | K25: =+I25-J25 -> 0
B26: 45794 | G26: 12 | H26: Restaurante | I26: 140 | J26: 140 | K26: =+I26-J26 -> 0 | N26: EDUCAÇÃO | O26: Previsto | P26: Real | Q26: Diferença
B27: 45795 | G27: 13 | H27: Café \ Almoço | I27: 100 | J27: 250 | K27: =+I27-J27 -> -150 | M27: 52 | N27: Mensalidades | O27: 0 | P27: =SUMIF(E$10:E$144,"52",D$10:D$144) -> 0 | Q27: =+O27-P27 -> 0
B28: 45796 | G28: 14 | H28: Pedidos IFood | I28: 140 | J28: =SUMIF(E$10:E$144,"14",D$10:D$144) -> 0 | K28: =+I28-J28 -> 140 | M28: 53 | N28: Idiomas | O28: 0 | P28: =SUMIF(E$10:E$144,"53",D$10:D$144) -> 0 | Q28: =+O28-P28 -> 0
B29: 45797 | H29: TOTAL | I29: =SUM(I25:I28) -> 830 | J29: =SUM(J25:J28) -> 840 | K29: =+I29-J29 -> -10 | M29: 54 | N29: CNH [Matheus] | O29: 0 | P29: =SUMIF(E$10:E$144,"54",D$10:D$144) -> 0 | Q29: =+O29-P29 -> 0
B30: 45798 | M30: 55 | N30: Cursos | O30: 140 | P30: =SUMIF(E$10:E$144,"55",D$10:D$144) -> 0 | Q30: =+O30-P30 -> 140
B31: 45799 | H31: COMUNICAÇÃO | I31: Previsto | J31: Real | K31: Diferença | M31: 56 | N31: Livros | O31: 0 | P31: =SUMIF(E$10:E$144,"56",D$10:D$144) -> 0 | Q31: =+O31-P31 -> 0
B32: 45800 | G32: 15 | H32: Celular | I32: 45 | J32: 45 | K32: =+I32-J32 -> 0 | M32: 57 | N32: Faculdade [Jhenis] | O32: 0 | P32: =SUMIF(E$10:E$144,"57",D$10:D$144) -> 0 | Q32: =+O32-P32 -> 0
B33: 45801 | G33: 16 | H33: Internet | I33: 89 | J33: 89 | K33: =+I33-J33 -> 0 | M33: 58 | N33: Outros Educação | O33: 0 | P33: =SUMIF(E$10:E$144,"58",D$10:D$144) -> 0 | Q33: =+O33-P33 -> 0
B34: 45802 | G34: 17 | H34: Streaming | I34: 24 | J34: 24 | K34: =+I34-J34 -> 0 | N34: TOTAL | O34: =SUM(O27:O33) -> 140 | P34: =SUM(P27:P33) -> 0 | Q34: =+O34-P34 -> 140
B35: 45803 | G35: 18 | H35: Netflix | I35: 21.9 | J35: 22 | K35: =+I35-J35 -> -0.1
B36: 45804 | G36: 19 | H36: Amazon | I36: 10.9 | J36: 11 | K36: =+I36-J36 -> -0.1 | N36: LAZER | O36: Previsto | P36: Real | Q36: Diferença
B37: 45805 | G37: 20 | H37: Max Plus | I37: 34.5 | J37: 45 | K37: =+I37-J37 -> -10.5 | M37: 60 | N37: Cinema | O37: 450 | P37: =SUMIF(E$10:E$144,"60",D$10:D$144) -> 0 | Q37: =+O37-P37 -> 450
B38: 45806 | H38: TOTAL | I38: =SUM(I32:I37) -> 225.3 | J38: =SUM(J32:J37) -> 236 | K38: =+I38-J38 -> -10.7 | M38: 61 | N38: Esportes | O38: 0 | P38: =SUMIF(E$10:E$144,"61",D$10:D$144) -> 0 | Q38: =+O38-P38 -> 0
B39: 45807 | M39: 62 | N39: Shows [Consertos] | O39: 120 | P39: =SUMIF(E$10:E$144,"62",D$10:D$144) -> 0 | Q39: =+O39-P39 -> 120
H40: SAÚDE E CUIDADOS | I40: Previsto | J40: Real | K40: Diferença | M40: 63 | N40: Viagens [Férias] | O40: 148 | P40: =SUMIF(E$10:E$144,"63",D$10:D$144) -> 0 | Q40: =+O40-P40 -> 148
G41: 21 | H41: Academia | I41: 120 | J41: =SUMIF(E$10:E$144,"21",D$10:D$144) -> 0 | K41: =+I41-J41 -> 120 | M41: 64 | N41: Outros Lazer | O41: 60 | P41: =SUMIF(E$10:E$144,"64",D$10:D$144) -> 0 | Q41: =+O41-P41 -> 60
G42: 22 | H42: Emergencia Médica | I42: 120 | J42: =SUMIF(E$10:E$144,"22",D$10:D$144) -> 0 | K42: =+I42-J42 -> 120 | N42: TOTAL | O42: =SUM(O37:O41) -> 778 | P42: =SUM(P37:P41) -> 0 | Q42: =+O42-P42 -> 778
G43: 23 | H43: Emergência Dentista | I43: 100 | J43: =SUMIF(E$10:E$144,"23",D$10:D$144) -> 0 | K43: =+I43-J43 -> 100
G44: 24 | H44: Cosméticos | I44: 100 | J44: =SUMIF(E$10:E$144,"24",D$10:D$144) -> 0 | K44: =+I44-J44 -> 100 | N44: Necessidades Da Casa | O44: Previsto | P44: Real | Q44: Diferença
G45: 25 | H45: Dentista | I45: 150 | J45: =SUMIF(E$10:E$144,"25",D$10:D$144) -> 0 | K45: =+I45-J45 -> 150 | M45: 70 | N45: Cama | O45: 0 | P45: =SUMIF(E$10:E$144,"70",D$10:D$144) -> 0 | Q45: =+O45-P45 -> 0
G46: 26 | H46: Exames médicos | I46: 0 | J46: =SUMIF(E$10:E$144,"26",D$10:D$144) -> 0 | K46: =+I46-J46 -> 0 | M46: 71 | N46: Consertos [ Futuros | O46: 0 | P46: =SUMIF(E$10:E$144,"71",D$10:D$144) -> 0 | Q46: =+O46-P46 -> 0
G47: 27 | H47: Farmácia | I47: 89 | J47: =SUMIF(E$10:E$144,"27",D$10:D$144) -> 0 | K47: =+I47-J47 -> 89 | M47: 72 | N47: Geladeira | O47: 0 | P47: =SUMIF(E$10:E$144,"72",D$10:D$144) -> 0 | Q47: =+O47-P47 -> 0
G48: 28 | H48: Médicos particular | I48: 0 | J48: =SUMIF(E$10:E$144,"28",D$10:D$144) -> 0 | K48: =+I48-J48 -> 0 | M48: 73 | N48: Lava e seca | O48: 0 | P48: =SUMIF(E$10:E$144,"73",D$10:D$144) -> 0 | Q48: =+O48-P48 -> 0
G49: 29 | H49: Suplementos | I49: 0 | J49: =SUMIF(E$10:E$144,"29",D$10:D$144) -> 0 | K49: =+I49-J49 -> 0 | M49: 74 | N49: Lavanderia louça | O49: 0 | P49: =SUMIF(E$10:E$144,"74",D$10:D$144) -> 0 | Q49: =+O49-P49 -> 0
G50: 30 | H50: Outros Saúde | I50: 0 | J50: =SUMIF(E$10:E$144,"30",D$10:D$144) -> 0 | K50: =+I50-J50 -> 0 | M50: 75 | N50: Utensílios e decoração | O50: 0 | P50: =SUMIF(E$10:E$144,"75",D$10:D$144) -> 0 | Q50: =+O50-P50 -> 0
H51: TOTAL | I51: =SUM(I41:I50) -> 679 | J51: =SUM(J41:J50) -> 0 | K51: =+I51-J51 -> 679 | M51: 76 | N51: Outros Artigos | O51: 0 | P51: =SUMIF(E$10:E$144,"76",D$10:D$144) -> 0 | Q51: =+O51-P51 -> 0
N52: TOTAL | O52: =SUM(O45:O51) -> 0 | P52: =SUM(P45:P51) -> 0 | Q52: =+O52-P52 -> 0
H53: VESTUÁRIO | I53: Previsto | J53: Real | K53: Diferença
G54: 31 | H54: Roupas | I54: 39 | J54: =SUMIF(E$10:E$144,"31",D$10:D$144) -> 0 | K54: =+I54-J54 -> 39 | N54: OUTROS | O54: Previsto | P54: Real | Q54: Diferença
G55: 32 | H55: Sapatos | I55: 0 | J55: =SUMIF(E$10:E$144,"32",D$10:D$144) -> 0 | K55: =+I55-J55 -> 0 | M55: 80 | N55: Presentes | O55: 89 | P55: =SUMIF(E$10:E$144,"80",D$10:D$144) -> 0 | Q55: =+O55-P55 -> 89
G56: 33 | H56: Outros Vestuário | I56: 0 | J56: =SUMIF(E$10:E$144,"33",D$10:D$144) -> 0 | K56: =+I56-J56 -> 0 | M56: 81 | N56: Doações | O56: 0 | P56: =SUMIF(E$10:E$144,"81",D$10:D$144) -> 0 | Q56: =+O56-P56 -> 0
H57: TOTAL | I57: =SUM(I54:I56) -> 39 | J57: =SUM(J54:J56) -> 0 | K57: =+I57-J57 -> 39 | M57: 82 | N57: Ensaio | O57: 140 | P57: =SUMIF(E$10:E$144,"82",D$10:D$144) -> 0 | Q57: =+O57-P57 -> 140
M58: 83 | N58: Outros | O58: 0 | P58: =SUMIF(E$10:E$144,"83",D$10:D$144) -> 0 | Q58: =+O58-P58 -> 0
H59: Investimentos | I59: Previsto | J59: Rendimento | K59: Dividendos | N59: TOTAL | O59: =SUM(O55:O58) -> 229 | P59: =SUM(P55:P58) -> 0 | Q59: =+O59-P59 -> 229
G60: 34 | H60: Renda Variavel | I60: 1200 | J60: =SUMIF(E$10:E$144,"34",D$10:D$144) -> 0 | K60: =+I60-O620 -> 1200
G61: 35 | H61: Fundos imobiliário | I61: 1200 | J61: =SUMIF(E$10:E$144,"35",D$10:D$144) -> 0 | K61: =+I61-J61 -> 1200 | N61: FINANCEIRO | O61: Previsto | P61: Real | Q61: Diferença
G62: 36 | H62: Ações Baixo Risco | I62: 1200 | J62: =SUMIF(E$10:E$144,"36",D$10:D$144) -> 0 | K62: =+I62-J62 -> 1200 | M62: 90 | N62: Investimentos Mensais | O62: 0 | P62: =SUMIF(E$10:E$144,"90",D$10:D$144) -> 0 | Q62: =+O62-P62 -> 0
G63: 37 | H63: Ações Altos Risco | I63: 1200 | J63: =SUMIF(E$10:E$144,"37",D$10:D$144) -> 0 | K63: =+I63-J63 -> 1200 | M63: 91 | N63: Cartas de Crédito | O63: 0 | P63: =SUMIF(E$10:E$144,"91",D$10:D$144) -> 0 | Q63: =+O63-P63 -> 0
H64: TOTAL | I64: =SUM(I60:I63) -> 4800 | J64: =SUM(J60:J63) -> 0 | K64: =+I64-J64 -> 4800 | M64: 92 | N64: Outros Financeiro | O64: 0 | P64: =SUMIF(E$10:E$144,"92",D$10:D$144) -> 0 | Q64: =+O64-P64 -> 0
N65: TOTAL | O65: =SUM(O62:O64) -> 0 | P65: =SUM(P62:P64) -> 0 | Q65: =+O65-P65 -> 0

Sheet JUN
B1: Lançamento de Compras e Gastos Casa Organizada
I3: Previsto | K3: Real | N3: Diferença
H4: Renda 1 | I4: 2398 | J4: 1940 | K4: 1940 | N4: =I4-K4 -> 458
H5: Renda 2 | I5: 2500 | J5: 2500 | K5: 2500 | N5: =I5-J5 -> 0
B6: Despesas Mensais | H6: Renda Total | I6: =+I4+I5 -> 4898 | K6: =+K4+K5 -> 4440 | N6: =+I6-K6 -> 458
H7: Despesas | I7: =+SUM(I22,O24,I29,O34,I38,O42,I51,O52,I57,O59,I64,O65,) -> 12013.3 | K7: =+SUM(J22,J29,J38,J51,J57,J64,P65,P59,P52,P42,P34,P24,) -> 3361 | N7: =+I7-K7 -> 8652.3
B8: Data | C8: Despesa | D8: Valor | E8: Área | H8: Saldo | I8: =+I6-I7 -> -7115.3 | K8: =+K6-K7 -> 1079 | N8: =I8-K8 -> -8194.3
D9: =SUM(D10:D112) -> 0
B10: 45809
B11: 45810 | H11: MORADIA | I11: Previsto | J11: Real | K11: Diferença | N11: TRANSPORTE | O11: Previsto | P11: Real | Q11: Diferença
B12: 45811 | G12: 1 | H12: Caixa de Emergência | I12: 150 | J12: =SUMIF(E$10:E$144,"1",D$10:D$144) -> 0 | K12: =+I12-J12 -> 150 | M12: 40 | N12: Uber 99 | O12: 58 | P12: 45 | Q12: =+O12-P12 -> 13
B13: 45812 | G13: 2 | H13: Inevitavelmento fixo | I13: 1200 | J13: =SUMIF(E$10:E$144,"2",D$10:D$144) -> 0 | K13: =+I13-J13 -> 1200 | M13: 41 | N13: Uber | O13: 68 | P13: =SUMIF(E$10:E$144,"41",D$10:D$144) -> 0 | Q13: =+O13-P13 -> 68
B14: 45813 | G14: 3 | H14: Das Jhenis | I14: 250 | J14: =SUMIF(E$10:E$144,"3",D$10:D$144) -> 0 | K14: =+I14-J14 -> 250 | M14: 42 | N14: Transporte Público | O14: 440 | P14: 0 | Q14: =+O14-P14 -> 440
B15: 45814 | G15: 4 | H15: Cartao Jhenismara | I15: 1200 | J15: 1400 | K15: =+I15-J15 -> -200 | M15: 43 | N15: Transporte Trabalho J | O15: 240 | P15: 143 | Q15: =+O15-P15 -> 97
B16: 45815 | G16: 5 | H16: Emergência Casa | I16: 120 | J16: =SUMIF(E$10:E$144,"5",D$10:D$144) -> 0 | K16: =+I16-J16 -> 120 | M16: 44 | N16: Transporte Trabalho M | O16: 110 | P16: 240 | Q16: =+O16-P16 -> -130
B17: 45816 | G17: 6 | H17: Energia | I17: 150 | J17: 150 | K17: =+I17-J17 -> 0 | M17: 45 | N17: Caixa Carro J | O17: 0 | P17: =SUMIF(E$10:E$144,"45",D$10:D$144) -> 0 | Q17: =+O17-P17 -> 0
B18: 45817 | G18: 7 | H18: Água | I18: 77 | J18: 77 | K18: =+I18-J18 -> 0 | M18: 46 | N18: Caixa Carro M | O18: 0 | P18: =SUMIF(E$10:E$144,"46",D$10:D$144) -> 0 | Q18: =+O18-P18 -> 0
B19: 45818 | G19: 8 | H19: Gás | I19: 55 | J19: 55 | K19: =+I19-J19 -> 0 | M19: 47 | O19: 0 | P19: =SUMIF(E$10:E$144,"47",D$10:D$144) -> 0 | Q19: =+O19-P19 -> 0
B20: 45819 | G20: 9 | H20: Cartao (Matheus) | I20: 175 | J20: 175 | K20: =+I20-J20 -> 0 | M20: 48 | O20: 0 | P20: =SUMIF(E$10:E$144,"48",D$10:D$144) -> 0 | Q20: =+O20-P20 -> 0
B21: 45820 | G21: 10 | H21: Outrs Dispesas | J21: =SUMIF(E$10:E$144,"10",D$10:D$144) -> 0 | K21: =+I21-J21 -> 0 | M21: 49 | O21: 0 | P21: 0 | Q21: =+O21-P21 -> 0
B22: 45821 | H22: TOTAL | I22: =SUM(I12:I21) -> 3377 | J22: =SUM(J12:J21) -> 1857 | K22: =+I22-J22 -> 1520 | M22: 50 | O22: 0 | P22: 0 | Q22: =+O22-P22 -> 0
B23: 45822 | M23: 51 | N23: Outros Transporte | O23: 0 | P23: =SUMIF(E$10:E$144,"51",D$10:D$144) -> 0 | Q23: =+O23-P23 -> 0
B24: 45823 | H24: ALIMENTAÇÃO | I24: Previsto | J24: Real | K24: Diferença | N24: TOTAL | O24: =SUM(O12:O23) -> 916 | P24: =SUM(P12:P23) -> 428 | Q24: =+O24-P24 -> 488
B25: 45824 | G25: 11 | H25: Supermercado | I25: 450 | J25: 450 | K25: =+I25-J25 -> 0
B26: 45825 | G26: 12 | H26: Restaurante | I26: 140 | J26: 140 | K26: =+I26-J26 -> 0 | N26: EDUCAÇÃO | O26: Previsto | P26: Real | Q26: Diferença
B27: 45826 | G27: 13 | H27: Café \ Almoço | I27: 100 | J27: 250 | K27: =+I27-J27 -> -150 | M27: 52 | N27: Mensalidades | O27: 0 | P27: =SUMIF(E$10:E$144,"52",D$10:D$144) -> 0 | Q27: =+O27-P27 -> 0
B28: 45827 | G28: 14 | H28: Pedidos IFood | I28: 140 | J28: =SUMIF(E$10:E$144,"14",D$10:D$144) -> 0 | K28: =+I28-J28 -> 140 | M28: 53 | N28: Idiomas | O28: 0 | P28: =SUMIF(E$10:E$144,"53",D$10:D$144) -> 0 | Q28: =+O28-P28 -> 0
B29: 45828 | H29: TOTAL | I29: =SUM(I25:I28) -> 830 | J29: =SUM(J25:J28) -> 840 | K29: =+I29-J29 -> -10 | M29: 54 | N29: CNH [Matheus] | O29: 0 | P29: =SUMIF(E$10:E$144,"54",D$10:D$144) -> 0 | Q29: =+O29-P29 -> 0
B30: 45829 | M30: 55 | N30: Cursos | O30: 140 | P30: =SUMIF(E$10:E$144,"55",D$10:D$144) -> 0 | Q30: =+O30-P30 -> 140
B31: 45830 | H31: COMUNICAÇÃO | I31: Previsto | J31: Real | K31: Diferença | M31: 56 | N31: Livros | O31: 0 | P31: =SUMIF(E$10:E$144,"56",D$10:D$144) -> 0 | Q31: =+O31-P31 -> 0
B32: 45831 | G32: 15 | H32: Celular | I32: 45 | J32: 45 | K32: =+I32-J32 -> 0 | M32: 57 | N32: Faculdade [Jhenis] | O32: 0 | P32: =SUMIF(E$10:E$144,"57",D$10:D$144) -> 0 | Q32: =+O32-P32 -> 0
B33: 45832 | G33: 16 | H33: Internet | I33: 89 | J33: 89 | K33: =+I33-J33 -> 0 | M33: 58 | N33: Outros Educação | O33: 0 | P33: =SUMIF(E$10:E$144,"58",D$10:D$144) -> 0 | Q33: =+O33-P33 -> 0
B34: 45833 | G34: 17 | H34: Streaming | I34: 24 | J34: 24 | K34: =+I34-J34 -> 0 | N34: TOTAL | O34: =SUM(O27:O33) -> 140 | P34: =SUM(P27:P33) -> 0 | Q34: =+O34-P34 -> 140
B35: 45834 | G35: 18 | H35: Netflix | I35: 21.9 | J35: 22 | K35: =+I35-J35 -> -0.1
B36: 45835 | G36: 19 | H36: Amazon | I36: 10.9 | J36: 11 | K36: =+I36-J36 -> -0.1 | N36: LAZER | O36: Previsto | P36: Real | Q36: Diferença
B37: 45836 | G37: 20 | H37: Max Plus | I37: 34.5 | J37: 45 | K37: =+I37-J37 -> -10.5 | M37: 60 | N37: Cinema | O37: 450 | P37: =SUMIF(E$10:E$144,"60",D$10:D$144) -> 0 | Q37: =+O37-P37 -> 450
B38: 45837 | H38: TOTAL | I38: =SUM(I32:I37) -> 225.3 | J38: =SUM(J32:J37) -> 236 | K38: =+I38-J38 -> -10.7 | M38: 61 | N38: Esportes | O38: 0 | P38: =SUMIF(E$10:E$144,"61",D$10:D$144) -> 0 | Q38: =+O38-P38 -> 0
B39: 45838 | M39: 62 | N39: Shows [Consertos] | O39: 120 | P39: =SUMIF(E$10:E$144,"62",D$10:D$144) -> 0 | Q39: =+O39-P39 -> 120
H40: SAÚDE E CUIDADOS | I40: Previsto | J40: Real | K40: Diferença | M40: 63 | N40: Viagens [Férias] | O40: 148 | P40: =SUMIF(E$10:E$144,"63",D$10:D$144) -> 0 | Q40: =+O40-P40 -> 148
G41: 21 | H41: Academia | I41: 120 | J41: =SUMIF(E$10:E$144,"21",D$10:D$144) -> 0 | K41: =+I41-J41 -> 120 | M41: 64 | N41: Outros Lazer | O41: 60 | P41: =SUMIF(E$10:E$144,"64",D$10:D$144) -> 0 | Q41: =+O41-P41 -> 60
G42: 22 | H42: Emergencia Médica | I42: 120 | J42: =SUMIF(E$10:E$144,"22",D$10:D$144) -> 0 | K42: =+I42-J42 -> 120 | N42: TOTAL | O42: =SUM(O37:O41) -> 778 | P42: =SUM(P37:P41) -> 0 | Q42: =+O42-P42 -> 778
G43: 23 | H43: Emergência Dentista | I43: 100 | J43: =SUMIF(E$10:E$144,"23",D$10:D$144) -> 0 | K43: =+I43-J43 -> 100
G44: 24 | H44: Cosméticos | I44: 100 | J44: =SUMIF(E$10:E$144,"24",D$10:D$144) -> 0 | K44: =+I44-J44 -> 100 | N44: Necessidades Da Casa | O44: Previsto | P44: Real | Q44: Diferença
G45: 25 | H45: Dentista | I45: 150 | J45: =SUMIF(E$10:E$144,"25",D$10:D$144) -> 0 | K45: =+I45-J45 -> 150 | M45: 70 | N45: Cama | O45: 0 | P45: =SUMIF(E$10:E$144,"70",D$10:D$144) -> 0 | Q45: =+O45-P45 -> 0
G46: 26 | H46: Exames médicos | I46: 0 | J46: =SUMIF(E$10:E$144,"26",D$10:D$144) -> 0 | K46: =+I46-J46 -> 0 | M46: 71 | N46: Consertos [ Futuros | O46: 0 | P46: =SUMIF(E$10:E$144,"71",D$10:D$144) -> 0 | Q46: =+O46-P46 -> 0
G47: 27 | H47: Farmácia | I47: 89 | J47: =SUMIF(E$10:E$144,"27",D$10:D$144) -> 0 | K47: =+I47-J47 -> 89 | M47: 72 | N47: Geladeira | O47: 0 | P47: =SUMIF(E$10:E$144,"72",D$10:D$144) -> 0 | Q47: =+O47-P47 -> 0
G48: 28 | H48: Médicos particular | I48: 0 | J48: =SUMIF(E$10:E$144,"28",D$10:D$144) -> 0 | K48: =+I48-J48 -> 0 | M48: 73 | N48: Lava e seca | O48: 0 | P48: =SUMIF(E$10:E$144,"73",D$10:D$144) -> 0 | Q48: =+O48-P48 -> 0
G49: 29 | H49: Suplementos | I49: 0 | J49: =SUMIF(E$10:E$144,"29",D$10:D$144) -> 0 | K49: =+I49-J49 -> 0 | M49: 74 | N49: Lavanderia louça | O49: 0 | P49: =SUMIF(E$10:E$144,"74",D$10:D$144) -> 0 | Q49: =+O49-P49 -> 0
G50: 30 | H50: Outros Saúde | I50: 0 | J50: =SUMIF(E$10:E$144,"30",D$10:D$144) -> 0 | K50: =+I50-J50 -> 0 | M50: 75 | N50: Utensílios e decoração | O50: 0 | P50: =SUMIF(E$10:E$144,"75",D$10:D$144) -> 0 | Q50: =+O50-P50 -> 0
H51: TOTAL | I51: =SUM(I41:I50) -> 679 | J51: =SUM(J41:J50) -> 0 | K51: =+I51-J51 -> 679 | M51: 76 | N51: Outros Artigos | O51: 0 | P51: =SUMIF(E$10:E$144,"76",D$10:D$144) -> 0 | Q51: =+O51-P51 -> 0
N52: TOTAL | O52: =SUM(O45:O51) -> 0 | P52: =SUM(P45:P51) -> 0 | Q52: =+O52-P52 -> 0
H53: VESTUÁRIO | I53: Previsto | J53: Real | K53: Diferença
G54: 31 | H54: Roupas | I54: 39 | J54: =SUMIF(E$10:E$144,"31",D$10:D$144) -> 0 | K54: =+I54-J54 -> 39 | N54: OUTROS | O54: Previsto | P54: Real | Q54: Diferença
G55: 32 | H55: Sapatos | I55: 0 | J55: =SUMIF(E$10:E$144,"32",D$10:D$144) -> 0 | K55: =+I55-J55 -> 0 | M55: 80 | N55: Presentes | O55: 89 | P55: =SUMIF(E$10:E$144,"80",D$10:D$144) -> 0 | Q55: =+O55-P55 -> 89
G56: 33 | H56: Outros Vestuário | I56: 0 | J56: =SUMIF(E$10:E$144,"33",D$10:D$144) -> 0 | K56: =+I56-J56 -> 0 | M56: 81 | N56: Doações | O56: 0 | P56: =SUMIF(E$10:E$144,"81",D$10:D$144) -> 0 | Q56: =+O56-P56 -> 0
H57: TOTAL | I57: =SUM(I54:I56) -> 39 | J57: =SUM(J54:J56) -> 0 | K57: =+I57-J57 -> 39 | M57: 82 | N57: Ensaio | O57: 140 | P57: =SUMIF(E$10:E$144,"82",D$10:D$144) -> 0 | Q57: =+O57-P57 -> 140
M58: 83 | N58: Outros | O58: 0 | P58: =SUMIF(E$10:E$144,"83",D$10:D$144) -> 0 | Q58: =+O58-P58 -> 0
H59: Investimentos | I59: Previsto | J59: Rendimento | K59: Dividendos | N59: TOTAL | O59: =SUM(O55:O58) -> 229 | P59: =SUM(P55:P58) -> 0 | Q59: =+O59-P59 -> 229
G60: 34 | H60: Renda Variavel | I60: 1200 | J60: =SUMIF(E$10:E$144,"34",D$10:D$144) -> 0 | K60: =+I60-O620 -> 1200
G61: 35 | H61: Fundos imobiliário | I61: 1200 | J61: =SUMIF(E$10:E$144,"35",D$10:D$144) -> 0 | K61: =+I61-J61 -> 1200 | N61: FINANCEIRO | O61: Previsto | P61: Real | Q61: Diferença
G62: 36 | H62: Ações Baixo Risco | I62: 1200 | J62: =SUMIF(E$10:E$144,"36",D$10:D$144) -> 0 | K62: =+I62-J62 -> 1200 | M62: 90 | N62: Investimentos Mensais | O62: 0 | P62: =SUMIF(E$10:E$144,"90",D$10:D$144) -> 0 | Q62: =+O62-P62 -> 0
G63: 37 | H63: Ações Altos Risco | I63: 1200 | J63: =SUMIF(E$10:E$144,"37",D$10:D$144) -> 0 | K63: =+I63-J63 -> 1200 | M63: 91 | N63: Cartas de Crédito | O63: 0 | P63: =SUMIF(E$10:E$144,"91",D$10:D$144) -> 0 | Q63: =+O63-P63 -> 0
H64: TOTAL | I64: =SUM(I60:I63) -> 4800 | J64: =SUM(J60:J63) -> 0 | K64: =+I64-J64 -> 4800 | M64: 92 | N64: Outros Financeiro | O64: 0 | P64: =SUMIF(E$10:E$144,"92",D$10:D$144) -> 0 | Q64: =+O64-P64 -> 0
N65: TOTAL | O65: =SUM(O62:O64) -> 0 | P65: =SUM(P62:P64) -> 0 | Q65: =+O65-P65 -> 0

Sheet JUL
B1: Lançamento de Compras e Gastos Casa Organizada
I3: Previsto | K3: Real | N3: Diferença
H4: Renda 1 | I4: 2398 | J4: 1940 | K4: 1940 | N4: =I4-K4 -> 458
H5: Renda 2 | I5: 2500 | J5: 2500 | K5: 2500 | N5: =I5-J5 -> 0
B6: Despesas Mensais | H6: Renda Total | I6: =+I4+I5 -> 4898 | K6: =+K4+K5 -> 4440 | N6: =+I6-K6 -> 458
H7: Despesas | I7: =+SUM(I22,O24,I29,O34,I38,O42,I51,O52,I57,O59,I64,O65,) -> 12013.3 | K7: =+SUM(J22,J29,J38,J51,J57,J64,P65,P59,P52,P42,P34,P24,) -> 3361 | N7: =+I7-K7 -> 8652.3
B8: Data | C8: Despesa | D8: Valor | E8: Área | H8: Saldo | I8: =+I6-I7 -> -7115.3 | K8: =+K6-K7 -> 1079 | N8: =I8-K8 -> -8194.3
D9: =SUM(D10:D112) -> 0
B10: 45839
B11: 45840 | H11: MORADIA | I11: Previsto | J11: Real | K11: Diferença | N11: TRANSPORTE | O11: Previsto | P11: Real | Q11: Diferença
B12: 45841 | G12: 1 | H12: Caixa de Emergência | I12: 150 | J12: =SUMIF(E$10:E$144,"1",D$10:D$144) -> 0 | K12: =+I12-J12 -> 150 | M12: 40 | N12: Uber 99 | O12: 58 | P12: 45 | Q12: =+O12-P12 -> 13
B13: 45842 | G13: 2 | H13: Inevitavelmento fixo | I13: 1200 | J13: =SUMIF(E$10:E$144,"2",D$10:D$144) -> 0 | K13: =+I13-J13 -> 1200 | M13: 41 | N13: Uber | O13: 68 | P13: =SUMIF(E$10:E$144,"41",D$10:D$144) -> 0 | Q13: =+O13-P13 -> 68
B14: 45843 | G14: 3 | H14: Das Jhenis | I14: 250 | J14: =SUMIF(E$10:E$144,"3",D$10:D$144) -> 0 | K14: =+I14-J14 -> 250 | M14: 42 | N14: Transporte Público | O14: 440 | P14: 0 | Q14: =+O14-P14 -> 440
B15: 45844 | G15: 4 | H15: Cartao Jhenismara | I15: 1200 | J15: 1400 | K15: =+I15-J15 -> -200 | M15: 43 | N15: Transporte Trabalho J | O15: 240 | P15: 143 | Q15: =+O15-P15 -> 97
B16: 45845 | G16: 5 | H16: Emergência Casa | I16: 120 | J16: =SUMIF(E$10:E$144,"5",D$10:D$144) -> 0 | K16: =+I16-J16 -> 120 | M16: 44 | N16: Transporte Trabalho M | O16: 110 | P16: 240 | Q16: =+O16-P16 -> -130
B17: 45846 | G17: 6 | H17: Energia | I17: 150 | J17: 150 | K17: =+I17-J17 -> 0 | M17: 45 | N17: Caixa Carro J | O17: 0 | P17: =SUMIF(E$10:E$144,"45",D$10:D$144) -> 0 | Q17: =+O17-P17 -> 0
B18: 45847 | G18: 7 | H18: Água | I18: 77 | J18: 77 | K18: =+I18-J18 -> 0 | M18: 46 | N18: Caixa Carro M | O18: 0 | P18: =SUMIF(E$10:E$144,"46",D$10:D$144) -> 0 | Q18: =+O18-P18 -> 0
B19: 45848 | G19: 8 | H19: Gás | I19: 55 | J19: 55 | K19: =+I19-J19 -> 0 | M19: 47 | O19: 0 | P19: =SUMIF(E$10:E$144,"47",D$10:D$144) -> 0 | Q19: =+O19-P19 -> 0
B20: 45849 | G20: 9 | H20: Cartao (Matheus) | I20: 175 | J20: 175 | K20: =+I20-J20 -> 0 | M20: 48 | O20: 0 | P20: =SUMIF(E$10:E$144,"48",D$10:D$144) -> 0 | Q20: =+O20-P20 -> 0
B21: 45850 | G21: 10 | H21: Outrs Dispesas | J21: =SUMIF(E$10:E$144,"10",D$10:D$144) -> 0 | K21: =+I21-J21 -> 0 | M21: 49 | O21: 0 | P21: 0 | Q21: =+O21-P21 -> 0
B22: 45851 | H22: TOTAL | I22: =SUM(I12:I21) -> 3377 | J22: =SUM(J12:J21) -> 1857 | K22: =+I22-J22 -> 1520 | M22: 50 | O22: 0 | P22: 0 | Q22: =+O22-P22 -> 0
B23: 45852 | M23: 51 | N23: Outros Transporte | O23: 0 | P23: =SUMIF(E$10:E$144,"51",D$10:D$144) -> 0 | Q23: =+O23-P23 -> 0
B24: 45853 | H24: ALIMENTAÇÃO | I24: Previsto | J24: Real | K24: Diferença | N24: TOTAL | O24: =SUM(O12:O23) -> 916 | P24: =SUM(P12:P23) -> 428 | Q24: =+O24-P24 -> 488
B25: 45854 | G25: 11 | H25: Supermercado | I25: 450 | J25: 450 | K25: =+I25-J25 -> 0
B26: 45855 | G26: 12 | H26: Restaurante | I26: 140 | J26: 140 | K26: =+I26-J26 -> 0 | N26: EDUCAÇÃO | O26: Previsto | P26: Real | Q26: Diferença
B27: 45856 | G27: 13 | H27: Café \ Almoço | I27: 100 | J27: 250 | K27: =+I27-J27 -> -150 | M27: 52 | N27: Mensalidades | O27: 0 | P27: =SUMIF(E$10:E$144,"52",D$10:D$144) -> 0 | Q27: =+O27-P27 -> 0
B28: 45857 | G28: 14 | H28: Pedidos IFood | I28: 140 | J28: =SUMIF(E$10:E$144,"14",D$10:D$144) -> 0 | K28: =+I28-J28 -> 140 | M28: 53 | N28: Idiomas | O28: 0 | P28: =SUMIF(E$10:E$144,"53",D$10:D$144) -> 0 | Q28: =+O28-P28 -> 0
B29: 45858 | H29: TOTAL | I29: =SUM(I25:I28) -> 830 | J29: =SUM(J25:J28) -> 840 | K29: =+I29-J29 -> -10 | M29: 54 | N29: CNH [Matheus] | O29: 0 | P29: =SUMIF(E$10:E$144,"54",D$10:D$144) -> 0 | Q29: =+O29-P29 -> 0
B30: 45859 | M30: 55 | N30: Cursos | O30: 140 | P30: =SUMIF(E$10:E$144,"55",D$10:D$144) -> 0 | Q30: =+O30-P30 -> 140
B31: 45860 | H31: COMUNICAÇÃO | I31: Previsto | J31: Real | K31: Diferença | M31: 56 | N31: Livros | O31: 0 | P31: =SUMIF(E$10:E$144,"56",D$10:D$144) -> 0 | Q31: =+O31-P31 -> 0
B32: 45861 | G32: 15 | H32: Celular | I32: 45 | J32: 45 | K32: =+I32-J32 -> 0 | M32: 57 | N32: Faculdade [Jhenis] | O32: 0 | P32: =SUMIF(E$10:E$144,"57",D$10:D$144) -> 0 | Q32: =+O32-P32 -> 0
B33: 45862 | G33: 16 | H33: Internet | I33: 89 | J33: 89 | K33: =+I33-J33 -> 0 | M33: 58 | N33: Outros Educação | O33: 0 | P33: =SUMIF(E$10:E$144,"58",D$10:D$144) -> 0 | Q33: =+O33-P33 -> 0
B34: 45863 | G34: 17 | H34: Streaming | I34: 24 | J34: 24 | K34: =+I34-J34 -> 0 | N34: TOTAL | O34: =SUM(O27:O33) -> 140 | P34: =SUM(P27:P33) -> 0 | Q34: =+O34-P34 -> 140
B35: 45864 | G35: 18 | H35: Netflix | I35: 21.9 | J35: 22 | K35: =+I35-J35 -> -0.1
B36: 45865 | G36: 19 | H36: Amazon | I36: 10.9 | J36: 11 | K36: =+I36-J36 -> -0.1 | N36: LAZER | O36: Previsto | P36: Real | Q36: Diferença
B37: 45866 | G37: 20 | H37: Max Plus | I37: 34.5 | J37: 45 | K37: =+I37-J37 -> -10.5 | M37: 60 | N37: Cinema | O37: 450 | P37: =SUMIF(E$10:E$144,"60",D$10:D$144) -> 0 | Q37: =+O37-P37 -> 450
B38: 45867 | H38: TOTAL | I38: =SUM(I32:I37) -> 225.3 | J38: =SUM(J32:J37) -> 236 | K38: =+I38-J38 -> -10.7 | M38: 61 | N38: Esportes | O38: 0 | P38: =SUMIF(E$10:E$144,"61",D$10:D$144) -> 0 | Q38: =+O38-P38 -> 0
B39: 45868 | M39: 62 | N39: Shows [Consertos] | O39: 120 | P39: =SUMIF(E$10:E$144,"62",D$10:D$144) -> 0 | Q39: =+O39-P39 -> 120
B40: 45869 | H40: SAÚDE E CUIDADOS | I40: Previsto | J40: Real | K40: Diferença | M40: 63 | N40: Viagens [Férias] | O40: 148 | P40: =SUMIF(E$10:E$144,"63",D$10:D$144) -> 0 | Q40: =+O40-P40 -> 148
G41: 21 | H41: Academia | I41: 120 | J41: =SUMIF(E$10:E$144,"21",D$10:D$144) -> 0 | K41: =+I41-J41 -> 120 | M41: 64 | N41: Outros Lazer | O41: 60 | P41: =SUMIF(E$10:E$144,"64",D$10:D$144) -> 0 | Q41: =+O41-P41 -> 60
G42: 22 | H42: Emergencia Médica | I42: 120 | J42: =SUMIF(E$10:E$144,"22",D$10:D$144) -> 0 | K42: =+I42-J42 -> 120 | N42: TOTAL | O42: =SUM(O37:O41) -> 778 | P42: =SUM(P37:P41) -> 0 | Q42: =+O42-P42 -> 778
G43: 23 | H43: Emergência Dentista | I43: 100 | J43: =SUMIF(E$10:E$144,"23",D$10:D$144) -> 0 | K43: =+I43-J43 -> 100
G44: 24 | H44: Cosméticos | I44: 100 | J44: =SUMIF(E$10:E$144,"24",D$10:D$144) -> 0 | K44: =+I44-J44 -> 100 | N44: Necessidades Da Casa | O44: Previsto | P44: Real | Q44: Diferença
G45: 25 | H45: Dentista | I45: 150 | J45: =SUMIF(E$10:E$144,"25",D$10:D$144) -> 0 | K45: =+I45-J45 -> 150 | M45: 70 | N45: Cama | O45: 0 | P45: =SUMIF(E$10:E$144,"70",D$10:D$144) -> 0 | Q45: =+O45-P45 -> 0
G46: 26 | H46: Exames médicos | I46: 0 | J46: =SUMIF(E$10:E$144,"26",D$10:D$144) -> 0 | K46: =+I46-J46 -> 0 | M46: 71 | N46: Consertos [ Futuros | O46: 0 | P46: =SUMIF(E$10:E$144,"71",D$10:D$144) -> 0 | Q46: =+O46-P46 -> 0
G47: 27 | H47: Farmácia | I47: 89 | J47: =SUMIF(E$10:E$144,"27",D$10:D$144) -> 0 | K47: =+I47-J47 -> 89 | M47: 72 | N47: Geladeira | O47: 0 | P47: =SUMIF(E$10:E$144,"72",D$10:D$144) -> 0 | Q47: =+O47-P47 -> 0
G48: 28 | H48: Médicos particular | I48: 0 | J48: =SUMIF(E$10:E$144,"28",D$10:D$144) -> 0 | K48: =+I48-J48 -> 0 | M48: 73 | N48: Lava e seca | O48: 0 | P48: =SUMIF(E$10:E$144,"73",D$10:D$144) -> 0 | Q48: =+O48-P48 -> 0
G49: 29 | H49: Suplementos | I49: 0 | J49: =SUMIF(E$10:E$144,"29",D$10:D$144) -> 0 | K49: =+I49-J49 -> 0 | M49: 74 | N49: Lavanderia louça | O49: 0 | P49: =SUMIF(E$10:E$144,"74",D$10:D$144) -> 0 | Q49: =+O49-P49 -> 0
G50: 30 | H50: Outros Saúde | I50: 0 | J50: =SUMIF(E$10:E$144,"30",D$10:D$144) -> 0 | K50: =+I50-J50 -> 0 | M50: 75 | N50: Utensílios e decoração | O50: 0 | P50: =SUMIF(E$10:E$144,"75",D$10:D$144) -> 0 | Q50: =+O50-P50 -> 0
H51: TOTAL | I51: =SUM(I41:I50) -> 679 | J51: =SUM(J41:J50) -> 0 | K51: =+I51-J51 -> 679 | M51: 76 | N51: Outros Artigos | O51: 0 | P51: =SUMIF(E$10:E$144,"76",D$10:D$144) -> 0 | Q51: =+O51-P51 -> 0
N52: TOTAL | O52: =SUM(O45:O51) -> 0 | P52: =SUM(P45:P51) -> 0 | Q52: =+O52-P52 -> 0
H53: VESTUÁRIO | I53: Previsto | J53: Real | K53: Diferença
G54: 31 | H54: Roupas | I54: 39 | J54: =SUMIF(E$10:E$144,"31",D$10:D$144) -> 0 | K54: =+I54-J54 -> 39 | N54: OUTROS | O54: Previsto | P54: Real | Q54: Diferença
G55: 32 | H55: Sapatos | I55: 0 | J55: =SUMIF(E$10:E$144,"32",D$10:D$144) -> 0 | K55: =+I55-J55 -> 0 | M55: 80 | N55: Presentes | O55: 89 | P55: =SUMIF(E$10:E$144,"80",D$10:D$144) -> 0 | Q55: =+O55-P55 -> 89
G56: 33 | H56: Outros Vestuário | I56: 0 | J56: =SUMIF(E$10:E$144,"33",D$10:D$144) -> 0 | K56: =+I56-J56 -> 0 | M56: 81 | N56: Doações | O56: 0 | P56: =SUMIF(E$10:E$144,"81",D$10:D$144) -> 0 | Q56: =+O56-P56 -> 0
H57: TOTAL | I57: =SUM(I54:I56) -> 39 | J57: =SUM(J54:J56) -> 0 | K57: =+I57-J57 -> 39 | M57: 82 | N57: Ensaio | O57: 140 | P57: =SUMIF(E$10:E$144,"82",D$10:D$144) -> 0 | Q57: =+O57-P57 -> 140
M58: 83 | N58: Outros | O58: 0 | P58: =SUMIF(E$10:E$144,"83",D$10:D$144) -> 0 | Q58: =+O58-P58 -> 0
H59: Investimentos | I59: Previsto | J59: Rendimento | K59: Dividendos | N59: TOTAL | O59: =SUM(O55:O58) -> 229 | P59: =SUM(P55:P58) -> 0 | Q59: =+O59-P59 -> 229
G60: 34 | H60: Renda Variavel | I60: 1200 | J60: =SUMIF(E$10:E$144,"34",D$10:D$144) -> 0 | K60: =+I60-O620 -> 1200
G61: 35 | H61: Fundos imobiliário | I61: 1200 | J61: =SUMIF(E$10:E$144,"35",D$10:D$144) -> 0 | K61: =+I61-J61 -> 1200 | N61: FINANCEIRO | O61: Previsto | P61: Real | Q61: Diferença
G62: 36 | H62: Ações Baixo Risco | I62: 1200 | J62: =SUMIF(E$10:E$144,"36",D$10:D$144) -> 0 | K62: =+I62-J62 -> 1200 | M62: 90 | N62: Investimentos Mensais | O62: 0 | P62: =SUMIF(E$10:E$144,"90",D$10:D$144) -> 0 | Q62: =+O62-P62 -> 0
G63: 37 | H63: Ações Altos Risco | I63: 1200 | J63: =SUMIF(E$10:E$144,"37",D$10:D$144) -> 0 | K63: =+I63-J63 -> 1200 | M63: 91 | N63: Cartas de Crédito | O63: 0 | P63: =SUMIF(E$10:E$144,"91",D$10:D$144) -> 0 | Q63: =+O63-P63 -> 0
H64: TOTAL | I64: =SUM(I60:I63) -> 4800 | J64: =SUM(J60:J63) -> 0 | K64: =+I64-J64 -> 4800 | M64: 92 | N64: Outros Financeiro | O64: 0 | P64: =SUMIF(E$10:E$144,"92",D$10:D$144) -> 0 | Q64: =+O64-P64 -> 0
N65: TOTAL | O65: =SUM(O62:O64) -> 0 | P65: =SUM(P62:P64) -> 0 | Q65: =+O65-P65 -> 0

Sheet AGO
B1: Lançamento de Compras e Gastos Casa Organizada
I3: Previsto | K3: Real | N3: Diferença
H4: Renda 1 | I4: 2398 | J4: 1940 | K4: 1940 | N4: =I4-K4 -> 458
H5: Renda 2 | I5: 2500 | J5: 2500 | K5: 2500 | N5: =I5-J5 -> 0
B6: Despesas Mensais | H6: Renda Total | I6: =+I4+I5 -> 4898 | K6: =+K4+K5 -> 4440 | N6: =+I6-K6 -> 458
H7: Despesas | I7: =+SUM(I22,O24,I29,O34,I38,O42,I51,O52,I57,O59,I64,O65,) -> 12013.3 | K7: =+SUM(J22,J29,J38,J51,J57,J64,P65,P59,P52,P42,P34,P24,) -> 3361 | N7: =+I7-K7 -> 8652.3
B8: Data | C8: Despesa | D8: Valor | E8: Área | H8: Saldo | I8: =+I6-I7 -> -7115.3 | K8: =+K6-K7 -> 1079 | N8: =I8-K8 -> -8194.3
D9: =SUM(D10:D112) -> 0
B10: 45870
B11: 45871 | H11: MORADIA | I11: Previsto | J11: Real | K11: Diferença | N11: TRANSPORTE | O11: Previsto | P11: Real | Q11: Diferença
B12: 45872 | G12: 1 | H12: Caixa de Emergência | I12: 150 | J12: =SUMIF(E$10:E$144,"1",D$10:D$144) -> 0 | K12: =+I12-J12 -> 150 | M12: 40 | N12: Uber 99 | O12: 58 | P12: 45 | Q12: =+O12-P12 -> 13
B13: 45873 | G13: 2 | H13: Inevitavelmento fixo | I13: 1200 | J13: =SUMIF(E$10:E$144,"2",D$10:D$144) -> 0 | K13: =+I13-J13 -> 1200 | M13: 41 | N13: Uber | O13: 68 | P13: =SUMIF(E$10:E$144,"41",D$10:D$144) -> 0 | Q13: =+O13-P13 -> 68
B14: 45874 | G14: 3 | H14: Das Jhenis | I14: 250 | J14: =SUMIF(E$10:E$144,"3",D$10:D$144) -> 0 | K14: =+I14-J14 -> 250 | M14: 42 | N14: Transporte Público | O14: 440 | P14: 0 | Q14: =+O14-P14 -> 440
B15: 45875 | G15: 4 | H15: Cartao Jhenismara | I15: 1200 | J15: 1400 | K15: =+I15-J15 -> -200 | M15: 43 | N15: Transporte Trabalho J | O15: 240 | P15: 143 | Q15: =+O15-P15 -> 97
B16: 45876 | G16: 5 | H16: Emergência Casa | I16: 120 | J16: =SUMIF(E$10:E$144,"5",D$10:D$144) -> 0 | K16: =+I16-J16 -> 120 | M16: 44 | N16: Transporte Trabalho M | O16: 110 | P16: 240 | Q16: =+O16-P16 -> -130
B17: 45877 | G17: 6 | H17: Energia | I17: 150 | J17: 150 | K17: =+I17-J17 -> 0 | M17: 45 | N17: Caixa Carro J | O17: 0 | P17: =SUMIF(E$10:E$144,"45",D$10:D$144) -> 0 | Q17: =+O17-P17 -> 0
B18: 45878 | G18: 7 | H18: Água | I18: 77 | J18: 77 | K18: =+I18-J18 -> 0 | M18: 46 | N18: Caixa Carro M | O18: 0 | P18: =SUMIF(E$10:E$144,"46",D$10:D$144) -> 0 | Q18: =+O18-P18 -> 0
B19: 45879 | G19: 8 | H19: Gás | I19: 55 | J19: 55 | K19: =+I19-J19 -> 0 | M19: 47 | O19: 0 | P19: =SUMIF(E$10:E$144,"47",D$10:D$144) -> 0 | Q19: =+O19-P19 -> 0
B20: 45880 | G20: 9 | H20: Cartao (Matheus) | I20: 175 | J20: 175 | K20: =+I20-J20 -> 0 | M20: 48 | O20: 0 | P20: =SUMIF(E$10:E$144,"48",D$10:D$144) -> 0 | Q20: =+O20-P20 -> 0
B21: 45881 | G21: 10 | H21: Outrs Dispesas | J21: =SUMIF(E$10:E$144,"10",D$10:D$144) -> 0 | K21: =+I21-J21 -> 0 | M21: 49 | O21: 0 | P21: 0 | Q21: =+O21-P21 -> 0
B22: 45882 | H22: TOTAL | I22: =SUM(I12:I21) -> 3377 | J22: =SUM(J12:J21) -> 1857 | K22: =+I22-J22 -> 1520 | M22: 50 | O22: 0 | P22: 0 | Q22: =+O22-P22 -> 0
B23: 45883 | M23: 51 | N23: Outros Transporte | O23: 0 | P23: =SUMIF(E$10:E$144,"51",D$10:D$144) -> 0 | Q23: =+O23-P23 -> 0
B24: 45884 | H24: ALIMENTAÇÃO | I24: Previsto | J24: Real | K24: Diferença | N24: TOTAL | O24: =SUM(O12:O23) -> 916 | P24: =SUM(P12:P23) -> 428 | Q24: =+O24-P24 -> 488
B25: 45885 | G25: 11 | H25: Supermercado | I25: 450 | J25: 450 | K25: =+I25-J25 -> 0
B26: 45886 | G26: 12 | H26: Restaurante | I26: 140 | J26: 140 | K26: =+I26-J26 -> 0 | N26: EDUCAÇÃO | O26: Previsto | P26: Real | Q26: Diferença
B27: 45887 | G27: 13 | H27: Café \ Almoço | I27: 100 | J27: 250 | K27: =+I27-J27 -> -150 | M27: 52 | N27: Mensalidades | O27: 0 | P27: =SUMIF(E$10:E$144,"52",D$10:D$144) -> 0 | Q27: =+O27-P27 -> 0
B28: 45888 | G28: 14 | H28: Pedidos IFood | I28: 140 | J28: =SUMIF(E$10:E$144,"14",D$10:D$144) -> 0 | K28: =+I28-J28 -> 140 | M28: 53 | N28: Idiomas | O28: 0 | P28: =SUMIF(E$10:E$144,"53",D$10:D$144) -> 0 | Q28: =+O28-P28 -> 0
B29: 45889 | H29: TOTAL | I29: =SUM(I25:I28) -> 830 | J29: =SUM(J25:J28) -> 840 | K29: =+I29-J29 -> -10 | M29: 54 | N29: CNH [Matheus] | O29: 0 | P29: =SUMIF(E$10:E$144,"54",D$10:D$144) -> 0 | Q29: =+O29-P29 -> 0
B30: 45890 | M30: 55 | N30: Cursos | O30: 140 | P30: =SUMIF(E$10:E$144,"55",D$10:D$144) -> 0 | Q30: =+O30-P30 -> 140
B31: 45891 | H31: COMUNICAÇÃO | I31: Previsto | J31: Real | K31: Diferença | M31: 56 | N31: Livros | O31: 0 | P31: =SUMIF(E$10:E$144,"56",D$10:D$144) -> 0 | Q31: =+O31-P31 -> 0
B32: 45892 | G32: 15 | H32: Celular | I32: 45 | J32: 45 | K32: =+I32-J32 -> 0 | M32: 57 | N32: Faculdade [Jhenis] | O32: 0 | P32: =SUMIF(E$10:E$144,"57",D$10:D$144) -> 0 | Q32: =+O32-P32 -> 0
B33: 45893 | G33: 16 | H33: Internet | I33: 89 | J33: 89 | K33: =+I33-J33 -> 0 | M33: 58 | N33: Outros Educação | O33: 0 | P33: =SUMIF(E$10:E$144,"58",D$10:D$144) -> 0 | Q33: =+O33-P33 -> 0
B34: 45894 | G34: 17 | H34: Streaming | I34: 24 | J34: 24 | K34: =+I34-J34 -> 0 | N34: TOTAL | O34: =SUM(O27:O33) -> 140 | P34: =SUM(P27:P33) -> 0 | Q34: =+O34-P34 -> 140
B35: 45895 | G35: 18 | H35: Netflix | I35: 21.9 | J35: 22 | K35: =+I35-J35 -> -0.1
B36: 45896 | G36: 19 | H36: Amazon | I36: 10.9 | J36: 11 | K36: =+I36-J36 -> -0.1 | N36: LAZER | O36: Previsto | P36: Real | Q36: Diferença
B37: 45897 | G37: 20 | H37: Max Plus | I37: 34.5 | J37: 45 | K37: =+I37-J37 -> -10.5 | M37: 60 | N37: Cinema | O37: 450 | P37: =SUMIF(E$10:E$144,"60",D$10:D$144) -> 0 | Q37: =+O37-P37 -> 450
B38: 45898 | H38: TOTAL | I38: =SUM(I32:I37) -> 225.3 | J38: =SUM(J32:J37) -> 236 | K38: =+I38-J38 -> -10.7 | M38: 61 | N38: Esportes | O38: 0 | P38: =SUMIF(E$10:E$144,"61",D$10:D$144) -> 0 | Q38: =+O38-P38 -> 0
B39: 45899 | M39: 62 | N39: Shows [Consertos] | O39: 120 | P39: =SUMIF(E$10:E$144,"62",D$10:D$144) -> 0 | Q39: =+O39-P39 -> 120
B40: 45900 | H40: SAÚDE E CUIDADOS | I40: Previsto | J40: Real | K40: Diferença | M40: 63 | N40: Viagens [Férias] | O40: 148 | P40: =SUMIF(E$10:E$144,"63",D$10:D$144) -> 0 | Q40: =+O40-P40 -> 148
G41: 21 | H41: Academia | I41: 120 | J41: =SUMIF(E$10:E$144,"21",D$10:D$144) -> 0 | K41: =+I41-J41 -> 120 | M41: 64 | N41: Outros Lazer | O41: 60 | P41: =SUMIF(E$10:E$144,"64",D$10:D$144) -> 0 | Q41: =+O41-P41 -> 60
G42: 22 | H42: Emergencia Médica | I42: 120 | J42: =SUMIF(E$10:E$144,"22",D$10:D$144) -> 0 | K42: =+I42-J42 -> 120 | N42: TOTAL | O42: =SUM(O37:O41) -> 778 | P42: =SUM(P37:P41) -> 0 | Q42: =+O42-P42 -> 778
G43: 23 | H43: Emergência Dentista | I43: 100 | J43: =SUMIF(E$10:E$144,"23",D$10:D$144) -> 0 | K43: =+I43-J43 -> 100
G44: 24 | H44: Cosméticos | I44: 100 | J44: =SUMIF(E$10:E$144,"24",D$10:D$144) -> 0 | K44: =+I44-J44 -> 100 | N44: Necessidades Da Casa | O44: Previsto | P44: Real | Q44: Diferença
G45: 25 | H45: Dentista | I45: 150 | J45: =SUMIF(E$10:E$144,"25",D$10:D$144) -> 0 | K45: =+I45-J45 -> 150 | M45: 70 | N45: Cama | O45: 0 | P45: =SUMIF(E$10:E$144,"70",D$10:D$144) -> 0 | Q45: =+O45-P45 -> 0
G46: 26 | H46: Exames médicos | I46: 0 | J46: =SUMIF(E$10:E$144,"26",D$10:D$144) -> 0 | K46: =+I46-J46 -> 0 | M46: 71 | N46: Consertos [ Futuros | O46: 0 | P46: =SUMIF(E$10:E$144,"71",D$10:D$144) -> 0 | Q46: =+O46-P46 -> 0
G47: 27 | H47: Farmácia | I47: 89 | J47: =SUMIF(E$10:E$144,"27",D$10:D$144) -> 0 | K47: =+I47-J47 -> 89 | M47: 72 | N47: Geladeira | O47: 0 | P47: =SUMIF(E$10:E$144,"72",D$10:D$144) -> 0 | Q47: =+O47-P47 -> 0
G48: 28 | H48: Médicos particular | I48: 0 | J48: =SUMIF(E$10:E$144,"28",D$10:D$144) -> 0 | K48: =+I48-J48 -> 0 | M48: 73 | N48: Lava e seca | O48: 0 | P48: =SUMIF(E$10:E$144,"73",D$10:D$144) -> 0 | Q48: =+O48-P48 -> 0
G49: 29 | H49: Suplementos | I49: 0 | J49: =SUMIF(E$10:E$144,"29",D$10:D$144) -> 0 | K49: =+I49-J49 -> 0 | M49: 74 | N49: Lavanderia louça | O49: 0 | P49: =SUMIF(E$10:E$144,"74",D$10:D$144) -> 0 | Q49: =+O49-P49 -> 0
G50: 30 | H50: Outros Saúde | I50: 0 | J50: =SUMIF(E$10:E$144,"30",D$10:D$144) -> 0 | K50: =+I50-J50 -> 0 | M50: 75 | N50: Utensílios e decoração | O50: 0 | P50: =SUMIF(E$10:E$144,"75",D$10:D$144) -> 0 | Q50: =+O50-P50 -> 0
H51: TOTAL | I51: =SUM(I41:I50) -> 679 | J51: =SUM(J41:J50) -> 0 | K51: =+I51-J51 -> 679 | M51: 76 | N51: Outros Artigos | O51: 0 | P51: =SUMIF(E$10:E$144,"76",D$10:D$144) -> 0 | Q51: =+O51-P51 -> 0
N52: TOTAL | O52: =SUM(O45:O51) -> 0 | P52: =SUM(P45:P51) -> 0 | Q52: =+O52-P52 -> 0
H53: VESTUÁRIO | I53: Previsto | J53: Real | K53: Diferença
G54: 31 | H54: Roupas | I54: 39 | J54: =SUMIF(E$10:E$144,"31",D$10:D$144) -> 0 | K54: =+I54-J54 -> 39 | N54: OUTROS | O54: Previsto | P54: Real | Q54: Diferença
G55: 32 | H55: Sapatos | I55: 0 | J55: =SUMIF(E$10:E$144,"32",D$10:D$144) -> 0 | K55: =+I55-J55 -> 0 | M55: 80 | N55: Presentes | O55: 89 | P55: =SUMIF(E$10:E$144,"80",D$10:D$144) -> 0 | Q55: =+O55-P55 -> 89
G56: 33 | H56: Outros Vestuário | I56: 0 | J56: =SUMIF(E$10:E$144,"33",D$10:D$144) -> 0 | K56: =+I56-J56 -> 0 | M56: 81 | N56: Doações | O56: 0 | P56: =SUMIF(E$10:E$144,"81",D$10:D$144) -> 0 | Q56: =+O56-P56 -> 0
H57: TOTAL | I57: =SUM(I54:I56) -> 39 | J57: =SUM(J54:J56) -> 0 | K57: =+I57-J57 -> 39 | M57: 82 | N57: Ensaio | O57: 140 | P57: =SUMIF(E$10:E$144,"82",D$10:D$144) -> 0 | Q57: =+O57-P57 -> 140
M58: 83 | N58: Outros | O58: 0 | P58: =SUMIF(E$10:E$144,"83",D$10:D$144) -> 0 | Q58: =+O58-P58 -> 0
H59: Investimentos | I59: Previsto | J59: Rendimento | K59: Dividendos | N59: TOTAL | O59: =SUM(O55:O58) -> 229 | P59: =SUM(P55:P58) -> 0 | Q59: =+O59-P59 -> 229
G60: 34 | H60: Renda Variavel | I60: 1200 | J60: =SUMIF(E$10:E$144,"34",D$10:D$144) -> 0 | K60: =+I60-O620 -> 1200
G61: 35 | H61: Fundos imobiliário | I61: 1200 | J61: =SUMIF(E$10:E$144,"35",D$10:D$144) -> 0 | K61: =+I61-J61 -> 1200 | N61: FINANCEIRO | O61: Previsto | P61: Real | Q61: Diferença
G62: 36 | H62: Ações Baixo Risco | I62: 1200 | J62: =SUMIF(E$10:E$144,"36",D$10:D$144) -> 0 | K62: =+I62-J62 -> 1200 | M62: 90 | N62: Investimentos Mensais | O62: 0 | P62: =SUMIF(E$10:E$144,"90",D$10:D$144) -> 0 | Q62: =+O62-P62 -> 0
G63: 37 | H63: Ações Altos Risco | I63: 1200 | J63: =SUMIF(E$10:E$144,"37",D$10:D$144) -> 0 | K63: =+I63-J63 -> 1200 | M63: 91 | N63: Cartas de Crédito | O63: 0 | P63: =SUMIF(E$10:E$144,"91",D$10:D$144) -> 0 | Q63: =+O63-P63 -> 0
H64: TOTAL | I64: =SUM(I60:I63) -> 4800 | J64: =SUM(J60:J63) -> 0 | K64: =+I64-J64 -> 4800 | M64: 92 | N64: Outros Financeiro | O64: 0 | P64: =SUMIF(E$10:E$144,"92",D$10:D$144) -> 0 | Q64: =+O64-P64 -> 0
N65: TOTAL | O65: =SUM(O62:O64) -> 0 | P65: =SUM(P62:P64) -> 0 | Q65: =+O65-P65 -> 0

Sheet SET
B1: Lançamento de Compras e Gastos Casa Organizada
I3: Previsto | K3: Real | N3: Diferença
H4: Renda 1 | I4: 2398 | J4: 1940 | K4: 1940 | N4: =I4-K4 -> 458
H5: Renda 2 | I5: 2500 | J5: 2500 | K5: 2500 | N5: =I5-J5 -> 0
B6: Despesas Mensais | H6: Renda Total | I6: =+I4+I5 -> 4898 | K6: =+K4+K5 -> 4440 | N6: =+I6-K6 -> 458
H7: Despesas | I7: =+SUM(I22,O24,I29,O34,I38,O42,I51,O52,I57,O59,I64,O65,) -> 12013.3 | K7: =+SUM(J22,J29,J38,J51,J57,J64,P65,P59,P52,P42,P34,P24,) -> 3361 | N7: =+I7-K7 -> 8652.3
B8: Data | C8: Despesa | D8: Valor | E8: Área | H8: Saldo | I8: =+I6-I7 -> -7115.3 | K8: =+K6-K7 -> 1079 | N8: =I8-K8 -> -8194.3
D9: =SUM(D10:D112) -> 0
B10: 45901
B11: 45902 | H11: MORADIA | I11: Previsto | J11: Real | K11: Diferença | N11: TRANSPORTE | O11: Previsto | P11: Real | Q11: Diferença
B12: 45903 | G12: 1 | H12: Caixa de Emergência | I12: 150 | J12: =SUMIF(E$10:E$144,"1",D$10:D$144) -> 0 | K12: =+I12-J12 -> 150 | M12: 40 | N12: Uber 99 | O12: 58 | P12: 45 | Q12: =+O12-P12 -> 13
B13: 45904 | G13: 2 | H13: Inevitavelmento fixo | I13: 1200 | J13: =SUMIF(E$10:E$144,"2",D$10:D$144) -> 0 | K13: =+I13-J13 -> 1200 | M13: 41 | N13: Uber | O13: 68 | P13: =SUMIF(E$10:E$144,"41",D$10:D$144) -> 0 | Q13: =+O13-P13 -> 68
B14: 45905 | G14: 3 | H14: Das Jhenis | I14: 250 | J14: =SUMIF(E$10:E$144,"3",D$10:D$144) -> 0 | K14: =+I14-J14 -> 250 | M14: 42 | N14: Transporte Público | O14: 440 | P14: 0 | Q14: =+O14-P14 -> 440
B15: 45906 | G15: 4 | H15: Cartao Jhenismara | I15: 1200 | J15: 1400 | K15: =+I15-J15 -> -200 | M15: 43 | N15: Transporte Trabalho J | O15: 240 | P15: 143 | Q15: =+O15-P15 -> 97
B16: 45907 | G16: 5 | H16: Emergência Casa | I16: 120 | J16: =SUMIF(E$10:E$144,"5",D$10:D$144) -> 0 | K16: =+I16-J16 -> 120 | M16: 44 | N16: Transporte Trabalho M | O16: 110 | P16: 240 | Q16: =+O16-P16 -> -130
B17: 45908 | G17: 6 | H17: Energia | I17: 150 | J17: 150 | K17: =+I17-J17 -> 0 | M17: 45 | N17: Caixa Carro J | O17: 0 | P17: =SUMIF(E$10:E$144,"45",D$10:D$144) -> 0 | Q17: =+O17-P17 -> 0
B18: 45909 | G18: 7 | H18: Água | I18: 77 | J18: 77 | K18: =+I18-J18 -> 0 | M18: 46 | N18: Caixa Carro M | O18: 0 | P18: =SUMIF(E$10:E$144,"46",D$10:D$144) -> 0 | Q18: =+O18-P18 -> 0
B19: 45910 | G19: 8 | H19: Gás | I19: 55 | J19: 55 | K19: =+I19-J19 -> 0 | M19: 47 | O19: 0 | P19: =SUMIF(E$10:E$144,"47",D$10:D$144) -> 0 | Q19: =+O19-P19 -> 0
B20: 45911 | G20: 9 | H20: Cartao (Matheus) | I20: 175 | J20: 175 | K20: =+I20-J20 -> 0 | M20: 48 | O20: 0 | P20: =SUMIF(E$10:E$144,"48",D$10:D$144) -> 0 | Q20: =+O20-P20 -> 0
B21: 45912 | G21: 10 | H21: Outrs Dispesas | J21: =SUMIF(E$10:E$144,"10",D$10:D$144) -> 0 | K21: =+I21-J21 -> 0 | M21: 49 | O21: 0 | P21: 0 | Q21: =+O21-P21 -> 0
B22: 45913 | H22: TOTAL | I22: =SUM(I12:I21) -> 3377 | J22: =SUM(J12:J21) -> 1857 | K22: =+I22-J22 -> 1520 | M22: 50 | O22: 0 | P22: 0 | Q22: =+O22-P22 -> 0
B23: 45914 | M23: 51 | N23: Outros Transporte | O23: 0 | P23: =SUMIF(E$10:E$144,"51",D$10:D$144) -> 0 | Q23: =+O23-P23 -> 0
B24: 45915 | H24: ALIMENTAÇÃO | I24: Previsto | J24: Real | K24: Diferença | N24: TOTAL | O24: =SUM(O12:O23) -> 916 | P24: =SUM(P12:P23) -> 428 | Q24: =+O24-P24 -> 488
B25: 45916 | G25: 11 | H25: Supermercado | I25: 450 | J25: 450 | K25: =+I25-J25 -> 0
B26: 45917 | G26: 12 | H26: Restaurante | I26: 140 | J26: 140 | K26: =+I26-J26 -> 0 | N26: EDUCAÇÃO | O26: Previsto | P26: Real | Q26: Diferença
B27: 45918 | G27: 13 | H27: Café \ Almoço | I27: 100 | J27: 250 | K27: =+I27-J27 -> -150 | M27: 52 | N27: Mensalidades | O27: 0 | P27: =SUMIF(E$10:E$144,"52",D$10:D$144) -> 0 | Q27: =+O27-P27 -> 0
B28: 45919 | G28: 14 | H28: Pedidos IFood | I28: 140 | J28: =SUMIF(E$10:E$144,"14",D$10:D$144) -> 0 | K28: =+I28-J28 -> 140 | M28: 53 | N28: Idiomas | O28: 0 | P28: =SUMIF(E$10:E$144,"53",D$10:D$144) -> 0 | Q28: =+O28-P28 -> 0
B29: 45920 | H29: TOTAL | I29: =SUM(I25:I28) -> 830 | J29: =SUM(J25:J28) -> 840 | K29: =+I29-J29 -> -10 | M29: 54 | N29: CNH [Matheus] | O29: 0 | P29: =SUMIF(E$10:E$144,"54",D$10:D$144) -> 0 | Q29: =+O29-P29 -> 0
B30: 45921 | M30: 55 | N30: Cursos | O30: 140 | P30: =SUMIF(E$10:E$144,"55",D$10:D$144) -> 0 | Q30: =+O30-P30 -> 140
B31: 45922 | H31: COMUNICAÇÃO | I31: Previsto | J31: Real | K31: Diferença | M31: 56 | N31: Livros | O31: 0 | P31: =SUMIF(E$10:E$144,"56",D$10:D$144) -> 0 | Q31: =+O31-P31 -> 0
B32: 45923 | G32: 15 | H32: Celular | I32: 45 | J32: 45 | K32: =+I32-J32 -> 0 | M32: 57 | N32: Faculdade [Jhenis] | O32: 0 | P32: =SUMIF(E$10:E$144,"57",D$10:D$144) -> 0 | Q32: =+O32-P32 -> 0
B33: 45924 | G33: 16 | H33: Internet | I33: 89 | J33: 89 | K33: =+I33-J33 -> 0 | M33: 58 | N33: Outros Educação | O33: 0 | P33: =SUMIF(E$10:E$144,"58",D$10:D$144) -> 0 | Q33: =+O33-P33 -> 0
B34: 45925 | G34: 17 | H34: Streaming | I34: 24 | J34: 24 | K34: =+I34-J34 -> 0 | N34: TOTAL | O34: =SUM(O27:O33) -> 140 | P34: =SUM(P27:P33) -> 0 | Q34: =+O34-P34 -> 140
B35: 45926 | G35: 18 | H35: Netflix | I35: 21.9 | J35: 22 | K35: =+I35-J35 -> -0.1
B36: 45927 | G36: 19 | H36: Amazon | I36: 10.9 | J36: 11 | K36: =+I36-J36 -> -0.1 | N36: LAZER | O36: Previsto | P36: Real | Q36: Diferença
B37: 45928 | G37: 20 | H37: Max Plus | I37: 34.5 | J37: 45 | K37: =+I37-J37 -> -10.5 | M37: 60 | N37: Cinema | O37: 450 | P37: =SUMIF(E$10:E$144,"60",D$10:D$144) -> 0 | Q37: =+O37-P37 -> 450
B38: 45929 | H38: TOTAL | I38: =SUM(I32:I37) -> 225.3 | J38: =SUM(J32:J37) -> 236 | K38: =+I38-J38 -> -10.7 | M38: 61 | N38: Esportes | O38: 0 | P38: =SUMIF(E$10:E$144,"61",D$10:D$144) -> 0 | Q38: =+O38-P38 -> 0
B39: 45930 | M39: 62 | N39: Shows [Consertos] | O39: 120 | P39: =SUMIF(E$10:E$144,"62",D$10:D$144) -> 0 | Q39: =+O39-P39 -> 120
H40: SAÚDE E CUIDADOS | I40: Previsto | J40: Real | K40: Diferença | M40: 63 | N40: Viagens [Férias] | O40: 148 | P40: =SUMIF(E$10:E$144,"63",D$10:D$144) -> 0 | Q40: =+O40-P40 -> 148
G41: 21 | H41: Academia | I41: 120 | J41: =SUMIF(E$10:E$144,"21",D$10:D$144) -> 0 | K41: =+I41-J41 -> 120 | M41: 64 | N41: Outros Lazer | O41: 60 | P41: =SUMIF(E$10:E$144,"64",D$10:D$144) -> 0 | Q41: =+O41-P41 -> 60
G42: 22 | H42: Emergencia Médica | I42: 120 | J42: =SUMIF(E$10:E$144,"22",D$10:D$144) -> 0 | K42: =+I42-J42 -> 120 | N42: TOTAL | O42: =SUM(O37:O41) -> 778 | P42: =SUM(P37:P41) -> 0 | Q42: =+O42-P42 -> 778
G43: 23 | H43: Emergência Dentista | I43: 100 | J43: =SUMIF(E$10:E$144,"23",D$10:D$144) -> 0 | K43: =+I43-J43 -> 100
G44: 24 | H44: Cosméticos | I44: 100 | J44: =SUMIF(E$10:E$144,"24",D$10:D$144) -> 0 | K44: =+I44-J44 -> 100 | N44: Necessidades Da Casa | O44: Previsto | P44: Real | Q44: Diferença
G45: 25 | H45: Dentista | I45: 150 | J45: =SUMIF(E$10:E$144,"25",D$10:D$144) -> 0 | K45: =+I45-J45 -> 150 | M45: 70 | N45: Cama | O45: 0 | P45: =SUMIF(E$10:E$144,"70",D$10:D$144) -> 0 | Q45: =+O45-P45 -> 0
G46: 26 | H46: Exames médicos | I46: 0 | J46: =SUMIF(E$10:E$144,"26",D$10:D$144) -> 0 | K46: =+I46-J46 -> 0 | M46: 71 | N46: Consertos [ Futuros | O46: 0 | P46: =SUMIF(E$10:E$144,"71",D$10:D$144) -> 0 | Q46: =+O46-P46 -> 0
G47: 27 | H47: Farmácia | I47: 89 | J47: =SUMIF(E$10:E$144,"27",D$10:D$144) -> 0 | K47: =+I47-J47 -> 89 | M47: 72 | N47: Geladeira | O47: 0 | P47: =SUMIF(E$10:E$144,"72",D$10:D$144) -> 0 | Q47: =+O47-P47 -> 0
G48: 28 | H48: Médicos particular | I48: 0 | J48: =SUMIF(E$10:E$144,"28",D$10:D$144) -> 0 | K48: =+I48-J48 -> 0 | M48: 73 | N48: Lava e seca | O48: 0 | P48: =SUMIF(E$10:E$144,"73",D$10:D$144) -> 0 | Q48: =+O48-P48 -> 0
G49: 29 | H49: Suplementos | I49: 0 | J49: =SUMIF(E$10:E$144,"29",D$10:D$144) -> 0 | K49: =+I49-J49 -> 0 | M49: 74 | N49: Lavanderia louça | O49: 0 | P49: =SUMIF(E$10:E$144,"74",D$10:D$144) -> 0 | Q49: =+O49-P49 -> 0
G50: 30 | H50: Outros Saúde | I50: 0 | J50: =SUMIF(E$10:E$144,"30",D$10:D$144) -> 0 | K50: =+I50-J50 -> 0 | M50: 75 | N50: Utensílios e decoração | O50: 0 | P50: =SUMIF(E$10:E$144,"75",D$10:D$144) -> 0 | Q50: =+O50-P50 -> 0
H51: TOTAL | I51: =SUM(I41:I50) -> 679 | J51: =SUM(J41:J50) -> 0 | K51: =+I51-J51 -> 679 | M51: 76 | N51: Outros Artigos | O51: 0 | P51: =SUMIF(E$10:E$144,"76",D$10:D$144) -> 0 | Q51: =+O51-P51 -> 0
N52: TOTAL | O52: =SUM(O45:O51) -> 0 | P52: =SUM(P45:P51) -> 0 | Q52: =+O52-P52 -> 0
H53: VESTUÁRIO | I53: Previsto | J53: Real | K53: Diferença
G54: 31 | H54: Roupas | I54: 39 | J54: =SUMIF(E$10:E$144,"31",D$10:D$144) -> 0 | K54: =+I54-J54 -> 39 | N54: OUTROS | O54: Previsto | P54: Real | Q54: Diferença
G55: 32 | H55: Sapatos | I55: 0 | J55: =SUMIF(E$10:E$144,"32",D$10:D$144) -> 0 | K55: =+I55-J55 -> 0 | M55: 80 | N55: Presentes | O55: 89 | P55: =SUMIF(E$10:E$144,"80",D$10:D$144) -> 0 | Q55: =+O55-P55 -> 89
G56: 33 | H56: Outros Vestuário | I56: 0 | J56: =SUMIF(E$10:E$144,"33",D$10:D$144) -> 0 | K56: =+I56-J56 -> 0 | M56: 81 | N56: Doações | O56: 0 | P56: =SUMIF(E$10:E$144,"81",D$10:D$144) -> 0 | Q56: =+O56-P56 -> 0
H57: TOTAL | I57: =SUM(I54:I56) -> 39 | J57: =SUM(J54:J56) -> 0 | K57: =+I57-J57 -> 39 | M57: 82 | N57: Ensaio | O57: 140 | P57: =SUMIF(E$10:E$144,"82",D$10:D$144) -> 0 | Q57: =+O57-P57 -> 140
M58: 83 | N58: Outros | O58: 0 | P58: =SUMIF(E$10:E$144,"83",D$10:D$144) -> 0 | Q58: =+O58-P58 -> 0
H59: Investimentos | I59: Previsto | J59: Rendimento | K59: Dividendos | N59: TOTAL | O59: =SUM(O55:O58) -> 229 | P59: =SUM(P55:P58) -> 0 | Q59: =+O59-P59 -> 229
G60: 34 | H60: Renda Variavel | I60: 1200 | J60: =SUMIF(E$10:E$144,"34",D$10:D$144) -> 0 | K60: =+I60-O620 -> 1200
G61: 35 | H61: Fundos imobiliário | I61: 1200 | J61: =SUMIF(E$10:E$144,"35",D$10:D$144) -> 0 | K61: =+I61-J61 -> 1200 | N61: FINANCEIRO | O61: Previsto | P61: Real | Q61: Diferença
G62: 36 | H62: Ações Baixo Risco | I62: 1200 | J62: =SUMIF(E$10:E$144,"36",D$10:D$144) -> 0 | K62: =+I62-J62 -> 1200 | M62: 90 | N62: Investimentos Mensais | O62: 0 | P62: =SUMIF(E$10:E$144,"90",D$10:D$144) -> 0 | Q62: =+O62-P62 -> 0
G63: 37 | H63: Ações Altos Risco | I63: 1200 | J63: =SUMIF(E$10:E$144,"37",D$10:D$144) -> 0 | K63: =+I63-J63 -> 1200 | M63: 91 | N63: Cartas de Crédito | O63: 0 | P63: =SUMIF(E$10:E$144,"91",D$10:D$144) -> 0 | Q63: =+O63-P63 -> 0
H64: TOTAL | I64: =SUM(I60:I63) -> 4800 | J64: =SUM(J60:J63) -> 0 | K64: =+I64-J64 -> 4800 | M64: 92 | N64: Outros Financeiro | O64: 0 | P64: =SUMIF(E$10:E$144,"92",D$10:D$144) -> 0 | Q64: =+O64-P64 -> 0
N65: TOTAL | O65: =SUM(O62:O64) -> 0 | P65: =SUM(P62:P64) -> 0 | Q65: =+O65-P65 -> 0

Sheet OUT
B1: Lançamento de Compras e Gastos Casa Organizada
I3: Previsto | K3: Real | N3: Diferença
H4: Renda 1 | I4: 2398 | J4: 1940 | K4: 1940 | N4: =I4-K4 -> 458
H5: Renda 2 | I5: 2500 | J5: 2500 | K5: 2500 | N5: =I5-J5 -> 0
B6: Despesas Mensais | H6: Renda Total | I6: =+I4+I5 -> 4898 | K6: =+K4+K5 -> 4440 | N6: =+I6-K6 -> 458
H7: Despesas | I7: =+SUM(I22,O24,I29,O34,I38,O42,I51,O52,I57,O59,I64,O65,) -> 12013.3 | K7: =+SUM(J22,J29,J38,J51,J57,J64,P65,P59,P52,P42,P34,P24,) -> 3361 | N7: =+I7-K7 -> 8652.3
B8: Data | C8: Despesa | D8: Valor | E8: Área | H8: Saldo | I8: =+I6-I7 -> -7115.3 | K8: =+K6-K7 -> 1079 | N8: =I8-K8 -> -8194.3
D9: =SUM(D10:D107) -> 0
B10: 45566
B11: 45567 | H11: MORADIA | I11: Previsto | J11: Real | K11: Diferença | N11: TRANSPORTE | O11: Previsto | P11: Real | Q11: Diferença
B12: 45568 | G12: 1 | H12: Caixa de Emergência | I12: 150 | J12: =SUMIF(E$10:E$144,"1",D$10:D$144) -> 0 | K12: =+I12-J12 -> 150 | M12: 40 | N12: Uber 99 | O12: 58 | P12: 45 | Q12: =+O12-P12 -> 13
B13: 45574 | G13: 2 | H13: Inevitavelmento fixo | I13: 1200 | J13: =SUMIF(E$10:E$144,"2",D$10:D$144) -> 0 | K13: =+I13-J13 -> 1200 | M13: 41 | N13: Uber | O13: 68 | P13: =SUMIF(E$10:E$144,"41",D$10:D$144) -> 0 | Q13: =+O13-P13 -> 68
B14: 45575 | G14: 3 | H14: Das Jhenis | I14: 250 | J14: =SUMIF(E$10:E$144,"3",D$10:D$144) -> 0 | K14: =+I14-J14 -> 250 | M14: 42 | N14: Transporte Público | O14: 440 | P14: 0 | Q14: =+O14-P14 -> 440
B15: 45576 | G15: 4 | H15: Cartao Jhenismara | I15: 1200 | J15: 1400 | K15: =+I15-J15 -> -200 | M15: 43 | N15: Transporte Trabalho J | O15: 240 | P15: 143 | Q15: =+O15-P15 -> 97
B16: 45577 | G16: 5 | H16: Emergência Casa | I16: 120 | J16: =SUMIF(E$10:E$144,"5",D$10:D$144) -> 0 | K16: =+I16-J16 -> 120 | M16: 44 | N16: Transporte Trabalho M | O16: 110 | P16: 240 | Q16: =+O16-P16 -> -130
B17: 45578 | G17: 6 | H17: Energia | I17: 150 | J17: 150 | K17: =+I17-J17 -> 0 | M17: 45 | N17: Caixa Carro J | O17: 0 | P17: =SUMIF(E$10:E$144,"45",D$10:D$144) -> 0 | Q17: =+O17-P17 -> 0
B18: 45579 | G18: 7 | H18: Água | I18: 77 | J18: 77 | K18: =+I18-J18 -> 0 | M18: 46 | N18: Caixa Carro M | O18: 0 | P18: =SUMIF(E$10:E$144,"46",D$10:D$144) -> 0 | Q18: =+O18-P18 -> 0
B19: 45580 | G19: 8 | H19: Gás | I19: 55 | J19: 55 | K19: =+I19-J19 -> 0 | M19: 47 | O19: 0 | P19: =SUMIF(E$10:E$144,"47",D$10:D$144) -> 0 | Q19: =+O19-P19 -> 0
B20: 45581 | G20: 9 | H20: Cartao (Matheus) | I20: 175 | J20: 175 | K20: =+I20-J20 -> 0 | M20: 48 | O20: 0 | P20: =SUMIF(E$10:E$144,"48",D$10:D$144) -> 0 | Q20: =+O20-P20 -> 0
B21: 45582 | G21: 10 | H21: Outrs Dispesas | J21: =SUMIF(E$10:E$144,"10",D$10:D$144) -> 0 | K21: =+I21-J21 -> 0 | M21: 49 | O21: 0 | P21: 0 | Q21: =+O21-P21 -> 0
B22: 45583 | H22: TOTAL | I22: =SUM(I12:I21) -> 3377 | J22: =SUM(J12:J21) -> 1857 | K22: =+I22-J22 -> 1520 | M22: 50 | O22: 0 | P22: 0 | Q22: =+O22-P22 -> 0
B23: 45584 | M23: 51 | N23: Outros Transporte | O23: 0 | P23: =SUMIF(E$10:E$144,"51",D$10:D$144) -> 0 | Q23: =+O23-P23 -> 0
B24: 45585 | H24: ALIMENTAÇÃO | I24: Previsto | J24: Real | K24: Diferença | N24: TOTAL | O24: =SUM(O12:O23) -> 916 | P24: =SUM(P12:P23) -> 428 | Q24: =+O24-P24 -> 488
B25: 45586 | G25: 11 | H25: Supermercado | I25: 450 | J25: 450 | K25: =+I25-J25 -> 0
B26: 45587 | G26: 12 | H26: Restaurante | I26: 140 | J26: 140 | K26: =+I26-J26 -> 0 | N26: EDUCAÇÃO | O26: Previsto | P26: Real | Q26: Diferença
B27: 45588 | G27: 13 | H27: Café \ Almoço | I27: 100 | J27: 250 | K27: =+I27-J27 -> -150 | M27: 52 | N27: Mensalidades | O27: 0 | P27: =SUMIF(E$10:E$144,"52",D$10:D$144) -> 0 | Q27: =+O27-P27 -> 0
B28: 45589 | G28: 14 | H28: Pedidos IFood | I28: 140 | J28: =SUMIF(E$10:E$144,"14",D$10:D$144) -> 0 | K28: =+I28-J28 -> 140 | M28: 53 | N28: Idiomas | O28: 0 | P28: =SUMIF(E$10:E$144,"53",D$10:D$144) -> 0 | Q28: =+O28-P28 -> 0
B29: 45590 | H29: TOTAL | I29: =SUM(I25:I28) -> 830 | J29: =SUM(J25:J28) -> 840 | K29: =+I29-J29 -> -10 | M29: 54 | N29: CNH [Matheus] | O29: 0 | P29: =SUMIF(E$10:E$144,"54",D$10:D$144) -> 0 | Q29: =+O29-P29 -> 0
B30: 45591 | M30: 55 | N30: Cursos | O30: 140 | P30: =SUMIF(E$10:E$144,"55",D$10:D$144) -> 0 | Q30: =+O30-P30 -> 140
B31: 45592 | H31: COMUNICAÇÃO | I31: Previsto | J31: Real | K31: Diferença | M31: 56 | N31: Livros | O31: 0 | P31: =SUMIF(E$10:E$144,"56",D$10:D$144) -> 0 | Q31: =+O31-P31 -> 0
B32: 45593 | G32: 15 | H32: Celular | I32: 45 | J32: 45 | K32: =+I32-J32 -> 0 | M32: 57 | N32: Faculdade [Jhenis] | O32: 0 | P32: =SUMIF(E$10:E$144,"57",D$10:D$144) -> 0 | Q32: =+O32-P32 -> 0
B33: 45594 | G33: 16 | H33: Internet | I33: 89 | J33: 89 | K33: =+I33-J33 -> 0 | M33: 58 | N33: Outros Educação | O33: 0 | P33: =SUMIF(E$10:E$144,"58",D$10:D$144) -> 0 | Q33: =+O33-P33 -> 0
B34: 45595 | G34: 17 | H34: Streaming | I34: 24 | J34: 24 | K34: =+I34-J34 -> 0 | N34: TOTAL | O34: =SUM(O27:O33) -> 140 | P34: =SUM(P27:P33) -> 0 | Q34: =+O34-P34 -> 140
G35: 18 | H35: Netflix | I35: 21.9 | J35: 22 | K35: =+I35-J35 -> -0.1
G36: 19 | H36: Amazon | I36: 10.9 | J36: 11 | K36: =+I36-J36 -> -0.1 | N36: LAZER | O36: Previsto | P36: Real | Q36: Diferença
G37: 20 | H37: Max Plus | I37: 34.5 | J37: 45 | K37: =+I37-J37 -> -10.5 | M37: 60 | N37: Cinema | O37: 450 | P37: =SUMIF(E$10:E$144,"60",D$10:D$144) -> 0 | Q37: =+O37-P37 -> 450
H38: TOTAL | I38: =SUM(I32:I37) -> 225.3 | J38: =SUM(J32:J37) -> 236 | K38: =+I38-J38 -> -10.7 | M38: 61 | N38: Esportes | O38: 0 | P38: =SUMIF(E$10:E$144,"61",D$10:D$144) -> 0 | Q38: =+O38-P38 -> 0
M39: 62 | N39: Shows [Consertos] | O39: 120 | P39: =SUMIF(E$10:E$144,"62",D$10:D$144) -> 0 | Q39: =+O39-P39 -> 120
H40: SAÚDE E CUIDADOS | I40: Previsto | J40: Real | K40: Diferença | M40: 63 | N40: Viagens [Férias] | O40: 148 | P40: =SUMIF(E$10:E$144,"63",D$10:D$144) -> 0 | Q40: =+O40-P40 -> 148
G41: 21 | H41: Academia | I41: 120 | J41: =SUMIF(E$10:E$144,"21",D$10:D$144) -> 0 | K41: =+I41-J41 -> 120 | M41: 64 | N41: Outros Lazer | O41: 60 | P41: =SUMIF(E$10:E$144,"64",D$10:D$144) -> 0 | Q41: =+O41-P41 -> 60
G42: 22 | H42: Emergencia Médica | I42: 120 | J42: =SUMIF(E$10:E$144,"22",D$10:D$144) -> 0 | K42: =+I42-J42 -> 120 | N42: TOTAL | O42: =SUM(O37:O41) -> 778 | P42: =SUM(P37:P41) -> 0 | Q42: =+O42-P42 -> 778
G43: 23 | H43: Emergência Dentista | I43: 100 | J43: =SUMIF(E$10:E$144,"23",D$10:D$144) -> 0 | K43: =+I43-J43 -> 100
G44: 24 | H44: Cosméticos | I44: 100 | J44: =SUMIF(E$10:E$144,"24",D$10:D$144) -> 0 | K44: =+I44-J44 -> 100 | N44: Necessidades Da Casa | O44: Previsto | P44: Real | Q44: Diferença
G45: 25 | H45: Dentista | I45: 150 | J45: =SUMIF(E$10:E$144,"25",D$10:D$144) -> 0 | K45: =+I45-J45 -> 150 | M45: 70 | N45: Cama | O45: 0 | P45: =SUMIF(E$10:E$144,"70",D$10:D$144) -> 0 | Q45: =+O45-P45 -> 0
G46: 26 | H46: Exames médicos | I46: 0 | J46: =SUMIF(E$10:E$144,"26",D$10:D$144) -> 0 | K46: =+I46-J46 -> 0 | M46: 71 | N46: Consertos [ Futuros | O46: 0 | P46: =SUMIF(E$10:E$144,"71",D$10:D$144) -> 0 | Q46: =+O46-P46 -> 0
G47: 27 | H47: Farmácia | I47: 89 | J47: =SUMIF(E$10:E$144,"27",D$10:D$144) -> 0 | K47: =+I47-J47 -> 89 | M47: 72 | N47: Geladeira | O47: 0 | P47: =SUMIF(E$10:E$144,"72",D$10:D$144) -> 0 | Q47: =+O47-P47 -> 0
G48: 28 | H48: Médicos particular | I48: 0 | J48: =SUMIF(E$10:E$144,"28",D$10:D$144) -> 0 | K48: =+I48-J48 -> 0 | M48: 73 | N48: Lava e seca | O48: 0 | P48: =SUMIF(E$10:E$144,"73",D$10:D$144) -> 0 | Q48: =+O48-P48 -> 0
G49: 29 | H49: Suplementos | I49: 0 | J49: =SUMIF(E$10:E$144,"29",D$10:D$144) -> 0 | K49: =+I49-J49 -> 0 | M49: 74 | N49: Lavanderia louça | O49: 0 | P49: =SUMIF(E$10:E$144,"74",D$10:D$144) -> 0 | Q49: =+O49-P49 -> 0
G50: 30 | H50: Outros Saúde | I50: 0 | J50: =SUMIF(E$10:E$144,"30",D$10:D$144) -> 0 | K50: =+I50-J50 -> 0 | M50: 75 | N50: Utensílios e decoração | O50: 0 | P50: =SUMIF(E$10:E$144,"75",D$10:D$144) -> 0 | Q50: =+O50-P50 -> 0
H51: TOTAL | I51: =SUM(I41:I50) -> 679 | J51: =SUM(J41:J50) -> 0 | K51: =+I51-J51 -> 679 | M51: 76 | N51: Outros Artigos | O51: 0 | P51: =SUMIF(E$10:E$144,"76",D$10:D$144) -> 0 | Q51: =+O51-P51 -> 0
N52: TOTAL | O52: =SUM(O45:O51) -> 0 | P52: =SUM(P45:P51) -> 0 | Q52: =+O52-P52 -> 0
H53: VESTUÁRIO | I53: Previsto | J53: Real | K53: Diferença
G54: 31 | H54: Roupas | I54: 39 | J54: =SUMIF(E$10:E$144,"31",D$10:D$144) -> 0 | K54: =+I54-J54 -> 39 | N54: OUTROS | O54: Previsto | P54: Real | Q54: Diferença
G55: 32 | H55: Sapatos | I55: 0 | J55: =SUMIF(E$10:E$144,"32",D$10:D$144) -> 0 | K55: =+I55-J55 -> 0 | M55: 80 | N55: Presentes | O55: 89 | P55: =SUMIF(E$10:E$144,"80",D$10:D$144) -> 0 | Q55: =+O55-P55 -> 89
G56: 33 | H56: Outros Vestuário | I56: 0 | J56: =SUMIF(E$10:E$144,"33",D$10:D$144) -> 0 | K56: =+I56-J56 -> 0 | M56: 81 | N56: Doações | O56: 0 | P56: =SUMIF(E$10:E$144,"81",D$10:D$144) -> 0 | Q56: =+O56-P56 -> 0
H57: TOTAL | I57: =SUM(I54:I56) -> 39 | J57: =SUM(J54:J56) -> 0 | K57: =+I57-J57 -> 39 | M57: 82 | N57: Ensaio | O57: 140 | P57: =SUMIF(E$10:E$144,"82",D$10:D$144) -> 0 | Q57: =+O57-P57 -> 140
M58: 83 | N58: Outros | O58: 0 | P58: =SUMIF(E$10:E$144,"83",D$10:D$144) -> 0 | Q58: =+O58-P58 -> 0
H59: Investimentos | I59: Previsto | J59: Rendimento | K59: Dividendos | N59: TOTAL | O59: =SUM(O55:O58) -> 229 | P59: =SUM(P55:P58) -> 0 | Q59: =+O59-P59 -> 229
G60: 34 | H60: Renda Variavel | I60: 1200 | J60: =SUMIF(E$10:E$144,"34",D$10:D$144) -> 0 | K60: =+I60-O620 -> 1200
G61: 35 | H61: Fundos imobiliário | I61: 1200 | J61: =SUMIF(E$10:E$144,"35",D$10:D$144) -> 0 | K61: =+I61-J61 -> 1200 | N61: FINANCEIRO | O61: Previsto | P61: Real | Q61: Diferença
G62: 36 | H62: Ações Baixo Risco | I62: 1200 | J62: =SUMIF(E$10:E$144,"36",D$10:D$144) -> 0 | K62: =+I62-J62 -> 1200 | M62: 90 | N62: Investimentos Mensais | O62: 0 | P62: =SUMIF(E$10:E$144,"90",D$10:D$144) -> 0 | Q62: =+O62-P62 -> 0
G63: 37 | H63: Ações Altos Risco | I63: 1200 | J63: =SUMIF(E$10:E$144,"37",D$10:D$144) -> 0 | K63: =+I63-J63 -> 1200 | M63: 91 | N63: Cartas de Crédito | O63: 0 | P63: =SUMIF(E$10:E$144,"91",D$10:D$144) -> 0 | Q63: =+O63-P63 -> 0
H64: TOTAL | I64: =SUM(I60:I63) -> 4800 | J64: =SUM(J60:J63) -> 0 | K64: =+I64-J64 -> 4800 | M64: 92 | N64: Outros Financeiro | O64: 0 | P64: =SUMIF(E$10:E$144,"92",D$10:D$144) -> 0 | Q64: =+O64-P64 -> 0
N65: TOTAL | O65: =SUM(O62:O64) -> 0 | P65: =SUM(P62:P64) -> 0 | Q65: =+O65-P65 -> 0

Sheet NOV
B1: Lançamento de Compras e Gastos Casa Organizada
I3: Previsto | K3: Real | N3: Diferença
H4: Renda 1 | I4: 2398 | J4: 1940 | K4: 1940 | N4: =I4-K4 -> 458
H5: Renda 2 | I5: 2500 | J5: 2500 | K5: 2500 | N5: =I5-J5 -> 0
B6: Despesas Mensais | H6: Renda Total | I6: =+I4+I5 -> 4898 | K6: =+K4+K5 -> 4440 | N6: =+I6-K6 -> 458
H7: Despesas | I7: =+SUM(I22,O24,I29,O34,I38,O42,I51,O52,I57,O59,I64,O65,) -> 12013.3 | K7: =+SUM(J22,J29,J38,J51,J57,J64,P65,P59,P52,P42,P34,P24,) -> 3361 | N7: =+I7-K7 -> 8652.3
B8: Data | C8: Despesa | D8: Valor | E8: Área | H8: Saldo | I8: =+I6-I7 -> -7115.3 | K8: =+K6-K7 -> 1079 | N8: =I8-K8 -> -8194.3
D9: =SUM(D10:D110) -> 0
B10: 45962
B11: 45963 | H11: MORADIA | I11: Previsto | J11: Real | K11: Diferença | N11: TRANSPORTE | O11: Previsto | P11: Real | Q11: Diferença
B12: 45964 | G12: 1 | H12: Caixa de Emergência | I12: 150 | J12: =SUMIF(E$10:E$144,"1",D$10:D$144) -> 0 | K12: =+I12-J12 -> 150 | M12: 40 | N12: Uber 99 | O12: 58 | P12: 45 | Q12: =+O12-P12 -> 13
B13: 45965 | G13: 2 | H13: Inevitavelmento fixo | I13: 1200 | J13: =SUMIF(E$10:E$144,"2",D$10:D$144) -> 0 | K13: =+I13-J13 -> 1200 | M13: 41 | N13: Uber | O13: 68 | P13: =SUMIF(E$10:E$144,"41",D$10:D$144) -> 0 | Q13: =+O13-P13 -> 68
B14: 45966 | G14: 3 | H14: Das Jhenis | I14: 250 | J14: =SUMIF(E$10:E$144,"3",D$10:D$144) -> 0 | K14: =+I14-J14 -> 250 | M14: 42 | N14: Transporte Público | O14: 440 | P14: 0 | Q14: =+O14-P14 -> 440
B15: 45967 | G15: 4 | H15: Cartao Jhenismara | I15: 1200 | J15: 1400 | K15: =+I15-J15 -> -200 | M15: 43 | N15: Transporte Trabalho J | O15: 240 | P15: 143 | Q15: =+O15-P15 -> 97
B16: 45968 | G16: 5 | H16: Emergência Casa | I16: 120 | J16: =SUMIF(E$10:E$144,"5",D$10:D$144) -> 0 | K16: =+I16-J16 -> 120 | M16: 44 | N16: Transporte Trabalho M | O16: 110 | P16: 240 | Q16: =+O16-P16 -> -130
B17: 45969 | G17: 6 | H17: Energia | I17: 150 | J17: 150 | K17: =+I17-J17 -> 0 | M17: 45 | N17: Caixa Carro J | O17: 0 | P17: =SUMIF(E$10:E$144,"45",D$10:D$144) -> 0 | Q17: =+O17-P17 -> 0
B18: 45970 | G18: 7 | H18: Água | I18: 77 | J18: 77 | K18: =+I18-J18 -> 0 | M18: 46 | N18: Caixa Carro M | O18: 0 | P18: =SUMIF(E$10:E$144,"46",D$10:D$144) -> 0 | Q18: =+O18-P18 -> 0
B19: 45971 | G19: 8 | H19: Gás | I19: 55 | J19: 55 | K19: =+I19-J19 -> 0 | M19: 47 | O19: 0 | P19: =SUMIF(E$10:E$144,"47",D$10:D$144) -> 0 | Q19: =+O19-P19 -> 0
B20: 45972 | G20: 9 | H20: Cartao (Matheus) | I20: 175 | J20: 175 | K20: =+I20-J20 -> 0 | M20: 48 | O20: 0 | P20: =SUMIF(E$10:E$144,"48",D$10:D$144) -> 0 | Q20: =+O20-P20 -> 0
B21: 45973 | G21: 10 | H21: Outrs Dispesas | J21: =SUMIF(E$10:E$144,"10",D$10:D$144) -> 0 | K21: =+I21-J21 -> 0 | M21: 49 | O21: 0 | P21: 0 | Q21: =+O21-P21 -> 0
B22: 45974 | H22: TOTAL | I22: =SUM(I12:I21) -> 3377 | J22: =SUM(J12:J21) -> 1857 | K22: =+I22-J22 -> 1520 | M22: 50 | O22: 0 | P22: 0 | Q22: =+O22-P22 -> 0
B23: 45975 | M23: 51 | N23: Outros Transporte | O23: 0 | P23: =SUMIF(E$10:E$144,"51",D$10:D$144) -> 0 | Q23: =+O23-P23 -> 0
B24: 45976 | H24: ALIMENTAÇÃO | I24: Previsto | J24: Real | K24: Diferença | N24: TOTAL | O24: =SUM(O12:O23) -> 916 | P24: =SUM(P12:P23) -> 428 | Q24: =+O24-P24 -> 488
B25: 45977 | G25: 11 | H25: Supermercado | I25: 450 | J25: 450 | K25: =+I25-J25 -> 0
B26: 45978 | G26: 12 | H26: Restaurante | I26: 140 | J26: 140 | K26: =+I26-J26 -> 0 | N26: EDUCAÇÃO | O26: Previsto | P26: Real | Q26: Diferença
B27: 45979 | G27: 13 | H27: Café \ Almoço | I27: 100 | J27: 250 | K27: =+I27-J27 -> -150 | M27: 52 | N27: Mensalidades | O27: 0 | P27: =SUMIF(E$10:E$144,"52",D$10:D$144) -> 0 | Q27: =+O27-P27 -> 0
B28: 45980 | G28: 14 | H28: Pedidos IFood | I28: 140 | J28: =SUMIF(E$10:E$144,"14",D$10:D$144) -> 0 | K28: =+I28-J28 -> 140 | M28: 53 | N28: Idiomas | O28: 0 | P28: =SUMIF(E$10:E$144,"53",D$10:D$144) -> 0 | Q28: =+O28-P28 -> 0
B29: 45981 | H29: TOTAL | I29: =SUM(I25:I28) -> 830 | J29: =SUM(J25:J28) -> 840 | K29: =+I29-J29 -> -10 | M29: 54 | N29: CNH [Matheus] | O29: 0 | P29: =SUMIF(E$10:E$144,"54",D$10:D$144) -> 0 | Q29: =+O29-P29 -> 0
B30: 45982 | M30: 55 | N30: Cursos | O30: 140 | P30: =SUMIF(E$10:E$144,"55",D$10:D$144) -> 0 | Q30: =+O30-P30 -> 140
B31: 45983 | H31: COMUNICAÇÃO | I31: Previsto | J31: Real | K31: Diferença | M31: 56 | N31: Livros | O31: 0 | P31: =SUMIF(E$10:E$144,"56",D$10:D$144) -> 0 | Q31: =+O31-P31 -> 0
B32: 45984 | G32: 15 | H32: Celular | I32: 45 | J32: 45 | K32: =+I32-J32 -> 0 | M32: 57 | N32: Faculdade [Jhenis] | O32: 0 | P32: =SUMIF(E$10:E$144,"57",D$10:D$144) -> 0 | Q32: =+O32-P32 -> 0
B33: 45985 | G33: 16 | H33: Internet | I33: 89 | J33: 89 | K33: =+I33-J33 -> 0 | M33: 58 | N33: Outros Educação | O33: 0 | P33: =SUMIF(E$10:E$144,"58",D$10:D$144) -> 0 | Q33: =+O33-P33 -> 0
B34: 45986 | G34: 17 | H34: Streaming | I34: 24 | J34: 24 | K34: =+I34-J34 -> 0 | N34: TOTAL | O34: =SUM(O27:O33) -> 140 | P34: =SUM(P27:P33) -> 0 | Q34: =+O34-P34 -> 140
B35: 45987 | G35: 18 | H35: Netflix | I35: 21.9 | J35: 22 | K35: =+I35-J35 -> -0.1
B36: 45988 | G36: 19 | H36: Amazon | I36: 10.9 | J36: 11 | K36: =+I36-J36 -> -0.1 | N36: LAZER | O36: Previsto | P36: Real | Q36: Diferença
B37: 45989 | G37: 20 | H37: Max Plus | I37: 34.5 | J37: 45 | K37: =+I37-J37 -> -10.5 | M37: 60 | N37: Cinema | O37: 450 | P37: =SUMIF(E$10:E$144,"60",D$10:D$144) -> 0 | Q37: =+O37-P37 -> 450
B38: 45990 | H38: TOTAL | I38: =SUM(I32:I37) -> 225.3 | J38: =SUM(J32:J37) -> 236 | K38: =+I38-J38 -> -10.7 | M38: 61 | N38: Esportes | O38: 0 | P38: =SUMIF(E$10:E$144,"61",D$10:D$144) -> 0 | Q38: =+O38-P38 -> 0
B39: 45991 | M39: 62 | N39: Shows [Consertos] | O39: 120 | P39: =SUMIF(E$10:E$144,"62",D$10:D$144) -> 0 | Q39: =+O39-P39 -> 120
H40: SAÚDE E CUIDADOS | I40: Previsto | J40: Real | K40: Diferença | M40: 63 | N40: Viagens [Férias] | O40: 148 | P40: =SUMIF(E$10:E$144,"63",D$10:D$144) -> 0 | Q40: =+O40-P40 -> 148
G41: 21 | H41: Academia | I41: 120 | J41: =SUMIF(E$10:E$144,"21",D$10:D$144) -> 0 | K41: =+I41-J41 -> 120 | M41: 64 | N41: Outros Lazer | O41: 60 | P41: =SUMIF(E$10:E$144,"64",D$10:D$144) -> 0 | Q41: =+O41-P41 -> 60
G42: 22 | H42: Emergencia Médica | I42: 120 | J42: =SUMIF(E$10:E$144,"22",D$10:D$144) -> 0 | K42: =+I42-J42 -> 120 | N42: TOTAL | O42: =SUM(O37:O41) -> 778 | P42: =SUM(P37:P41) -> 0 | Q42: =+O42-P42 -> 778
G43: 23 | H43: Emergência Dentista | I43: 100 | J43: =SUMIF(E$10:E$144,"23",D$10:D$144) -> 0 | K43: =+I43-J43 -> 100
G44: 24 | H44: Cosméticos | I44: 100 | J44: =SUMIF(E$10:E$144,"24",D$10:D$144) -> 0 | K44: =+I44-J44 -> 100 | N44: Necessidades Da Casa | O44: Previsto | P44: Real | Q44: Diferença
G45: 25 | H45: Dentista | I45: 150 | J45: =SUMIF(E$10:E$144,"25",D$10:D$144) -> 0 | K45: =+I45-J45 -> 150 | M45: 70 | N45: Cama | O45: 0 | P45: =SUMIF(E$10:E$144,"70",D$10:D$144) -> 0 | Q45: =+O45-P45 -> 0
G46: 26 | H46: Exames médicos | I46: 0 | J46: =SUMIF(E$10:E$144,"26",D$10:D$144) -> 0 | K46: =+I46-J46 -> 0 | M46: 71 | N46: Consertos [ Futuros | O46: 0 | P46: =SUMIF(E$10:E$144,"71",D$10:D$144) -> 0 | Q46: =+O46-P46 -> 0
G47: 27 | H47: Farmácia | I47: 89 | J47: =SUMIF(E$10:E$144,"27",D$10:D$144) -> 0 | K47: =+I47-J47 -> 89 | M47: 72 | N47: Geladeira | O47: 0 | P47: =SUMIF(E$10:E$144,"72",D$10:D$144) -> 0 | Q47: =+O47-P47 -> 0
G48: 28 | H48: Médicos particular | I48: 0 | J48: =SUMIF(E$10:E$144,"28",D$10:D$144) -> 0 | K48: =+I48-J48 -> 0 | M48: 73 | N48: Lava e seca | O48: 0 | P48: =SUMIF(E$10:E$144,"73",D$10:D$144) -> 0 | Q48: =+O48-P48 -> 0
G49: 29 | H49: Suplementos | I49: 0 | J49: =SUMIF(E$10:E$144,"29",D$10:D$144) -> 0 | K49: =+I49-J49 -> 0 | M49: 74 | N49: Lavanderia louça | O49: 0 | P49: =SUMIF(E$10:E$144,"74",D$10:D$144) -> 0 | Q49: =+O49-P49 -> 0
G50: 30 | H50: Outros Saúde | I50: 0 | J50: =SUMIF(E$10:E$144,"30",D$10:D$144) -> 0 | K50: =+I50-J50 -> 0 | M50: 75 | N50: Utensílios e decoração | O50: 0 | P50: =SUMIF(E$10:E$144,"75",D$10:D$144) -> 0 | Q50: =+O50-P50 -> 0
H51: TOTAL | I51: =SUM(I41:I50) -> 679 | J51: =SUM(J41:J50) -> 0 | K51: =+I51-J51 -> 679 | M51: 76 | N51: Outros Artigos | O51: 0 | P51: =SUMIF(E$10:E$144,"76",D$10:D$144) -> 0 | Q51: =+O51-P51 -> 0
N52: TOTAL | O52: =SUM(O45:O51) -> 0 | P52: =SUM(P45:P51) -> 0 | Q52: =+O52-P52 -> 0
H53: VESTUÁRIO | I53: Previsto | J53: Real | K53: Diferença
G54: 31 | H54: Roupas | I54: 39 | J54: =SUMIF(E$10:E$144,"31",D$10:D$144) -> 0 | K54: =+I54-J54 -> 39 | N54: OUTROS | O54: Previsto | P54: Real | Q54: Diferença
G55: 32 | H55: Sapatos | I55: 0 | J55: =SUMIF(E$10:E$144,"32",D$10:D$144) -> 0 | K55: =+I55-J55 -> 0 | M55: 80 | N55: Presentes | O55: 89 | P55: =SUMIF(E$10:E$144,"80",D$10:D$144) -> 0 | Q55: =+O55-P55 -> 89
G56: 33 | H56: Outros Vestuário | I56: 0 | J56: =SUMIF(E$10:E$144,"33",D$10:D$144) -> 0 | K56: =+I56-J56 -> 0 | M56: 81 | N56: Doações | O56: 0 | P56: =SUMIF(E$10:E$144,"81",D$10:D$144) -> 0 | Q56: =+O56-P56 -> 0
H57: TOTAL | I57: =SUM(I54:I56) -> 39 | J57: =SUM(J54:J56) -> 0 | K57: =+I57-J57 -> 39 | M57: 82 | N57: Ensaio | O57: 140 | P57: =SUMIF(E$10:E$144,"82",D$10:D$144) -> 0 | Q57: =+O57-P57 -> 140
M58: 83 | N58: Outros | O58: 0 | P58: =SUMIF(E$10:E$144,"83",D$10:D$144) -> 0 | Q58: =+O58-P58 -> 0
H59: Investimentos | I59: Previsto | J59: Rendimento | K59: Dividendos | N59: TOTAL | O59: =SUM(O55:O58) -> 229 | P59: =SUM(P55:P58) -> 0 | Q59: =+O59-P59 -> 229
G60: 34 | H60: Renda Variavel | I60: 1200 | J60: =SUMIF(E$10:E$144,"34",D$10:D$144) -> 0 | K60: =+I60-O620 -> 1200
G61: 35 | H61: Fundos imobiliário | I61: 1200 | J61: =SUMIF(E$10:E$144,"35",D$10:D$144) -> 0 | K61: =+I61-J61 -> 1200 | N61: FINANCEIRO | O61: Previsto | P61: Real | Q61: Diferença
G62: 36 | H62: Ações Baixo Risco | I62: 1200 | J62: =SUMIF(E$10:E$144,"36",D$10:D$144) -> 0 | K62: =+I62-J62 -> 1200 | M62: 90 | N62: Investimentos Mensais | O62: 0 | P62: =SUMIF(E$10:E$144,"90",D$10:D$144) -> 0 | Q62: =+O62-P62 -> 0
G63: 37 | H63: Ações Altos Risco | I63: 1200 | J63: =SUMIF(E$10:E$144,"37",D$10:D$144) -> 0 | K63: =+I63-J63 -> 1200 | M63: 91 | N63: Cartas de Crédito | O63: 0 | P63: =SUMIF(E$10:E$144,"91",D$10:D$144) -> 0 | Q63: =+O63-P63 -> 0
H64: TOTAL | I64: =SUM(I60:I63) -> 4800 | J64: =SUM(J60:J63) -> 0 | K64: =+I64-J64 -> 4800 | M64: 92 | N64: Outros Financeiro | O64: 0 | P64: =SUMIF(E$10:E$144,"92",D$10:D$144) -> 0 | Q64: =+O64-P64 -> 0
N65: TOTAL | O65: =SUM(O62:O64) -> 0 | P65: =SUM(P62:P64) -> 0 | Q65: =+O65-P65 -> 0

Sheet DEZ
B1: Lançamento de Compras e Gastos Casa Organizada
I3: Previsto | K3: Real | N3: Diferença
H4: Renda 1 | I4: 2398 | J4: 1940 | K4: 1940 | N4: =I4-K4 -> 458
H5: Renda 2 | I5: 2500 | J5: 2500 | K5: 2500 | N5: =I5-J5 -> 0
B6: Despesas Mensais | H6: Renda Total | I6: =+I4+I5 -> 4898 | K6: =+K4+K5 -> 4440 | N6: =+I6-K6 -> 458
H7: Despesas | I7: =+SUM(I22,O24,I29,O34,I38,O42,I51,O52,I57,O59,I64,O65,) -> 12013.3 | K7: =+SUM(J22,J29,J38,J51,J57,J64,P65,P59,P52,P42,P34,P24,) -> 3361 | N7: =+I7-K7 -> 8652.3
B8: Data | C8: Despesa | D8: Valor | E8: Área | H8: Saldo | I8: =+I6-I7 -> -7115.3 | K8: =+K6-K7 -> 1079 | N8: =I8-K8 -> -8194.3
D9: =SUM(D10:D111) -> 0
B10: 45992
B11: 45993 | H11: MORADIA | I11: Previsto | J11: Real | K11: Diferença | N11: TRANSPORTE | O11: Previsto | P11: Real | Q11: Diferença
B12: 45994 | G12: 1 | H12: Caixa de Emergência | I12: 150 | J12: =SUMIF(E$10:E$144,"1",D$10:D$144) -> 0 | K12: =+I12-J12 -> 150 | M12: 40 | N12: Uber 99 | O12: 58 | P12: 45 | Q12: =+O12-P12 -> 13
B13: 45995 | G13: 2 | H13: Inevitavelmento fixo | I13: 1200 | J13: =SUMIF(E$10:E$144,"2",D$10:D$144) -> 0 | K13: =+I13-J13 -> 1200 | M13: 41 | N13: Uber | O13: 68 | P13: =SUMIF(E$10:E$144,"41",D$10:D$144) -> 0 | Q13: =+O13-P13 -> 68
B14: 45996 | G14: 3 | H14: Das Jhenis | I14: 250 | J14: =SUMIF(E$10:E$144,"3",D$10:D$144) -> 0 | K14: =+I14-J14 -> 250 | M14: 42 | N14: Transporte Público | O14: 440 | P14: 0 | Q14: =+O14-P14 -> 440
B15: 45997 | G15: 4 | H15: Cartao Jhenismara | I15: 1200 | J15: 1400 | K15: =+I15-J15 -> -200 | M15: 43 | N15: Transporte Trabalho J | O15: 240 | P15: 143 | Q15: =+O15-P15 -> 97
B16: 45998 | G16: 5 | H16: Emergência Casa | I16: 120 | J16: =SUMIF(E$10:E$144,"5",D$10:D$144) -> 0 | K16: =+I16-J16 -> 120 | M16: 44 | N16: Transporte Trabalho M | O16: 110 | P16: 240 | Q16: =+O16-P16 -> -130
B17: 45999 | G17: 6 | H17: Energia | I17: 150 | J17: 150 | K17: =+I17-J17 -> 0 | M17: 45 | N17: Caixa Carro J | O17: 0 | P17: =SUMIF(E$10:E$144,"45",D$10:D$144) -> 0 | Q17: =+O17-P17 -> 0
B18: 46000 | G18: 7 | H18: Água | I18: 77 | J18: 77 | K18: =+I18-J18 -> 0 | M18: 46 | N18: Caixa Carro M | O18: 0 | P18: =SUMIF(E$10:E$144,"46",D$10:D$144) -> 0 | Q18: =+O18-P18 -> 0
B19: 46001 | G19: 8 | H19: Gás | I19: 55 | J19: 55 | K19: =+I19-J19 -> 0 | M19: 47 | O19: 0 | P19: =SUMIF(E$10:E$144,"47",D$10:D$144) -> 0 | Q19: =+O19-P19 -> 0
B20: 46002 | G20: 9 | H20: Cartao (Matheus) | I20: 175 | J20: 175 | K20: =+I20-J20 -> 0 | M20: 48 | O20: 0 | P20: =SUMIF(E$10:E$144,"48",D$10:D$144) -> 0 | Q20: =+O20-P20 -> 0
B21: 46003 | G21: 10 | H21: Outrs Dispesas | J21: =SUMIF(E$10:E$144,"10",D$10:D$144) -> 0 | K21: =+I21-J21 -> 0 | M21: 49 | O21: 0 | P21: 0 | Q21: =+O21-P21 -> 0
B22: 46004 | H22: TOTAL | I22: =SUM(I12:I21) -> 3377 | J22: =SUM(J12:J21) -> 1857 | K22: =+I22-J22 -> 1520 | M22: 50 | O22: 0 | P22: 0 | Q22: =+O22-P22 -> 0
B23: 46005 | M23: 51 | N23: Outros Transporte | O23: 0 | P23: =SUMIF(E$10:E$144,"51",D$10:D$144) -> 0 | Q23: =+O23-P23 -> 0
B24: 46006 | H24: ALIMENTAÇÃO | I24: Previsto | J24: Real | K24: Diferença | N24: TOTAL | O24: =SUM(O12:O23) -> 916 | P24: =SUM(P12:P23) -> 428 | Q24: =+O24-P24 -> 488
B25: 46007 | G25: 11 | H25: Supermercado | I25: 450 | J25: 450 | K25: =+I25-J25 -> 0
B26: 46008 | G26: 12 | H26: Restaurante | I26: 140 | J26: 140 | K26: =+I26-J26 -> 0 | N26: EDUCAÇÃO | O26: Previsto | P26: Real | Q26: Diferença
B27: 46009 | G27: 13 | H27: Café \ Almoço | I27: 100 | J27: 250 | K27: =+I27-J27 -> -150 | M27: 52 | N27: Mensalidades | O27: 0 | P27: =SUMIF(E$10:E$144,"52",D$10:D$144) -> 0 | Q27: =+O27-P27 -> 0
B28: 46010 | G28: 14 | H28: Pedidos IFood | I28: 140 | J28: =SUMIF(E$10:E$144,"14",D$10:D$144) -> 0 | K28: =+I28-J28 -> 140 | M28: 53 | N28: Idiomas | O28: 0 | P28: =SUMIF(E$10:E$144,"53",D$10:D$144) -> 0 | Q28: =+O28-P28 -> 0
B29: 46011 | H29: TOTAL | I29: =SUM(I25:I28) -> 830 | J29: =SUM(J25:J28) -> 840 | K29: =+I29-J29 -> -10 | M29: 54 | N29: CNH [Matheus] | O29: 0 | P29: =SUMIF(E$10:E$144,"54",D$10:D$144) -> 0 | Q29: =+O29-P29 -> 0
B30: 46012 | M30: 55 | N30: Cursos | O30: 140 | P30: =SUMIF(E$10:E$144,"55",D$10:D$144) -> 0 | Q30: =+O30-P30 -> 140
B31: 46013 | H31: COMUNICAÇÃO | I31: Previsto | J31: Real | K31: Diferença | M31: 56 | N31: Livros | O31: 0 | P31: =SUMIF(E$10:E$144,"56",D$10:D$144) -> 0 | Q31: =+O31-P31 -> 0
B32: 46014 | G32: 15 | H32: Celular | I32: 45 | J32: 45 | K32: =+I32-J32 -> 0 | M32: 57 | N32: Faculdade [Jhenis] | O32: 0 | P32: =SUMIF(E$10:E$144,"57",D$10:D$144) -> 0 | Q32: =+O32-P32 -> 0
B33: 46015 | G33: 16 | H33: Internet | I33: 89 | J33: 89 | K33: =+I33-J33 -> 0 | M33: 58 | N33: Outros Educação | O33: 0 | P33: =SUMIF(E$10:E$144,"58",D$10:D$144) -> 0 | Q33: =+O33-P33 -> 0
B34: 46016 | G34: 17 | H34: Streaming | I34: 24 | J34: 24 | K34: =+I34-J34 -> 0 | N34: TOTAL | O34: =SUM(O27:O33) -> 140 | P34: =SUM(P27:P33) -> 0 | Q34: =+O34-P34 -> 140
B35: 46017 | G35: 18 | H35: Netflix | I35: 21.9 | J35: 22 | K35: =+I35-J35 -> -0.1
B36: 46018 | G36: 19 | H36: Amazon | I36: 10.9 | J36: 11 | K36: =+I36-J36 -> -0.1 | N36: LAZER | O36: Previsto | P36: Real | Q36: Diferença
B37: 46019 | G37: 20 | H37: Max Plus | I37: 34.5 | J37: 45 | K37: =+I37-J37 -> -10.5 | M37: 60 | N37: Cinema | O37: 450 | P37: =SUMIF(E$10:E$144,"60",D$10:D$144) -> 0 | Q37: =+O37-P37 -> 450
B38: 46020 | H38: TOTAL | I38: =SUM(I32:I37) -> 225.3 | J38: =SUM(J32:J37) -> 236 | K38: =+I38-J38 -> -10.7 | M38: 61 | N38: Esportes | O38: 0 | P38: =SUMIF(E$10:E$144,"61",D$10:D$144) -> 0 | Q38: =+O38-P38 -> 0
B39: 46021 | M39: 62 | N39: Shows [Consertos] | O39: 120 | P39: =SUMIF(E$10:E$144,"62",D$10:D$144) -> 0 | Q39: =+O39-P39 -> 120
B40: 46022 | H40: SAÚDE E CUIDADOS | I40: Previsto | J40: Real | K40: Diferença | M40: 63 | N40: Viagens [Férias] | O40: 148 | P40: =SUMIF(E$10:E$144,"63",D$10:D$144) -> 0 | Q40: =+O40-P40 -> 148
G41: 21 | H41: Academia | I41: 120 | J41: =SUMIF(E$10:E$144,"21",D$10:D$144) -> 0 | K41: =+I41-J41 -> 120 | M41: 64 | N41: Outros Lazer | O41: 60 | P41: =SUMIF(E$10:E$144,"64",D$10:D$144) -> 0 | Q41: =+O41-P41 -> 60
G42: 22 | H42: Emergencia Médica | I42: 120 | J42: =SUMIF(E$10:E$144,"22",D$10:D$144) -> 0 | K42: =+I42-J42 -> 120 | N42: TOTAL | O42: =SUM(O37:O41) -> 778 | P42: =SUM(P37:P41) -> 0 | Q42: =+O42-P42 -> 778
G43: 23 | H43: Emergência Dentista | I43: 100 | J43: =SUMIF(E$10:E$144,"23",D$10:D$144) -> 0 | K43: =+I43-J43 -> 100
G44: 24 | H44: Cosméticos | I44: 100 | J44: =SUMIF(E$10:E$144,"24",D$10:D$144) -> 0 | K44: =+I44-J44 -> 100 | N44: Necessidades Da Casa | O44: Previsto | P44: Real | Q44: Diferença
G45: 25 | H45: Dentista | I45: 150 | J45: =SUMIF(E$10:E$144,"25",D$10:D$144) -> 0 | K45: =+I45-J45 -> 150 | M45: 70 | N45: Cama | O45: 0 | P45: =SUMIF(E$10:E$144,"70",D$10:D$144) -> 0 | Q45: =+O45-P45 -> 0
G46: 26 | H46: Exames médicos | I46: 0 | J46: =SUMIF(E$10:E$144,"26",D$10:D$144) -> 0 | K46: =+I46-J46 -> 0 | M46: 71 | N46: Consertos [ Futuros | O46: 0 | P46: =SUMIF(E$10:E$144,"71",D$10:D$144) -> 0 | Q46: =+O46-P46 -> 0
G47: 27 | H47: Farmácia | I47: 89 | J47: =SUMIF(E$10:E$144,"27",D$10:D$144) -> 0 | K47: =+I47-J47 -> 89 | M47: 72 | N47: Geladeira | O47: 0 | P47: =SUMIF(E$10:E$144,"72",D$10:D$144) -> 0 | Q47: =+O47-P47 -> 0
G48: 28 | H48: Médicos particular | I48: 0 | J48: =SUMIF(E$10:E$144,"28",D$10:D$144) -> 0 | K48: =+I48-J48 -> 0 | M48: 73 | N48: Lava e seca | O48: 0 | P48: =SUMIF(E$10:E$144,"73",D$10:D$144) -> 0 | Q48: =+O48-P48 -> 0
G49: 29 | H49: Suplementos | I49: 0 | J49: =SUMIF(E$10:E$144,"29",D$10:D$144) -> 0 | K49: =+I49-J49 -> 0 | M49: 74 | N49: Lavanderia louça | O49: 0 | P49: =SUMIF(E$10:E$144,"74",D$10:D$144) -> 0 | Q49: =+O49-P49 -> 0
G50: 30 | H50: Outros Saúde | I50: 0 | J50: =SUMIF(E$10:E$144,"30",D$10:D$144) -> 0 | K50: =+I50-J50 -> 0 | M50: 75 | N50: Utensílios e decoração | O50: 0 | P50: =SUMIF(E$10:E$144,"75",D$10:D$144) -> 0 | Q50: =+O50-P50 -> 0
H51: TOTAL | I51: =SUM(I41:I50) -> 679 | J51: =SUM(J41:J50) -> 0 | K51: =+I51-J51 -> 679 | M51: 76 | N51: Outros Artigos | O51: 0 | P51: =SUMIF(E$10:E$144,"76",D$10:D$144) -> 0 | Q51: =+O51-P51 -> 0
N52: TOTAL | O52: =SUM(O45:O51) -> 0 | P52: =SUM(P45:P51) -> 0 | Q52: =+O52-P52 -> 0
H53: VESTUÁRIO | I53: Previsto | J53: Real | K53: Diferença
G54: 31 | H54: Roupas | I54: 39 | J54: =SUMIF(E$10:E$144,"31",D$10:D$144) -> 0 | K54: =+I54-J54 -> 39 | N54: OUTROS | O54: Previsto | P54: Real | Q54: Diferença
G55: 32 | H55: Sapatos | I55: 0 | J55: =SUMIF(E$10:E$144,"32",D$10:D$144) -> 0 | K55: =+I55-J55 -> 0 | M55: 80 | N55: Presentes | O55: 89 | P55: =SUMIF(E$10:E$144,"80",D$10:D$144) -> 0 | Q55: =+O55-P55 -> 89
G56: 33 | H56: Outros Vestuário | I56: 0 | J56: =SUMIF(E$10:E$144,"33",D$10:D$144) -> 0 | K56: =+I56-J56 -> 0 | M56: 81 | N56: Doações | O56: 0 | P56: =SUMIF(E$10:E$144,"81",D$10:D$144) -> 0 | Q56: =+O56-P56 -> 0
H57: TOTAL | I57: =SUM(I54:I56) -> 39 | J57: =SUM(J54:J56) -> 0 | K57: =+I57-J57 -> 39 | M57: 82 | N57: Ensaio | O57: 140 | P57: =SUMIF(E$10:E$144,"82",D$10:D$144) -> 0 | Q57: =+O57-P57 -> 140
M58: 83 | N58: Outros | O58: 0 | P58: =SUMIF(E$10:E$144,"83",D$10:D$144) -> 0 | Q58: =+O58-P58 -> 0
H59: Investimentos | I59: Previsto | J59: Rendimento | K59: Dividendos | N59: TOTAL | O59: =SUM(O55:O58) -> 229 | P59: =SUM(P55:P58) -> 0 | Q59: =+O59-P59 -> 229
G60: 34 | H60: Renda Variavel | I60: 1200 | J60: =SUMIF(E$10:E$144,"34",D$10:D$144) -> 0 | K60: =+I60-O620 -> 1200
G61: 35 | H61: Fundos imobiliário | I61: 1200 | J61: =SUMIF(E$10:E$144,"35",D$10:D$144) -> 0 | K61: =+I61-J61 -> 1200 | N61: FINANCEIRO | O61: Previsto | P61: Real | Q61: Diferença
G62: 36 | H62: Ações Baixo Risco | I62: 1200 | J62: =SUMIF(E$10:E$144,"36",D$10:D$144) -> 0 | K62: =+I62-J62 -> 1200 | M62: 90 | N62: Investimentos Mensais | O62: 0 | P62: =SUMIF(E$10:E$144,"90",D$10:D$144) -> 0 | Q62: =+O62-P62 -> 0
G63: 37 | H63: Ações Altos Risco | I63: 1200 | J63: =SUMIF(E$10:E$144,"37",D$10:D$144) -> 0 | K63: =+I63-J63 -> 1200 | M63: 91 | N63: Cartas de Crédito | O63: 0 | P63: =SUMIF(E$10:E$144,"91",D$10:D$144) -> 0 | Q63: =+O63-P63 -> 0
H64: TOTAL | I64: =SUM(I60:I63) -> 4800 | J64: =SUM(J60:J63) -> 0 | K64: =+I64-J64 -> 4800 | M64: 92 | N64: Outros Financeiro | O64: 0 | P64: =SUMIF(E$10:E$144,"92",D$10:D$144) -> 0 | Q64: =+O64-P64 -> 0
N65: TOTAL | O65: =SUM(O62:O64) -> 0 | P65: =SUM(P62:P64) -> 0 | Q65: =+O65-P65 -> 0

Sheet Resumo
B1: Resumo Anual | F1: Lançamento de Compras e Gastos Casa Organizada
C3: JAN | D3: FEV | E3: MAR | F3: ABR | G3: MAI | H3: JUN | I3: JUL | J3: AGO | K3: SET | L3: OUT | M3: NOV | N3: DEZ | O3: TOTAL
B4: RENDA TOTAL | C4: =+JAN!K6 -> 4730 | D4: =+FEV!K6 -> 4440 | E4: =+MAR!K6 -> 4440 | F4: =+ABR!K6 -> 4440 | G4: =+MAI!K6 -> 4440 | H4: =+JUN!K6 -> 4440 | I4: =+JUL!K6 -> 4440 | K4: =+SET!K6 -> 4440 | L4: =+OUT!K6 -> 4440 | M4: =+NOV!K6 -> 4440 | N4: =+DEZ!K6 -> 4440 | O4: =SUM(C4:N4) -> 49130
B5: Renda 1 | C5: =+JAN!$K4 -> 2230 | D5: =+FEV!$K4 -> 1940 | E5: =+MAR!$K4 -> 1940 | F5: =+ABR!$K4 -> 1940 | G5: =+MAI!$K4 -> 1940 | H5: =+JUN!$K4 -> 1940 | I5: =+JUL!$K4 -> 1940 | J5: =+AGO!$K4 -> 1940 | K5: =+SET!$K4 -> 1940 | L5: =+OUT!$K4 -> 1940 | M5: =+NOV!$K4 -> 1940 | N5: =+DEZ!$K4 -> 1940 | O5: =SUM(C5:N5) -> 23570
B6: Renda 2 | C6: =+JAN!$K5 -> 2500 | D6: =+FEV!$K5 -> 2500 | E6: =+MAR!$K5 -> 2500 | F6: =+ABR!$K5 -> 2500 | G6: =+MAI!$K5 -> 2500 | H6: =+JUN!$K5 -> 2500 | I6: =+JUL!$K5 -> 2500 | J6: =+AGO!$K5 -> 2500 | K6: =+SET!$K5 -> 2500 | L6: =+OUT!$K5 -> 2500 | M6: =+NOV!$K5 -> 2500 | N6: =+DEZ!$K5 -> 2500 | O6: =SUM(C6:N6) -> 30000
B8: DESPESA TOTAL | C8: =+JAN!$K$7 -> 3651 | D8: =+FEV!$K$7 -> 3361 | E8: =+MAR!$K$7 -> 3361 | F8: =+ABR!$K$7 -> 3361 | G8: =+MAI!$K$7 -> 3361 | H8: =+JUN!$K$7 -> 3361 | I8: =+JUL!$K$7 -> 3361 | J8: =+AGO!$K$7 -> 3361 | K8: =+SET!$K$7 -> 3361 | L8: =+OUT!$K$7 -> 3361 | M8: =+NOV!$K$7 -> 3361 | N8: =+DEZ!$K$7 -> 3361 | O8: =+SUM(C8:N8) -> 40622
A9: 1 | B9: Moradia | C9: =+JAN!K22 -> 610 | D9: =+FEV!K22 -> 1520 | E9: =+MAR!$J$22 -> 1857 | F9: =+ABR!$J$22 -> 1857 | G9: =+MAI!$J$22 -> 1857 | H9: =+JUN!$J$22 -> 1857 | I9: =+JUL!$J$22 -> 1857 | J9: =+AGO!$J$22 -> 1857 | K9: =+SET!$J$22 -> 1857 | L9: =+OUT!$J$17 -> 150 | M9: =+NOV!$J$20 -> 175 | N9: =+DEZ!$J$21 -> 0 | O9: =SUM(C9:N9) -> 15454
A10: 2 | B10: Alimentação | C10: =+JAN!$J$29 -> 840 | D10: =+FEV!$J$29 -> 840 | E10: =+MAR!$J$29 -> 840 | F10: =+ABR!$J$29 -> 840 | G10: =+MAI!$J$29 -> 840 | H10: =+JUN!$J$29 -> 840 | I10: =+JUL!$J$29 -> 840 | J10: =+AGO!$J$29 -> 840 | K10: =+SET!$J$29 -> 840 | L10: =+OUT!$J$24 -> Real | M10: =+NOV!$J$27 -> 250 | N10: =+DEZ!$J$28 -> 0 | O10: =SUM(C10:N10) -> 7810
A11: 4 | B11: Saúde | C11: =+JAN!K51 -> 679 | D11: =+FEV!K51 -> 679 | E11: =+MAR!$J$51 -> 0 | F11: =+ABR!$J$51 -> 0 | G11: =+MAI!$J$51 -> 0 | H11: =+JUN!$J$51 -> 0 | I11: =+JUL!$J$51 -> 0 | J11: =+AGO!$J$51 -> 0 | K11: =+SET!$J$51 -> 0 | L11: =+OUT!$J$46 -> 0 | M11: =+NOV!$J$49 -> 0 | N11: =+DEZ!$J$50 -> 0 | O11: =SUM(C11:N11) -> 1358
A12: 7 | B12: Vestuário | C12: =+JAN!K57 -> 39 | D12: =+FEV!$K57 -> 39 | E12: =+MAR!$J$57 -> 0 | F12: =+ABR!$J$57 -> 0 | G12: =+MAI!$J$57 -> 0 | H12: =+JUN!$J$57 -> 0 | I12: =+JUL!$J$57 -> 0 | J12: =+AGO!$J$57 -> 0 | K12: =+SET!$J$57 -> 0 | L12: =+OUT!$J$52 | M12: =+NOV!$J$55 -> 0 | N12: =+DEZ!$J$56 -> 0 | O12: =SUM(C12:N12) -> 78
A13: 3 | B13: Transporte | C13: =+JAN!$P$24 -> 428 | D13: =+FEV!$P$24 -> 428 | E13: =+MAR!$P$24 -> 428 | F13: =+ABR!$P$24 -> 428 | G13: =+MAI!$P$24 -> 428 | H13: =+JUN!$P$24 -> 428 | I13: =+JUL!$P$24 -> 428 | J13: =+AGO!$P$24 -> 428 | K13: =+SET!$P$24 -> 428 | L13: =+OUT!$P$19 -> 0 | M13: =+NOV!$P$22 -> 0 | N13: =+DEZ!$P$23 -> 0 | O13: =SUM(C13:N13) -> 3852
A14: 5 | B14: Educação | C14: =+JAN!Q34 -> 140 | D14: =+FEV!$Q$34 -> 140 | E14: =+MAR!$P$34 -> 0 | F14: =+ABR!$P$34 -> 0 | G14: =+MAI!$P$34 -> 0 | H14: =+JUN!$P$34 -> 0 | I14: =+JUL!$P$34 -> 0 | J14: =+AGO!$P$34 -> 0 | K14: =+SET!$P$34 -> 0 | L14: =+OUT!$P$29 -> 0 | M14: =+NOV!$P$32 -> 0 | N14: =+DEZ!$P$33 -> 0 | O14: =SUM(C14:N14) -> 280
B15: Lazer | C15: =+JAN!Q42 -> 778 | D15: =+FEV!$Q$42 -> 778 | E15: =+MAR!$P$42 -> 0 | F15: =+ABR!$P$42 -> 0 | G15: =+MAI!$P$42 -> 0 | H15: =+JUN!$P$42 -> 0 | I15: =+JUL!$P$42 -> 0 | J15: =+AGO!$P$42 -> 0 | K15: =+SET!$P$42 -> 0 | L15: =+OUT!$P$37 -> 0 | M15: =+NOV!$P$40 -> 0 | N15: =+DEZ!$P$41 -> 0 | O15: =SUM(C15:N15) -> 1556
B16: Artigos Residenciais | C16: =+JAN!Q52 -> 0 | D16: =+FEV!$Q$52 -> 0 | E16: =+MAR!$P$52 -> 0 | F16: =+ABR!$P$52 -> 0 | G16: =+MAI!$P$52 -> 0 | H16: =+JUN!$P$52 -> 0 | I16: =+JUL!$P$52 -> 0 | J16: =+AGO!$P$52 -> 0 | K16: =+SET!$P$52 -> 0 | L16: =+OUT!$P$47 -> 0 | M16: =+NOV!$P$50 -> 0 | N16: =+DEZ!$P$51 -> 0 | O16: =SUM(C16:N16) -> 0
B17: Financeiro | C17: =+JAN!Q67 -> 0 | D17: =+FEV!$P$65 -> 0 | E17: =+MAR!$Q$65 -> 0 | F17: =+ABR!$P$65 -> 0 | G17: =+MAI!$P$65 -> 0 | H17: =+JUN!$P$65 -> 0 | I17: =+JUL!$P$65 -> 0 | J17: =+AGO!$P$65 -> 0 | K17: =+SET!$P$65 -> 0 | L17: =+OUT!$P$60 | M17: =+NOV!$P$63 -> 0 | N17: =+DEZ!$P$64 -> 0 | O17: =SUM(C17:N17) -> 0
B18: Investimentos | C18: =+JAN!K66 -> 5090 | D18: =+FEV!$K$64 -> 4800 | E18: =+MAR!$P$59 -> 0 | F18: =+ABR!$P$59 -> 0 | G18: =+MAI!$P$59 -> 0 | H18: =+JUN!$P$59 -> 0 | I18: =+JUL!$P$59 -> 0 | J18: =+AGO!$P$59 -> 0 | K18: =+SET!$P$59 -> 0 | L18: =+OUT!$P$54 -> Real | M18: =+NOV!$P$57 -> 0 | N18: =+DEZ!$P$58 -> 0 | O18: =SUM(C18:N18) -> 9890
B20: SALDO | C20: =+C4-C8 -> 1079 | D20: =+D4-D8 -> 1079 | E20: =+E4-E8 -> 1079 | F20: =+F4-F8 -> 1079 | G20: =+G4-G8 -> 1079 | H20: =+H4-H8 -> 1079 | I20: =+I4-I8 -> 1079 | J20: =+J4-J8 -> #VALUE! | ... O20: =+O4-O8 -> 8508
B22: INVESTIMENTOS
B23: Poupança | C23: 1200 | O23: =SUM(C23:N23) -> 1200
B24: CDB | C24: 1200 | O24: =SUM(C24:N24) -> 1200
B25: Renda Fixa | C25: 1200 | O25: =SUM(C25:N25) -> 1200
B26: Criptoativos | C26: 1200 | O26: =SUM(C26:N26) -> 1200
B27: FII | C27: 1200 | O27: =SUM(C27:N27) -> 1200
B28: Fundos | C28: 1200 | O28: =SUM(C28:N28) -> 1200
B29: Ações | C29: 1200 | O29: =SUM(C29:N29) -> 1200
B30: Previdência | C30: 1200 | O30: =SUM(C30:N30) -> 1200
B31: Dólar | C31: 1200 | O31: =SUM(C31:N31) -> 1200
B32: Outros | C32: 1200 | O32: =SUM(C32:N32) -> 1200
B33: SALDO | C33: =+C20-SUM(C23:C32) -> -10921 | D33: =+D20-SUM(D23:D32) -> 1079 | E33: =+E20-SUM(E23:E32) -> 1079 | F33: =+F20-SUM(F23:F32) -> 1079 | G33: =+G20-SUM(G23:G32) -> 1079 | H33: =+H20-SUM(H23:H32) -> 1079 | I33: =+I20-SUM(I23:I32) -> 1079 | J33: =+J20-SUM(J23:J32) -> #VALUE! | ... O33: =+O20-SUM(O23:O32) -> -3492
